Workbook
Name APPLICANTS_PER_YEAR: Assumptions!$C$34
Name BASE_CONVERSION: Assumptions!$C$30
Name BASE_RETENTION: Assumptions!$C$29
Name CAP_DOWN: Assumptions!$C$26
Name CAP_UP: Assumptions!$C$25
Name COMMISSION_NB: Assumptions!$C$11
Name COMMISSION_RN: Assumptions!$C$12
Name CONV_CEIL: Assumptions!$C$39
Name CONV_FLOOR: Assumptions!$C$38
Name CURRENT_FLAT: Assumptions!$C$27
Name ELAST_INCREASE: Assumptions!$C$32
Name ELAST_MARKET: Assumptions!$C$31
Name EXPECTED_NB_SHARE: Assumptions!$C$16
Name FIXED_BLENDED: Assumptions!$C$22
Name FIXED_PER_POLICY: Assumptions!$C$14
Name GRAD_CONTINUE: Assumptions!$C$35
Name GROSS_MULT: Assumptions!$C$21
Name LAE_RATIO: Assumptions!$C$8
Name LOSS_TREND: Assumptions!$C$6
Name MARKET_RISK_WEIGHT: Assumptions!$C$33
Name NB_ACQUISITION: Assumptions!$C$15
Name OTHER_VARIABLE: Assumptions!$C$10
Name PERMISSIBLE: Assumptions!$C$19
Name POLICY_FEE: Assumptions!$C$23
Name PREMIUM_TAX: Assumptions!$C$9
Name PROFIT_LOAD: Assumptions!$C$13
Name RET_CEIL: Assumptions!$C$37
Name RET_FLOOR: Assumptions!$C$36
Name TREND_FACTOR: Assumptions!$C$20
Name TREND_YEARS: Assumptions!$C$7
Name VAR_EXPENSE: Assumptions!$C$18

Sheet README
B2: ABG Dormitory Insurance — Pricing, Dislocation & Business Plan
B6: WHAT THIS IS
C7: A working rating and business-plan model. Change any assumption and every table, premium, dislocation figure and pro forma line recalculates.
B9: TAB GUIDE
B10: Assumptions | C10: Every lever. Yellow cells are the ones to edit. It also contains market sensitivity analsyis for the 3 plans with varying price elasticity and competitor behaviour.
B11: ModelOutput | C11: GLM output: base loss costs by tier, and the rating factors. Blue = pasted from Python.
B12: RateBuildup | C12: Loss cost -> premium: trend, claims handling, expenses, profit, policy fee.
B13: QuoteCalc | C13: Pick a student from the dropdowns and watch the premium build up coverage by coverage.
B14: Segments | C14: The engine. All 400 segments, each with its factors, loss cost and indicated premium.
B15: Dislocation | C15: Who pays more, who pays less, and what capping the change costs.
B16: ProFormaA/B/C | C16: Three-year business plan under each strategy. A = keep flat rate, B = new plan with +/-25% caps, C = new plan capping increases only.
B17: PlanCompare | C17: The three plans side by side.
B19: COLOR LEGEND
B20: Blue text | C20: Hardcoded input or model output. Safe to change only if you know the source.
B21: Black text | C21: Formula. Do not overwrite.
B22: Green text | C22: Link to another tab.
B23: Yellow fill | C23: Key assumptions: Edittable Cells
B25: KEY ASSUMPTIONS
C26: 1. Exposure is ONE policy-year per student. Verified: class and GPA are single-valued per student, and the data has no time dimension.
C27: 2. Today's flat premium (CURRENT_FLAT) is NOT given in the case. It defaults to the new plan's own average, which makes the rollout revenue-neutral.
C28: 3. All expense, trend and market figures are cited values
C29: 4. The indicated premium is far above typical renters insurance (~$150-270/yr) because ABG's product is much richer ($150k guest medical vs $1-5k market) and dorm frequency runs high.
B32: PRO FORMA TABS — HOW THE COLUMNS WORK
C33: The three ProForma tabs are identical except for one column (Charged — renewal). Each projects the book forward three years at segment level.
B34: Columns A-J | C34: Segment keys, tier, class adjustment, year-0 student count, and base loss cost all linked from Segments. Column J is the offset 0-4 within the group; every ageing formula switches on it.
B36: YEAR BLOCK — 14 COLUMNS, IN CALCULATION ORDER
B37: Prev premium | C37: What this cohort paid last year. Year 1 = CURRENT_FLAT. Freshmen have no renewals, so theirs is set to the indicated premium.
B38: Loss cost (trended) | C38: Base loss cost inflated to the projection year at LOSS_TREND.
B39: Indicated premium | C39: Loss cost x GROSS_MULT + POLICY_FEE.
B40: Market price | C40: What a competitor would charge: a blend of our indicated premium and a flat price, weighted by MARKET_RISK_WEIGHT.
B41: Charged — renewal | C41: The renewal premium for this year
B42: Retention | C42: Base renewal rate, less a penalty for pricing above market, less a rate-shock penalty for a large increase. Clamped between RET_FLOOR and RET_CEIL.
B43: Conversion | C43: Same shape for new business, but only the market term. A new applicant has no prior premium, so no rate shock applies.
B44: Renewal policies | C44: The ageing engine. Offset 0 (Freshman): zero, nobody ages into Freshman. Offsets 1-3: the row above, i.e. the class below them last year. Offset 4 (Grad): itself, x GRAD_CONTINUE. Seniors never appear as a source — that is how graduation is modelled. Retention is applied after ageing, so it reflects the price at the new class and tier.
B45: New policies | C45: The applicant funnel mirrors the current book's segment mix (segment students / 10,000), scaled to APPLICANTS_PER_YEAR, times conversion. New business enters at its own class, not aged.
B46: Total policies | C46: Renewals + new business.
B47: Avg charged | C47: Policy-weighted blend of what renewals and new business actually paid. This becomes next year's prior premium.
B48: Written premium | C48: Renewals at the capped rate + new business at the indicated rate.
... B50: Expenses | C50: Four terms: renewals x charged x (tax + other + renewal commission), plus new x indicated x (tax + other + NB commission), plus all policies x fixed expense, plus new x acquisition cost. New business is dearer on both counts — this is the new-vs-renewal cost difference the case asks about.
B52: YEARS 2 AND 3
B53: What changes | C53: Only two columns change shape. Prev premium pulls last year's Avg charged from the source row instead of CURRENT_FLAT. Renewal policies draws on last year's Total policies instead of the year-0 student count — this is what compounds the book forward and lets Year 1 new business become Year 2 renewals. Everything else differs only by the trend exponent.
B55: SUMMARY BLOCK (rows 8-18)
B56: How it is built | C56: Each line is a SUM down the matching column for that year. Loss ratio, expense ratio and Combined ratio are then derived from those sums. Combined ratio below 100% means the plan is profitable before investment income.
B57: High-risk share | C57: Share of policies whose expected loss is more than twice the book average. Under the flat plan this climbs every year — low-risk students leave for a cheaper competitor, high-risk students stay. That is adverse selection, and it is the case against doing nothing.

Sheet Assumptions
B2: Assumptions
B3: Yellow cells are inputs. White cells with black text are derived — do not overwrite.
B5: PRICING | F5: MARKET SENSITIVITY: 3-year underwriting profit
B6: Annual loss-cost trend | C6: 0.03 | D6: Placeholder. Source needed (e.g. CPI medical + electronics).
B7: Years: experience mid -> policy mid | C7: 1.5 | D7: Experience period midpoint to first policy year midpoint.
B8: Loss adjustment expense (% of loss) | C8: 0.12 | D8: Claims handling. TX filing gives loss+LAE combined only.
B9: Premium tax (% of premium) | C9: 0.018 | D9: Allstate TX REN filing, Attachment I Exhibit 2: 1.8%. | F9: A. Keep flat rate | G9: Competitors flat | H9: Half risk-based | I9: Fully risk-based
B10: Other variable expense (% of premium) | C10: 0.091 | D10: TX filing: licenses/fees 0.2% + other acq 4.7% + general 4.2%. | F10: =PlanCompare!C10 -> -8687023.9 | G10: 0 | H10: 0.5 | I10: 1
B11: Commission — new business | C11: 0.115 | D11: TX filing Exhibit 2 gives 11.5% blended; NB/RN split is assumed. | F11: 0 | G11: 4030441.9 | H11: 4030441.9 | I11: 4030441.9
B12: Commission — renewal | C12: 0.08 | D12: Assumed lower than new business. | F12: 0.25 | G12: 4030441.9 | H12: -3121800.9 | I12: -8664773.7
B13: Underwriting profit & contingency | C13: 0.077 | D13: TX filing Attachment II p.9 step (15): 7.7%. | F13: 0.5 | G13: 4030441.9 | H13: -8687023.9 | I13: -13253530
B14: Fixed expense ($ per policy-year) | C14: 20 | D14: Overhead / policy admin. Placeholder — filing is % based. | F14: 1 | G14: 4030441.9 | H14: -14723742 | I14: -17245062
B15: Acquisition cost ($ per NEW policy) | C15: 25 | D15: One-time marketing cost. Placeholder.
B16: Expected new-business share of book | C16: 0.4 | D16: Used to blend commission and fixed cost into the filed rate. | F16: B. New plan, +/-25% caps | G16: Competitors flat | H16: Half risk-based | I16: Fully risk-based
B17: DERIVED — do not edit | F17: =PlanCompare!D10 -> 1548746.7 | G17: 0 | H17: 0.5 | I17: 1
B18: Variable expense V | C18: =PREMIUM_TAX+OTHER_VARIABLE+EXPECTED_NB_SHARE*COMMISSION_NB+(1-EXPECTED_NB_SHARE)*COMMISSION_RN -> 0.203 | D18: Tax + other + blended commission. | F18: 0 | G18: 3262189.7 | H18: 3262189.7 | I18: 3262189.7
B19: Permissible loss ratio (1 - V - Q) | C19: =1-VAR_EXPENSE-PROFIT_LOAD -> 0.72 | D19: Share of premium available for loss + LAE. | F19: 0.25 | G19: 2659875 | H19: 2157694.1 | I19: 2282637.2
B20: Trend factor | C20: =(1+LOSS_TREND)^TREND_YEARS -> 1.0453358 | D20: Brings experience losses to the policy period. | F20: 0.5 | G20: 3090664.5 | H20: 1548746.7 | I20: 1786279.6
B21: Gross multiplier | C21: =TREND_FACTOR*(1+LAE_RATIO)/PERMISSIBLE -> 1.626078 | D21: Trend x (1+LAE) / permissible. | F21: 1 | G21: 3777631.2 | H21: 1359203.8 | I21: 1584661.4
B22: Blended fixed cost per policy | C22: =FIXED_PER_POLICY+EXPECTED_NB_SHARE*NB_ACQUISITION -> 30 | D22: Fixed + expected share of acquisition.
B23: Policy fee (flat, per policy) | C23: =FIXED_BLENDED/PERMISSIBLE -> 41.666667 | D23: Fixed Expense/Permissible loss ratio | F23: C. New plan, cap increases only | G23: Competitors flat | H23: Half risk-based | I23: Fully risk-based
B24: TRANSITION | F24: =PlanCompare!E10 -> 540129.12 | G24: 0 | H24: 0.5 | I24: 1
B25: Max renewal increase per year | C25: 0.25 | D25: Capped rate on the way up. | F25: 0 | G25: 1953151.1 | H25: 1953151.1 | I25: 1953151.1
B26: Max renewal decrease per year | C26: 0.25 | D26: Capped rate on the way down. | F26: 0.25 | G26: 1303793.4 | H26: 1013667.8 | I26: 1451655.1
B27: Today's flat premium (per student-year) | C27: =Segments!$AH$1 -> 1426.2298 | D27: NOT GIVEN IN THE CASE. Defaults to the indicated average (revenue-neutral). | F27: 0.5 | G27: 1693070.7 | H27: 540129.12 | I27: 1374062.6
B28: MARKET & RETENTION | F28: 1 | G28: 2416561.7 | H28: 560016.17 | I28: 1381031.4
B29: Base renewal rate at market price | C29: 0.85
B30: Base quote-to-bind rate at market | C30: 0.35 | F30: NEW PLAN (B) MINUS FLAT RATE (A)
B31: Retention drop per +100% vs market | C31: 0.5 | D31: Price elasticity. | F31: Price sensitivity | G31: Competitors flat | H31: Half risk-based | I31: Fully risk-based
B32: Extra retention drop per +100% increase | C32: 0.3 | D32: Rate-shock effect, on top of price-vs-market. | F32: =F18 -> 0 | G32: =G18-G11 -> -768252.19 | H32: =H18-H11 -> -768252.19 | I32: =I18-I11 -> -768252.19
B33: How risk-based competitors are | C33: 0.5 | D33: 0 = competitors charge flat like ABG today; 1 = fully risk-based. | F33: =F19 -> 0.25 | G33: =G19-G12 -> -1370566.9 | H33: =H19-H12 -> 5279495 | I33: =I19-I12 -> 10947411
B34: Applicants per year | C34: 12000 | D34: New-business applicants | F34: =F20 -> 0.5 | G34: =G20-G13 -> -939777.4 | H34: =H20-H13 -> 10235771 | I34: =I20-I13 -> 15039810
B35: Grad students still enrolled next year | C35: 0.5 | D35: Probability of grads being enrolled | F35: =F21 -> 1 | G35: =G21-G14 -> -252810.72 | H35: =H21-H14 -> 16082946 | I35: =I21-I14 -> 18829723
B36: Retention floor | C36: 0.3
B37: Retention ceiling | C37: 0.95 | F37: New plan (B) profitable in | G37: =COUNTIF(G18:I21,">0")&" of 12 scenarios" -> 12 of 12 scenarios
B38: Conversion floor | C38: 0.02 | F38: Flat rate (A) profitable in | G38: =COUNTIF(G11:I14,">0")&" of 12 scenarios" -> 6 of 12 scenarios
B39: Conversion ceiling | C39: 0.9 | F39: Plan C profitable in | G39: =COUNTIF(G25:I28,">0")&" of 12 scenarios" -> 12 of 12 scenarios
F41: Notes: Based on existing assumptions, policyholders are insensitive to price plan A dominates. When competitors charge flat premiums for all policyholders plan A also dominates.

Sheet ModelOutput
B2: Model Output — from the M5 frequency x severity GLM
B3: BLUE = pasted from Python. To change these, refit the model in the notebook and repaste.
B4: Model: Poisson frequency x Gamma severity, GM/Liability capped at $50k per claim, rebalanced and loaded back to uncapped. Fit on all 10,000 students.
B6: BASE LOSS COST BY TIER AND COVERAGE ($ per policy-year)
B7: Base risk profile: | C7: Freshman / Junior / Senior (tier base class), Non-greek, on campus, sprinklered, GPA 2.0-3.0
B8: Tier | C8: Base class | D8: Personal Property | E8: Additional Living Expense | F8: Guest Medical | G8: Liability | H8: Total
B9: Tier 1 | C9: Freshman | D9: 36.175497 | E9: 106.64708 | F9: 123.72648 | G9: 20.551544 | H9: =SUM(D9:G9) -> 287.10061
B10: Tier 2 | C10: Junior | D10: 42.805151 | E10: 126.19162 | F10: 146.40105 | G10: 24.317895 | H10: =SUM(D10:G10) -> 339.71571
B11: Tier 3 | C11: Senior | D11: 40.009437 | E11: 117.94972 | F11: 136.83923 | G11: 22.729632 | H11: =SUM(D11:G11) -> 317.52802
B13: RATING FACTORS (multiplicative, versus the base level within each coverage)
B15: Variable | C15: Level | D15: Personal Property | E15: Additional Living Expense | F15: Guest Medical | G15: Liability | H15: Base level (factor = 1.00)
B16: class_adj | C16: Sophomore | D16: 0.98982624 | E16: 0.98982624 | F16: 0.98982624 | G16: 0.98982624 | H16: Base (Freshman/Junior/Senior)
B17: class_adj | C17: Grad | D17: 1.1906804 | E17: 1.1906804 | F17: 1.1906804 | G17: 1.1906804 | H17: Base (Freshman/Junior/Senior)
B18: greek | C18: Greek | D18: 4.3562312 | E18: 4.3562312 | F18: 4.3562312 | G18: 4.3562312 | H18: Non-greek
B19: dist_band | C19: Off 0-1mi | D19: 1.9771404 | E19: 1.9459582 | F19: 2.5135188 | G19: 3.1684506 | H19: On campus
B20: dist_band | C20: Off 1-3mi | D20: 1.700622 | E20: 1.6738008 | F20: 2.1619837 | G20: 2.7253181 | H20: On campus
B21: dist_band | C21: Off 3-6mi | D21: 1.9507742 | E21: 1.9200078 | F21: 2.4799997 | G21: 3.1261976 | H21: On campus
B22: dist_band | C22: Off 6+mi | D22: 2.2239289 | E22: 2.1888545 | F22: 2.8272586 | G22: 3.5639395 | H22: On campus
B23: spr | C23: No | D23: 1.5400748 | E23: 1.5400748 | F23: 1.5400748 | G23: 1.5400748 | H23: Yes (sprinklered)
B24: gpa_band | C24: <1.0 | D24: 1.121448 | E24: 1.121448 | F24: 1.121448 | G24: 1.121448 | H24: 2.0-3.0
B25: gpa_band | C25: 1.0-2.0 | D25: 1.0176256 | E25: 1.0176256 | F25: 1.0176256 | G25: 1.0176256 | H25: 2.0-3.0
B26: gpa_band | C26: 3.0+ | D26: 0.87654762 | E26: 0.87654762 | F26: 0.87654762 | G26: 0.87654762 | H26: 2.0-3.0

Sheet RateBuildup
B2: Rate Build-up — from loss cost to filed premium
B3: Premium = (loss cost x trend x (1+LAE)) / (1 - V - Q) + policy fee
B5: STEP 1 — EXPENSE AND PROFIT PROVISIONS
B6: Premium tax | C6: =PREMIUM_TAX -> 0.018 | D6: % of premium
B7: Other variable expense | C7: =OTHER_VARIABLE -> 0.091 | D7: Licenses, other acquisition, general expense
B8: Commission (blended NB/RN) | C8: =EXPECTED_NB_SHARE*COMMISSION_NB+(1-EXPECTED_NB_SHARE)*COMMISSION_RN -> 0.094 | D8: Weighted by the expected new book share
B9: Total variable expense V | C9: =VAR_EXPENSE -> 0.203 | D9: Sum of the three above
B10: Underwriting profit & contingency Q | C10: =PROFIT_LOAD -> 0.077 | D10: Target return
B11: Permissible loss ratio (1 - V - Q) | C11: =PERMISSIBLE -> 0.72 | D11: Share of premium left for loss + LAE
B13: STEP 2 — LOSS LOADINGS
B14: Trend factor | C14: =TREND_FACTOR -> 1.0453358 | D14: (1 + annual trend) ^ years
B15: Loss adjustment expense | C15: =LAE_RATIO -> 0.12 | D15: % of loss
B16: Loss cost -> premium multiplier | C16: =GROSS_MULT -> 1.626078 | D16: Trend x (1+LAE) / permissible
B17: Policy fee | C17: =POLICY_FEE -> 41.666667 | D17: Fixed expense / permissible — flat per policy
B19: STEP 3 — GROSS BASE RATES BY TIER AND COVERAGE ($ per policy-year)
B20: Tier | C20: Personal Property | D20: Additional Living Expense | E20: Guest Medical | F20: Liability | G20: Policy fee | H20: Base policy total
B21: Tier 1 | C21: =ModelOutput!$D$9*GROSS_MULT -> 58.824178 | D21: =ModelOutput!$E$9*GROSS_MULT -> 173.41647 | E21: =ModelOutput!$F$9*GROSS_MULT -> 201.18891 | F21: =ModelOutput!$G$9*GROSS_MULT -> 33.418413 | G21: =POLICY_FEE -> 41.666667 | H21: =SUM(C21:G21) -> 508.51464
B22: Tier 2 | C22: =ModelOutput!$D$10*GROSS_MULT -> 69.604512 | D22: =ModelOutput!$E$10*GROSS_MULT -> 205.19741 | E22: =ModelOutput!$F$10*GROSS_MULT -> 238.05952 | F22: =ModelOutput!$G$10*GROSS_MULT -> 39.542793 | G22: =POLICY_FEE -> 41.666667 | H22: =SUM(C22:G22) -> 594.0709
B23: Tier 3 | C23: =ModelOutput!$D$11*GROSS_MULT -> 65.058464 | D23: =ModelOutput!$E$11*GROSS_MULT -> 191.79545 | E23: =ModelOutput!$F$11*GROSS_MULT -> 222.51125 | F23: =ModelOutput!$G$11*GROSS_MULT -> 36.960153 | G23: =POLICY_FEE -> 41.666667 | H23: =SUM(C23:G23) -> 557.99198
B25: These are the rates for the BASE risk in each tier. The factors from the ModelOutput tab then move an individual student up or down

Sheet QuoteCalc
B2: Quote Calculator — price a single student
B5: STUDENT PROFILE
B6: Class | C6: Junior
B7: Greek status | C7: Non-greek
B8: Distance band | C8: On campus
B9: Sprinklered | C9: Yes
B10: GPA band | C10: 3.0+
B12: Tier (derived from class) | C12: =IF(OR($C$6="Freshman",$C$6="Sophomore"),1,IF($C$6="Junior",2,3)) -> 2
B13: Class adjustment | C13: =IF($C$6="Sophomore","Sophomore",IF($C$6="Grad student","Grad","Base")) -> Base
B15: PREMIUM BUILD-UP BY COVERAGE
B16: Step | C16: Source | D16: Personal Property | E16: Additional Living Expense | F16: Guest Medical | G16: Liability | H16: Total
B17: Base loss cost (tier) | C17: ModelOutput | D17: =INDEX(ModelOutput!$D$9:$D$11,MATCH("Tier "&$C$12,ModelOutput!$B$9:$B$11,0)) -> 42.805151 | E17: =INDEX(ModelOutput!$E$9:$E$11,MATCH("Tier "&$C$12,ModelOutput!$B$9:$B$11,0)) -> 126.19162 | F17: =INDEX(ModelOutput!$F$9:$F$11,MATCH("Tier "&$C$12,ModelOutput!$B$9:$B$11,0)) -> 146.40105 | G17: =INDEX(ModelOutput!$G$9:$G$11,MATCH("Tier "&$C$12,ModelOutput!$B$9:$B$11,0)) -> 24.317895
B18: x Class factor | C18: ModelOutput | D18: =IF($C$13="Base",1,INDEX(ModelOutput!$D$16:$D$26,MATCH($C$13,ModelOutput!$C$16:$C$26,0))) -> 1 | E18: =IF($C$13="Base",1,INDEX(ModelOutput!$E$16:$E$26,MATCH($C$13,ModelOutput!$C$16:$C$26,0))) -> 1 | F18: =IF($C$13="Base",1,INDEX(ModelOutput!$F$16:$F$26,MATCH($C$13,ModelOutput!$C$16:$C$26,0))) -> 1 | G18: =IF($C$13="Base",1,INDEX(ModelOutput!$G$16:$G$26,MATCH($C$13,ModelOutput!$C$16:$C$26,0))) -> 1
B19: x Greek factor | C19: ModelOutput | D19: =IF($C$7="Non-greek",1,INDEX(ModelOutput!$D$16:$D$26,MATCH($C$7,ModelOutput!$C$16:$C$26,0))) -> 1 | E19: =IF($C$7="Non-greek",1,INDEX(ModelOutput!$E$16:$E$26,MATCH($C$7,ModelOutput!$C$16:$C$26,0))) -> 1 | F19: =IF($C$7="Non-greek",1,INDEX(ModelOutput!$F$16:$F$26,MATCH($C$7,ModelOutput!$C$16:$C$26,0))) -> 1 | G19: =IF($C$7="Non-greek",1,INDEX(ModelOutput!$G$16:$G$26,MATCH($C$7,ModelOutput!$C$16:$C$26,0))) -> 1
B20: x Distance factor | C20: ModelOutput | D20: =IF($C$8="On campus",1,INDEX(ModelOutput!$D$16:$D$26,MATCH($C$8,ModelOutput!$C$16:$C$26,0))) -> 1 | E20: =IF($C$8="On campus",1,INDEX(ModelOutput!$E$16:$E$26,MATCH($C$8,ModelOutput!$C$16:$C$26,0))) -> 1 | F20: =IF($C$8="On campus",1,INDEX(ModelOutput!$F$16:$F$26,MATCH($C$8,ModelOutput!$C$16:$C$26,0))) -> 1 | G20: =IF($C$8="On campus",1,INDEX(ModelOutput!$G$16:$G$26,MATCH($C$8,ModelOutput!$C$16:$C$26,0))) -> 1
B21: x Sprinkler factor | C21: ModelOutput | D21: =IF($C$9="Yes",1,INDEX(ModelOutput!$D$16:$D$26,MATCH($C$9,ModelOutput!$C$16:$C$26,0))) -> 1 | E21: =IF($C$9="Yes",1,INDEX(ModelOutput!$E$16:$E$26,MATCH($C$9,ModelOutput!$C$16:$C$26,0))) -> 1 | F21: =IF($C$9="Yes",1,INDEX(ModelOutput!$F$16:$F$26,MATCH($C$9,ModelOutput!$C$16:$C$26,0))) -> 1 | G21: =IF($C$9="Yes",1,INDEX(ModelOutput!$G$16:$G$26,MATCH($C$9,ModelOutput!$C$16:$C$26,0))) -> 1
B22: x GPA factor | C22: ModelOutput | D22: =IF($C$10="2.0-3.0",1,INDEX(ModelOutput!$D$16:$D$26,MATCH($C$10,ModelOutput!$C$16:$C$26,0))) -> 0.87654762 | E22: =IF($C$10="2.0-3.0",1,INDEX(ModelOutput!$E$16:$E$26,MATCH($C$10,ModelOutput!$C$16:$C$26,0))) -> 0.87654762 | F22: =IF($C$10="2.0-3.0",1,INDEX(ModelOutput!$F$16:$F$26,MATCH($C$10,ModelOutput!$C$16:$C$26,0))) -> 0.87654762 | G22: =IF($C$10="2.0-3.0",1,INDEX(ModelOutput!$G$16:$G$26,MATCH($C$10,ModelOutput!$C$16:$C$26,0))) -> 0.87654762
B23: Expected loss cost | C23: product of the above | D23: =D17*D18*D19*D20*D21*D22 -> 37.520753 | E23: =E17*E18*E19*E20*E21*E22 -> 110.61296 | F23: =F17*F18*F19*F20*F21*F22 -> 128.32749 | G23: =G17*G18*G19*G20*G21*G22 -> 21.315793 | H23: =SUM(D23:G23) -> 297.777
B24: x Trend / LAE / expense / profit | C24: RateBuildup (Assumptions) | D24: =GROSS_MULT -> 1.626078 | E24: =GROSS_MULT -> 1.626078 | F24: =GROSS_MULT -> 1.626078 | G24: =GROSS_MULT -> 1.626078
B25: Coverage premium | D25: =D23*D24 -> 61.011669 | E25: =E23*E24 -> 179.8653 | F25: =F23*F24 -> 208.67051 | G25: =G23*G24 -> 34.661141 | H25: =SUM(D25:G25) -> 484.20862
B26: + Policy fee | C26: Assumptions | H26: =POLICY_FEE -> 41.666667
B27: TOTAL ANNUAL PREMIUM | H27: =H25+H26 -> 525.87528
B29: COMPARISON TO TODAY
B30: Today's flat premium | H30: =CURRENT_FLAT -> 1426.2298 | I30: Same for every student under the current plan
B31: Change vs today | H31: =H27/CURRENT_FLAT-1 -> -0.63128292 | I31: Positive = this student is underpriced today
B32: Year-1 premium if capped | H32: =MEDIAN(CURRENT_FLAT*(1-CAP_DOWN),H27,CURRENT_FLAT*(1+CAP_UP)) -> 1069.6723
B33: Years to reach indicated | H33: =IF(H27>CURRENT_FLAT,ROUNDUP(LN(H27/CURRENT_FLAT)/LN(1+CAP_UP),0),IF(H27<CURRENT_FLAT,ROUNDUP(LN(H27/CURRENT_FLAT)/LN(1-CAP_DOWN),0),0)) -> 4

Sheet Segments
B1: Segment Engine — all 400 rating cells | AG1: Weighted avg indicated premium | AH1: =SUMPRODUCT($H$5:$H$404,$Z$5:$Z$404)/SUM($H$5:$H$404) -> 1426.2298
B2: Every student belongs to exactly one row. 375 of the 400 combinations occur in the book. Premium here reproduces the Python model exactly — see the check at AG1. | AG2: Total students | AH2: =SUM($H$5:$H$404) -> 10000
AG3: Weighted avg loss cost | AH3: =SUMPRODUCT($H$5:$H$404,$Y$5:$Y$404)/SUM($H$5:$H$404) -> 851.474
A4: Greek | B4: Distance band | C4: Sprinklered | D4: GPA band | E4: Class | F4: Tier | G4: Class adj | H4: Students | I4: F class | J4: F Greek | K4: F sprinkler | L4: F GPA | M4: F dist PP | N4: F dist ALE | O4: F dist GM | P4: F dist LIAB | Q4: Base PP | R4: Base ALE | S4: Base GM | T4: Base LIAB | U4: Loss cost PP | V4: Loss cost ALE | W4: Loss cost GM | X4: Loss cost LIAB | Y4: Loss cost total | Z4: Indicated premium | AA4: Change vs flat | AB4: Capped premium | AC4: Years to indicated | AD4: Model loss cost (Python) | AE4: Check diff | AF4: Years left to graduate | AG4: CHECK: max |Excel - Python| loss cost | AH4: {=SUMPRODUCT(MAX(ABS($AE$5:$AE$404)))} -> 2.8194336e-11
A5: Non-greek | B5: On campus | C5: Yes | D5: <1.0 | E5: Freshman | F5: 1 | G5: Base | H5: 61 | I5: =IF($G5="Base",1,INDEX(ModelOutput!$D$16:$D$26,MATCH($G5,ModelOutput!$C$16:$C$26,0))) -> 1 | J5: =IF($A5="Non-greek",1,INDEX(ModelOutput!$D$16:$D$26,MATCH($A5,ModelOutput!$C$16:$C$26,0))) -> 1 | K5: =IF($C5="Yes",1,INDEX(ModelOutput!$D$16:$D$26,MATCH($C5,ModelOutput!$C$16:$C$26,0))) -> 1 | L5: =IF($D5="2.0-3.0",1,INDEX(ModelOutput!$D$16:$D$26,MATCH($D5,ModelOutput!$C$16:$C$26,0))) -> 1.121448 | M5: =IF($B5="On campus",1,INDEX(ModelOutput!$D$16:$D$26,MATCH($B5,ModelOutput!$C$16:$C$26,0))) -> 1 | N5: =IF($B5="On campus",1,INDEX(ModelOutput!$E$16:$E$26,MATCH($B5,ModelOutput!$C$16:$C$26,0))) -> 1 | O5: =IF($B5="On campus",1,INDEX(ModelOutput!$F$16:$F$26,MATCH($B5,ModelOutput!$C$16:$C$26,0))) -> 1 | P5: =IF($B5="On campus",1,INDEX(ModelOutput!$G$16:$G$26,MATCH($B5,ModelOutput!$C$16:$C$26,0))) -> 1 | Q5: =INDEX(ModelOutput!$D$9:$D$11,MATCH("Tier "&$F5,ModelOutput!$B$9:$B$11,0)) -> 36.175497 | R5: =INDEX(ModelOutput!$E$9:$E$11,MATCH("Tier "&$F5,ModelOutput!$B$9:$B$11,0)) -> 106.64708 | S5: =INDEX(ModelOutput!$F$9:$F$11,MATCH("Tier "&$F5,ModelOutput!$B$9:$B$11,0)) -> 123.72648 | T5: =INDEX(ModelOutput!$G$9:$G$11,MATCH("Tier "&$F5,ModelOutput!$B$9:$B$11,0)) -> 20.551544 | U5: =$Q5*$I5*$J5*$K5*$L5*$M5 -> 40.568939 | V5: =$R5*$I5*$J5*$K5*$L5*$N5 -> 119.59916 | W5: =$S5*$I5*$J5*$K5*$L5*$O5 -> 138.75282 | X5: =$T5*$I5*$J5*$K5*$L5*$P5 -> 23.047488 | Y5: =SUM(U5:X5) -> 321.9684 | Z5: =$Y5*GROSS_MULT+POLICY_FEE -> 565.21239 | AA5: =$Z5/CURRENT_FLAT-1 -> -0.60370173 | AB5: =MEDIAN(CURRENT_FLAT*(1-CAP_DOWN),$Z5,CURRENT_FLAT*(1+CAP_UP)) -> 1069.6723 | AC5: =IF($Z5>CURRENT_FLAT,ROUNDUP(LN($Z5/CURRENT_FLAT)/LN(1+CAP_UP),0),IF($Z5<CURRENT_FLAT,ROUNDUP(LN($Z5/CURRENT_FLAT)/LN(1-CAP_DOWN),0),0)) -> 4 | AD5: 321.9684 | AE5: =$Y5-$AD5 -> -6.2527761e-13 | AF5: =IF($E5="Freshman",4,IF($E5="Sophomore",3,IF($E5="Junior",2,IF($E5="Senior",1,2)))) -> 4
A6: Non-greek | B6: On campus | C6: Yes | D6: <1.0 | E6: Sophomore | F6: 1 | G6: Sophomore | H6: 79 | I6: =IF($G6="Base",1,INDEX(ModelOutput!$D$16:$D$26,MATCH($G6,ModelOutput!$C$16:$C$26,0))) -> 0.98982624 | J6: =IF($A6="Non-greek",1,INDEX(ModelOutput!$D$16:$D$26,MATCH($A6,ModelOutput!$C$16:$C$26,0))) -> 1 | K6: =IF($C6="Yes",1,INDEX(ModelOutput!$D$16:$D$26,MATCH($C6,ModelOutput!$C$16:$C$26,0))) -> 1 | L6: =IF($D6="2.0-3.0",1,INDEX(ModelOutput!$D$16:$D$26,MATCH($D6,ModelOutput!$C$16:$C$26,0))) -> 1.121448 | M6: =IF($B6="On campus",1,INDEX(ModelOutput!$D$16:$D$26,MATCH($B6,ModelOutput!$C$16:$C$26,0))) -> 1 | N6: =IF($B6="On campus",1,INDEX(ModelOutput!$E$16:$E$26,MATCH($B6,ModelOutput!$C$16:$C$26,0))) -> 1 | O6: =IF($B6="On campus",1,INDEX(ModelOutput!$F$16:$F$26,MATCH($B6,ModelOutput!$C$16:$C$26,0))) -> 1 | P6: =IF($B6="On campus",1,INDEX(ModelOutput!$G$16:$G$26,MATCH($B6,ModelOutput!$C$16:$C$26,0))) -> 1 | Q6: =INDEX(ModelOutput!$D$9:$D$11,MATCH("Tier "&$F6,ModelOutput!$B$9:$B$11,0)) -> 36.175497 | R6: =INDEX(ModelOutput!$E$9:$E$11,MATCH("Tier "&$F6,ModelOutput!$B$9:$B$11,0)) -> 106.64708 | S6: =INDEX(ModelOutput!$F$9:$F$11,MATCH("Tier "&$F6,ModelOutput!$B$9:$B$11,0)) -> 123.72648 | T6: =INDEX(ModelOutput!$G$9:$G$11,MATCH("Tier "&$F6,ModelOutput!$B$9:$B$11,0)) -> 20.551544 | U6: =$Q6*$I6*$J6*$K6*$L6*$M6 -> 40.1562 | V6: =$R6*$I6*$J6*$K6*$L6*$N6 -> 118.38239 | W6: =$S6*$I6*$J6*$K6*$L6*$O6 -> 137.34118 | X6: =$T6*$I6*$J6*$K6*$L6*$P6 -> 22.813009 | Y6: =SUM(U6:X6) -> 318.69278 | Z6: =$Y6*GROSS_MULT+POLICY_FEE -> 559.88596 | AA6: =$Z6/CURRENT_FLAT-1 -> -0.60743635 | AB6: =MEDIAN(CURRENT_FLAT*(1-CAP_DOWN),$Z6,CURRENT_FLAT*(1+CAP_UP)) -> 1069.6723 | AC6: =IF($Z6>CURRENT_FLAT,ROUNDUP(LN($Z6/CURRENT_FLAT)/LN(1+CAP_UP),0),IF($Z6<CURRENT_FLAT,ROUNDUP(LN($Z6/CURRENT_FLAT)/LN(1-CAP_DOWN),0),0)) -> 4 | AD6: 318.69278 | AE6: =$Y6-$AD6 -> 0 | AF6: =IF($E6="Freshman",4,IF($E6="Sophomore",3,IF($E6="Junior",2,IF($E6="Senior",1,2)))) -> 3
A7: Non-greek | B7: On campus | C7: Yes | D7: <1.0 | E7: Junior | F7: 2 | G7: Base | H7: 79 | I7: =IF($G7="Base",1,INDEX(ModelOutput!$D$16:$D$26,MATCH($G7,ModelOutput!$C$16:$C$26,0))) -> 1 | J7: =IF($A7="Non-greek",1,INDEX(ModelOutput!$D$16:$D$26,MATCH($A7,ModelOutput!$C$16:$C$26,0))) -> 1 | K7: =IF($C7="Yes",1,INDEX(ModelOutput!$D$16:$D$26,MATCH($C7,ModelOutput!$C$16:$C$26,0))) -> 1 | L7: =IF($D7="2.0-3.0",1,INDEX(ModelOutput!$D$16:$D$26,MATCH($D7,ModelOutput!$C$16:$C$26,0))) -> 1.121448 | M7: =IF($B7="On campus",1,INDEX(ModelOutput!$D$16:$D$26,MATCH($B7,ModelOutput!$C$16:$C$26,0))) -> 1 | N7: =IF($B7="On campus",1,INDEX(ModelOutput!$E$16:$E$26,MATCH($B7,ModelOutput!$C$16:$C$26,0))) -> 1 | O7: =IF($B7="On campus",1,INDEX(ModelOutput!$F$16:$F$26,MATCH($B7,ModelOutput!$C$16:$C$26,0))) -> 1 | P7: =IF($B7="On campus",1,INDEX(ModelOutput!$G$16:$G$26,MATCH($B7,ModelOutput!$C$16:$C$26,0))) -> 1 | Q7: =INDEX(ModelOutput!$D$9:$D$11,MATCH("Tier "&$F7,ModelOutput!$B$9:$B$11,0)) -> 42.805151 | R7: =INDEX(ModelOutput!$E$9:$E$11,MATCH("Tier "&$F7,ModelOutput!$B$9:$B$11,0)) -> 126.19162 | S7: =INDEX(ModelOutput!$F$9:$F$11,MATCH("Tier "&$F7,ModelOutput!$B$9:$B$11,0)) -> 146.40105 | T7: =INDEX(ModelOutput!$G$9:$G$11,MATCH("Tier "&$F7,ModelOutput!$B$9:$B$11,0)) -> 24.317895 | U7: =$Q7*$I7*$J7*$K7*$L7*$M7 -> 48.003751 | V7: =$R7*$I7*$J7*$K7*$L7*$N7 -> 141.51734 | W7: =$S7*$I7*$J7*$K7*$L7*$O7 -> 164.18117 | X7: =$T7*$I7*$J7*$K7*$L7*$P7 -> 27.271255 | Y7: =SUM(U7:X7) -> 380.97351 | Z7: =$Y7*GROSS_MULT+POLICY_FEE -> 661.15929 | AA7: =$Z7/CURRENT_FLAT-1 -> -0.53642863 | AB7: =MEDIAN(CURRENT_FLAT*(1-CAP_DOWN),$Z7,CURRENT_FLAT*(1+CAP_UP)) -> 1069.6723 | AC7: =IF($Z7>CURRENT_FLAT,ROUNDUP(LN($Z7/CURRENT_FLAT)/LN(1+CAP_UP),0),IF($Z7<CURRENT_FLAT,ROUNDUP(LN($Z7/CURRENT_FLAT)/LN(1-CAP_DOWN),0),0)) -> 3 | AD7: 380.97351 | AE7: =$Y7-$AD7 -> 0 | AF7: =IF($E7="Freshman",4,IF($E7="Sophomore",3,IF($E7="Junior",2,IF($E7="Senior",1,2)))) -> 2 | AG7: Years left in school (helper for capping)
A8: Non-greek | B8: On campus | C8: Yes | D8: <1.0 | E8: Senior | F8: 3 | G8: Base | H8: 58 | I8: =IF($G8="Base",1,INDEX(ModelOutput!$D$16:$D$26,MATCH($G8,ModelOutput!$C$16:$C$26,0))) -> 1 | J8: =IF($A8="Non-greek",1,INDEX(ModelOutput!$D$16:$D$26,MATCH($A8,ModelOutput!$C$16:$C$26,0))) -> 1 | K8: =IF($C8="Yes",1,INDEX(ModelOutput!$D$16:$D$26,MATCH($C8,ModelOutput!$C$16:$C$26,0))) -> 1 | L8: =IF($D8="2.0-3.0",1,INDEX(ModelOutput!$D$16:$D$26,MATCH($D8,ModelOutput!$C$16:$C$26,0))) -> 1.121448 | M8: =IF($B8="On campus",1,INDEX(ModelOutput!$D$16:$D$26,MATCH($B8,ModelOutput!$C$16:$C$26,0))) -> 1 | N8: =IF($B8="On campus",1,INDEX(ModelOutput!$E$16:$E$26,MATCH($B8,ModelOutput!$C$16:$C$26,0))) -> 1 | O8: =IF($B8="On campus",1,INDEX(ModelOutput!$F$16:$F$26,MATCH($B8,ModelOutput!$C$16:$C$26,0))) -> 1 | P8: =IF($B8="On campus",1,INDEX(ModelOutput!$G$16:$G$26,MATCH($B8,ModelOutput!$C$16:$C$26,0))) -> 1 | Q8: =INDEX(ModelOutput!$D$9:$D$11,MATCH("Tier "&$F8,ModelOutput!$B$9:$B$11,0)) -> 40.009437 | R8: =INDEX(ModelOutput!$E$9:$E$11,MATCH("Tier "&$F8,ModelOutput!$B$9:$B$11,0)) -> 117.94972 | S8: =INDEX(ModelOutput!$F$9:$F$11,MATCH("Tier "&$F8,ModelOutput!$B$9:$B$11,0)) -> 136.83923 | T8: =INDEX(ModelOutput!$G$9:$G$11,MATCH("Tier "&$F8,ModelOutput!$B$9:$B$11,0)) -> 22.729632 | U8: =$Q8*$I8*$J8*$K8*$L8*$M8 -> 44.868504 | V8: =$R8*$I8*$J8*$K8*$L8*$N8 -> 132.27448 | W8: =$S8*$I8*$J8*$K8*$L8*$O8 -> 153.45808 | X8: =$T8*$I8*$J8*$K8*$L8*$P8 -> 25.4901 | Y8: =SUM(U8:X8) -> 356.09116 | Z8: =$Y8*GROSS_MULT+POLICY_FEE -> 620.69865 | AA8: =$Z8/CURRENT_FLAT-1 -> -0.56479758 | AB8: =MEDIAN(CURRENT_FLAT*(1-CAP_DOWN),$Z8,CURRENT_FLAT*(1+CAP_UP)) -> 1069.6723 | AC8: =IF($Z8>CURRENT_FLAT,ROUNDUP(LN($Z8/CURRENT_FLAT)/LN(1+CAP_UP),0),IF($Z8<CURRENT_FLAT,ROUNDUP(LN($Z8/CURRENT_FLAT)/LN(1-CAP_DOWN),0),0)) -> 3 | AD8: 356.09116 | AE8: =$Y8-$AD8 -> -1.080025e-12 | AF8: =IF($E8="Freshman",4,IF($E8="Sophomore",3,IF($E8="Junior",2,IF($E8="Senior",1,2)))) -> 1
A9: Non-greek | B9: On campus | C9: Yes | D9: <1.0 | E9: Grad student | F9: 3 | G9: Grad | H9: 48 | I9: =IF($G9="Base",1,INDEX(ModelOutput!$D$16:$D$26,MATCH($G9,ModelOutput!$C$16:$C$26,0))) -> 1.1906804 | J9: =IF($A9="Non-greek",1,INDEX(ModelOutput!$D$16:$D$26,MATCH($A9,ModelOutput!$C$16:$C$26,0))) -> 1 | K9: =IF($C9="Yes",1,INDEX(ModelOutput!$D$16:$D$26,MATCH($C9,ModelOutput!$C$16:$C$26,0))) -> 1 | L9: =IF($D9="2.0-3.0",1,INDEX(ModelOutput!$D$16:$D$26,MATCH($D9,ModelOutput!$C$16:$C$26,0))) -> 1.121448 | M9: =IF($B9="On campus",1,INDEX(ModelOutput!$D$16:$D$26,MATCH($B9,ModelOutput!$C$16:$C$26,0))) -> 1 | N9: =IF($B9="On campus",1,INDEX(ModelOutput!$E$16:$E$26,MATCH($B9,ModelOutput!$C$16:$C$26,0))) -> 1 | O9: =IF($B9="On campus",1,INDEX(ModelOutput!$F$16:$F$26,MATCH($B9,ModelOutput!$C$16:$C$26,0))) -> 1 | P9: =IF($B9="On campus",1,INDEX(ModelOutput!$G$16:$G$26,MATCH($B9,ModelOutput!$C$16:$C$26,0))) -> 1 | Q9: =INDEX(ModelOutput!$D$9:$D$11,MATCH("Tier "&$F9,ModelOutput!$B$9:$B$11,0)) -> 40.009437 | R9: =INDEX(ModelOutput!$E$9:$E$11,MATCH("Tier "&$F9,ModelOutput!$B$9:$B$11,0)) -> 117.94972 | S9: =INDEX(ModelOutput!$F$9:$F$11,MATCH("Tier "&$F9,ModelOutput!$B$9:$B$11,0)) -> 136.83923 | T9: =INDEX(ModelOutput!$G$9:$G$11,MATCH("Tier "&$F9,ModelOutput!$B$9:$B$11,0)) -> 22.729632 | U9: =$Q9*$I9*$J9*$K9*$L9*$M9 -> 53.424049 | V9: =$R9*$I9*$J9*$K9*$L9*$N9 -> 157.49664 | W9: =$S9*$I9*$J9*$K9*$L9*$O9 -> 182.71953 | X9: =$T9*$I9*$J9*$K9*$L9*$P9 -> 30.350563 | Y9: =SUM(U9:X9) -> 423.99078 | Z9: =$Y9*GROSS_MULT+POLICY_FEE -> 731.10872 | AA9: =$Z9/CURRENT_FLAT-1 -> -0.48738364 | AB9: =MEDIAN(CURRENT_FLAT*(1-CAP_DOWN),$Z9,CURRENT_FLAT*(1+CAP_UP)) -> 1069.6723 | AC9: =IF($Z9>CURRENT_FLAT,ROUNDUP(LN($Z9/CURRENT_FLAT)/LN(1+CAP_UP),0),IF($Z9<CURRENT_FLAT,ROUNDUP(LN($Z9/CURRENT_FLAT)/LN(1-CAP_DOWN),0),0)) -> 3 | AD9: 423.99078 | AE9: =$Y9-$AD9 -> -1.7053026e-12 | AF9: =IF($E9="Freshman",4,IF($E9="Sophomore",3,IF($E9="Junior",2,IF($E9="Senior",1,2)))) -> 2
A10: Non-greek | B10: On campus | C10: Yes | D10: 1.0-2.0 | E10: Freshman | F10: 1 | G10: Base | H10: 188 | I10: =IF($G10="Base",1,INDEX(ModelOutput!$D$16:$D$26,MATCH($G10,ModelOutput!$C$16:$C$26,0))) -> 1 | J10: =IF($A10="Non-greek",1,INDEX(ModelOutput!$D$16:$D$26,MATCH($A10,ModelOutput!$C$16:$C$26,0))) -> 1 | K10: =IF($C10="Yes",1,INDEX(ModelOutput!$D$16:$D$26,MATCH($C10,ModelOutput!$C$16:$C$26,0))) -> 1 | L10: =IF($D10="2.0-3.0",1,INDEX(ModelOutput!$D$16:$D$26,MATCH($D10,ModelOutput!$C$16:$C$26,0))) -> 1.0176256 | M10: =IF($B10="On campus",1,INDEX(ModelOutput!$D$16:$D$26,MATCH($B10,ModelOutput!$C$16:$C$26,0))) -> 1 | N10: =IF($B10="On campus",1,INDEX(ModelOutput!$E$16:$E$26,MATCH($B10,ModelOutput!$C$16:$C$26,0))) -> 1 | O10: =IF($B10="On campus",1,INDEX(ModelOutput!$F$16:$F$26,MATCH($B10,ModelOutput!$C$16:$C$26,0))) -> 1 | P10: =IF($B10="On campus",1,INDEX(ModelOutput!$G$16:$G$26,MATCH($B10,ModelOutput!$C$16:$C$26,0))) -> 1 | Q10: =INDEX(ModelOutput!$D$9:$D$11,MATCH("Tier "&$F10,ModelOutput!$B$9:$B$11,0)) -> 36.175497 | R10: =INDEX(ModelOutput!$E$9:$E$11,MATCH("Tier "&$F10,ModelOutput!$B$9:$B$11,0)) -> 106.64708 | S10: =INDEX(ModelOutput!$F$9:$F$11,MATCH("Tier "&$F10,ModelOutput!$B$9:$B$11,0)) -> 123.72648 | T10: =INDEX(ModelOutput!$G$9:$G$11,MATCH("Tier "&$F10,ModelOutput!$B$9:$B$11,0)) -> 20.551544 | U10: =$Q10*$I10*$J10*$K10*$L10*$M10 -> 36.81311 | V10: =$R10*$I10*$J10*$K10*$L10*$N10 -> 108.5268 | W10: =$S10*$I10*$J10*$K10*$L10*$O10 -> 125.90723 | X10: =$T10*$I10*$J10*$K10*$L10*$P10 -> 20.913777 | Y10: =SUM(U10:X10) -> 292.16092 | Z10: =$Y10*GROSS_MULT+POLICY_FEE -> 516.7431 | AA10: =$Z10/CURRENT_FLAT-1 -> -0.63768594 | AB10: =MEDIAN(CURRENT_FLAT*(1-CAP_DOWN),$Z10,CURRENT_FLAT*(1+CAP_UP)) -> 1069.6723 | AC10: =IF($Z10>CURRENT_FLAT,ROUNDUP(LN($Z10/CURRENT_FLAT)/LN(1+CAP_UP),0),IF($Z10<CURRENT_FLAT,ROUNDUP(LN($Z10/CURRENT_FLAT)/LN(1-CAP_DOWN),0),0)) -> 4 | AD10: 292.16092 | AE10: =$Y10-$AD10 -> 4.5474735e-13 | AF10: =IF($E10="Freshman",4,IF($E10="Sophomore",3,IF($E10="Junior",2,IF($E10="Senior",1,2)))) -> 4
A11: Non-greek | B11: On campus | C11: Yes | D11: 1.0-2.0 | E11: Sophomore | F11: 1 | G11: Sophomore | H11: 216 | I11: =IF($G11="Base",1,INDEX(ModelOutput!$D$16:$D$26,MATCH($G11,ModelOutput!$C$16:$C$26,0))) -> 0.98982624 | J11: =IF($A11="Non-greek",1,INDEX(ModelOutput!$D$16:$D$26,MATCH($A11,ModelOutput!$C$16:$C$26,0))) -> 1 | K11: =IF($C11="Yes",1,INDEX(ModelOutput!$D$16:$D$26,MATCH($C11,ModelOutput!$C$16:$C$26,0))) -> 1 | L11: =IF($D11="2.0-3.0",1,INDEX(ModelOutput!$D$16:$D$26,MATCH($D11,ModelOutput!$C$16:$C$26,0))) -> 1.0176256 | M11: =IF($B11="On campus",1,INDEX(ModelOutput!$D$16:$D$26,MATCH($B11,ModelOutput!$C$16:$C$26,0))) -> 1 | N11: =IF($B11="On campus",1,INDEX(ModelOutput!$E$16:$E$26,MATCH($B11,ModelOutput!$C$16:$C$26,0))) -> 1 | O11: =IF($B11="On campus",1,INDEX(ModelOutput!$F$16:$F$26,MATCH($B11,ModelOutput!$C$16:$C$26,0))) -> 1 | P11: =IF($B11="On campus",1,INDEX(ModelOutput!$G$16:$G$26,MATCH($B11,ModelOutput!$C$16:$C$26,0))) -> 1 | Q11: =INDEX(ModelOutput!$D$9:$D$11,MATCH("Tier "&$F11,ModelOutput!$B$9:$B$11,0)) -> 36.175497 | R11: =INDEX(ModelOutput!$E$9:$E$11,MATCH("Tier "&$F11,ModelOutput!$B$9:$B$11,0)) -> 106.64708 | S11: =INDEX(ModelOutput!$F$9:$F$11,MATCH("Tier "&$F11,ModelOutput!$B$9:$B$11,0)) -> 123.72648 | T11: =INDEX(ModelOutput!$G$9:$G$11,MATCH("Tier "&$F11,ModelOutput!$B$9:$B$11,0)) -> 20.551544 | U11: =$Q11*$I11*$J11*$K11*$L11*$M11 -> 36.438583 | V11: =$R11*$I11*$J11*$K11*$L11*$N11 -> 107.42267 | W11: =$S11*$I11*$J11*$K11*$L11*$O11 -> 124.62628 | X11: =$T11*$I11*$J11*$K11*$L11*$P11 -> 20.701005 | Y11: =SUM(U11:X11) -> 289.18854 | Z11: =$Y11*GROSS_MULT+POLICY_FEE -> 511.90978 | AA11: =$Z11/CURRENT_FLAT-1 -> -0.64107482 | AB11: =MEDIAN(CURRENT_FLAT*(1-CAP_DOWN),$Z11,CURRENT_FLAT*(1+CAP_UP)) -> 1069.6723 | AC11: =IF($Z11>CURRENT_FLAT,ROUNDUP(LN($Z11/CURRENT_FLAT)/LN(1+CAP_UP),0),IF($Z11<CURRENT_FLAT,ROUNDUP(LN($Z11/CURRENT_FLAT)/LN(1-CAP_DOWN),0),0)) -> 4 | AD11: 289.18854 | AE11: =$Y11-$AD11 -> 0 | AF11: =IF($E11="Freshman",4,IF($E11="Sophomore",3,IF($E11="Junior",2,IF($E11="Senior",1,2)))) -> 3
A12: Non-greek | B12: On campus | C12: Yes | D12: 1.0-2.0 | E12: Junior | F12: 2 | G12: Base | H12: 194 | I12: =IF($G12="Base",1,INDEX(ModelOutput!$D$16:$D$26,MATCH($G12,ModelOutput!$C$16:$C$26,0))) -> 1 | J12: =IF($A12="Non-greek",1,INDEX(ModelOutput!$D$16:$D$26,MATCH($A12,ModelOutput!$C$16:$C$26,0))) -> 1 | K12: =IF($C12="Yes",1,INDEX(ModelOutput!$D$16:$D$26,MATCH($C12,ModelOutput!$C$16:$C$26,0))) -> 1 | L12: =IF($D12="2.0-3.0",1,INDEX(ModelOutput!$D$16:$D$26,MATCH($D12,ModelOutput!$C$16:$C$26,0))) -> 1.0176256 | M12: =IF($B12="On campus",1,INDEX(ModelOutput!$D$16:$D$26,MATCH($B12,ModelOutput!$C$16:$C$26,0))) -> 1 | N12: =IF($B12="On campus",1,INDEX(ModelOutput!$E$16:$E$26,MATCH($B12,ModelOutput!$C$16:$C$26,0))) -> 1 | O12: =IF($B12="On campus",1,INDEX(ModelOutput!$F$16:$F$26,MATCH($B12,ModelOutput!$C$16:$C$26,0))) -> 1 | P12: =IF($B12="On campus",1,INDEX(ModelOutput!$G$16:$G$26,MATCH($B12,ModelOutput!$C$16:$C$26,0))) -> 1 | Q12: =INDEX(ModelOutput!$D$9:$D$11,MATCH("Tier "&$F12,ModelOutput!$B$9:$B$11,0)) -> 42.805151 | R12: =INDEX(ModelOutput!$E$9:$E$11,MATCH("Tier "&$F12,ModelOutput!$B$9:$B$11,0)) -> 126.19162 | S12: =INDEX(ModelOutput!$F$9:$F$11,MATCH("Tier "&$F12,ModelOutput!$B$9:$B$11,0)) -> 146.40105 | T12: =INDEX(ModelOutput!$G$9:$G$11,MATCH("Tier "&$F12,ModelOutput!$B$9:$B$11,0)) -> 24.317895 | U12: =$Q12*$I12*$J12*$K12*$L12*$M12 -> 43.559615 | V12: =$R12*$I12*$J12*$K12*$L12*$N12 -> 128.41582 | W12: =$S12*$I12*$J12*$K12*$L12*$O12 -> 148.98145 | X12: =$T12*$I12*$J12*$K12*$L12*$P12 -> 24.746512 | Y12: =SUM(U12:X12) -> 345.70339 | Z12: =$Y12*GROSS_MULT+POLICY_FEE -> 603.80734 | AA12: =$Z12/CURRENT_FLAT-1 -> -0.57664091 | AB12: =MEDIAN(CURRENT_FLAT*(1-CAP_DOWN),$Z12,CURRENT_FLAT*(1+CAP_UP)) -> 1069.6723 | AC12: =IF($Z12>CURRENT_FLAT,ROUNDUP(LN($Z12/CURRENT_FLAT)/LN(1+CAP_UP),0),IF($Z12<CURRENT_FLAT,ROUNDUP(LN($Z12/CURRENT_FLAT)/LN(1-CAP_DOWN),0),0)) -> 3 | AD12: 345.70339 | AE12: =$Y12-$AD12 -> -5.6843419e-13 | AF12: =IF($E12="Freshman",4,IF($E12="Sophomore",3,IF($E12="Junior",2,IF($E12="Senior",1,2)))) -> 2
A13: Non-greek | B13: On campus | C13: Yes | D13: 1.0-2.0 | E13: Senior | F13: 3 | G13: Base | H13: 209 | I13: =IF($G13="Base",1,INDEX(ModelOutput!$D$16:$D$26,MATCH($G13,ModelOutput!$C$16:$C$26,0))) -> 1 | J13: =IF($A13="Non-greek",1,INDEX(ModelOutput!$D$16:$D$26,MATCH($A13,ModelOutput!$C$16:$C$26,0))) -> 1 | K13: =IF($C13="Yes",1,INDEX(ModelOutput!$D$16:$D$26,MATCH($C13,ModelOutput!$C$16:$C$26,0))) -> 1 | L13: =IF($D13="2.0-3.0",1,INDEX(ModelOutput!$D$16:$D$26,MATCH($D13,ModelOutput!$C$16:$C$26,0))) -> 1.0176256 | M13: =IF($B13="On campus",1,INDEX(ModelOutput!$D$16:$D$26,MATCH($B13,ModelOutput!$C$16:$C$26,0))) -> 1 | N13: =IF($B13="On campus",1,INDEX(ModelOutput!$E$16:$E$26,MATCH($B13,ModelOutput!$C$16:$C$26,0))) -> 1 | O13: =IF($B13="On campus",1,INDEX(ModelOutput!$F$16:$F$26,MATCH($B13,ModelOutput!$C$16:$C$26,0))) -> 1 | P13: =IF($B13="On campus",1,INDEX(ModelOutput!$G$16:$G$26,MATCH($B13,ModelOutput!$C$16:$C$26,0))) -> 1 | Q13: =INDEX(ModelOutput!$D$9:$D$11,MATCH("Tier "&$F13,ModelOutput!$B$9:$B$11,0)) -> 40.009437 | R13: =INDEX(ModelOutput!$E$9:$E$11,MATCH("Tier "&$F13,ModelOutput!$B$9:$B$11,0)) -> 117.94972 | S13: =INDEX(ModelOutput!$F$9:$F$11,MATCH("Tier "&$F13,ModelOutput!$B$9:$B$11,0)) -> 136.83923 | T13: =INDEX(ModelOutput!$G$9:$G$11,MATCH("Tier "&$F13,ModelOutput!$B$9:$B$11,0)) -> 22.729632 | U13: =$Q13*$I13*$J13*$K13*$L13*$M13 -> 40.714626 | V13: =$R13*$I13*$J13*$K13*$L13*$N13 -> 120.02865 | W13: =$S13*$I13*$J13*$K13*$L13*$O13 -> 139.25109 | X13: =$T13*$I13*$J13*$K13*$L13*$P13 -> 23.130254 | Y13: =SUM(U13:X13) -> 323.12463 | Z13: =$Y13*GROSS_MULT+POLICY_FEE -> 567.0925 | AA13: =$Z13/CURRENT_FLAT-1 -> -0.60238349 | AB13: =MEDIAN(CURRENT_FLAT*(1-CAP_DOWN),$Z13,CURRENT_FLAT*(1+CAP_UP)) -> 1069.6723 | AC13: =IF($Z13>CURRENT_FLAT,ROUNDUP(LN($Z13/CURRENT_FLAT)/LN(1+CAP_UP),0),IF($Z13<CURRENT_FLAT,ROUNDUP(LN($Z13/CURRENT_FLAT)/LN(1-CAP_DOWN),0),0)) -> 4 | AD13: 323.12463 | AE13: =$Y13-$AD13 -> -1.1368684e-12 | AF13: =IF($E13="Freshman",4,IF($E13="Sophomore",3,IF($E13="Junior",2,IF($E13="Senior",1,2)))) -> 1
A14: Non-greek | B14: On campus | C14: Yes | D14: 1.0-2.0 | E14: Grad student | F14: 3 | G14: Grad | H14: 113 | I14: =IF($G14="Base",1,INDEX(ModelOutput!$D$16:$D$26,MATCH($G14,ModelOutput!$C$16:$C$26,0))) -> 1.1906804 | J14: =IF($A14="Non-greek",1,INDEX(ModelOutput!$D$16:$D$26,MATCH($A14,ModelOutput!$C$16:$C$26,0))) -> 1 | K14: =IF($C14="Yes",1,INDEX(ModelOutput!$D$16:$D$26,MATCH($C14,ModelOutput!$C$16:$C$26,0))) -> 1 | L14: =IF($D14="2.0-3.0",1,INDEX(ModelOutput!$D$16:$D$26,MATCH($D14,ModelOutput!$C$16:$C$26,0))) -> 1.0176256 | M14: =IF($B14="On campus",1,INDEX(ModelOutput!$D$16:$D$26,MATCH($B14,ModelOutput!$C$16:$C$26,0))) -> 1 | N14: =IF($B14="On campus",1,INDEX(ModelOutput!$E$16:$E$26,MATCH($B14,ModelOutput!$C$16:$C$26,0))) -> 1 | O14: =IF($B14="On campus",1,INDEX(ModelOutput!$F$16:$F$26,MATCH($B14,ModelOutput!$C$16:$C$26,0))) -> 1 | P14: =IF($B14="On campus",1,INDEX(ModelOutput!$G$16:$G$26,MATCH($B14,ModelOutput!$C$16:$C$26,0))) -> 1 | Q14: =INDEX(ModelOutput!$D$9:$D$11,MATCH("Tier "&$F14,ModelOutput!$B$9:$B$11,0)) -> 40.009437 | R14: =INDEX(ModelOutput!$E$9:$E$11,MATCH("Tier "&$F14,ModelOutput!$B$9:$B$11,0)) -> 117.94972 | S14: =INDEX(ModelOutput!$F$9:$F$11,MATCH("Tier "&$F14,ModelOutput!$B$9:$B$11,0)) -> 136.83923 | T14: =INDEX(ModelOutput!$G$9:$G$11,MATCH("Tier "&$F14,ModelOutput!$B$9:$B$11,0)) -> 22.729632 | U14: =$Q14*$I14*$J14*$K14*$L14*$M14 -> 48.478108 | V14: =$R14*$I14*$J14*$K14*$L14*$N14 -> 142.91577 | W14: =$S14*$I14*$J14*$K14*$L14*$O14 -> 165.80355 | X14: =$T14*$I14*$J14*$K14*$L14*$P14 -> 27.540741 | Y14: =SUM(U14:X14) -> 384.73817 | Z14: =$Y14*GROSS_MULT+POLICY_FEE -> 667.28092 | AA14: =$Z14/CURRENT_FLAT-1 -> -0.53213645 | AB14: =MEDIAN(CURRENT_FLAT*(1-CAP_DOWN),$Z14,CURRENT_FLAT*(1+CAP_UP)) -> 1069.6723 | AC14: =IF($Z14>CURRENT_FLAT,ROUNDUP(LN($Z14/CURRENT_FLAT)/LN(1+CAP_UP),0),IF($Z14<CURRENT_FLAT,ROUNDUP(LN($Z14/CURRENT_FLAT)/LN(1-CAP_DOWN),0),0)) -> 3 | AD14: 384.73817 | AE14: =$Y14-$AD14 -> -7.3896445e-13 | AF14: =IF($E14="Freshman",4,IF($E14="Sophomore",3,IF($E14="Junior",2,IF($E14="Senior",1,2)))) -> 2
A15: Non-greek | B15: On campus | C15: Yes | D15: 2.0-3.0 | E15: Freshman | F15: 1 | G15: Base | H15: 348 | I15: =IF($G15="Base",1,INDEX(ModelOutput!$D$16:$D$26,MATCH($G15,ModelOutput!$C$16:$C$26,0))) -> 1 | J15: =IF($A15="Non-greek",1,INDEX(ModelOutput!$D$16:$D$26,MATCH($A15,ModelOutput!$C$16:$C$26,0))) -> 1 | K15: =IF($C15="Yes",1,INDEX(ModelOutput!$D$16:$D$26,MATCH($C15,ModelOutput!$C$16:$C$26,0))) -> 1 | L15: =IF($D15="2.0-3.0",1,INDEX(ModelOutput!$D$16:$D$26,MATCH($D15,ModelOutput!$C$16:$C$26,0))) -> 1 | M15: =IF($B15="On campus",1,INDEX(ModelOutput!$D$16:$D$26,MATCH($B15,ModelOutput!$C$16:$C$26,0))) -> 1 | N15: =IF($B15="On campus",1,INDEX(ModelOutput!$E$16:$E$26,MATCH($B15,ModelOutput!$C$16:$C$26,0))) -> 1 | O15: =IF($B15="On campus",1,INDEX(ModelOutput!$F$16:$F$26,MATCH($B15,ModelOutput!$C$16:$C$26,0))) -> 1 | P15: =IF($B15="On campus",1,INDEX(ModelOutput!$G$16:$G$26,MATCH($B15,ModelOutput!$C$16:$C$26,0))) -> 1 | Q15: =INDEX(ModelOutput!$D$9:$D$11,MATCH("Tier "&$F15,ModelOutput!$B$9:$B$11,0)) -> 36.175497 | R15: =INDEX(ModelOutput!$E$9:$E$11,MATCH("Tier "&$F15,ModelOutput!$B$9:$B$11,0)) -> 106.64708 | S15: =INDEX(ModelOutput!$F$9:$F$11,MATCH("Tier "&$F15,ModelOutput!$B$9:$B$11,0)) -> 123.72648 | T15: =INDEX(ModelOutput!$G$9:$G$11,MATCH("Tier "&$F15,ModelOutput!$B$9:$B$11,0)) -> 20.551544 | U15: =$Q15*$I15*$J15*$K15*$L15*$M15 -> 36.175497 | V15: =$R15*$I15*$J15*$K15*$L15*$N15 -> 106.64708 | W15: =$S15*$I15*$J15*$K15*$L15*$O15 -> 123.72648 | X15: =$T15*$I15*$J15*$K15*$L15*$P15 -> 20.551544 | Y15: =SUM(U15:X15) -> 287.10061 | Z15: =$Y15*GROSS_MULT+POLICY_FEE -> 508.51464 | AA15: =$Z15/CURRENT_FLAT-1 -> -0.64345532 | AB15: =MEDIAN(CURRENT_FLAT*(1-CAP_DOWN),$Z15,CURRENT_FLAT*(1+CAP_UP)) -> 1069.6723 | AC15: =IF($Z15>CURRENT_FLAT,ROUNDUP(LN($Z15/CURRENT_FLAT)/LN(1+CAP_UP),0),IF($Z15<CURRENT_FLAT,ROUNDUP(LN($Z15/CURRENT_FLAT)/LN(1-CAP_DOWN),0),0)) -> 4 | AD15: 287.10061 | AE15: =$Y15-$AD15 -> 7.9580786e-13 | AF15: =IF($E15="Freshman",4,IF($E15="Sophomore",3,IF($E15="Junior",2,IF($E15="Senior",1,2)))) -> 4
A16: Non-greek | B16: On campus | C16: Yes | D16: 2.0-3.0 | E16: Sophomore | F16: 1 | G16: Sophomore | H16: 328 | I16: =IF($G16="Base",1,INDEX(ModelOutput!$D$16:$D$26,MATCH($G16,ModelOutput!$C$16:$C$26,0))) -> 0.98982624 | J16: =IF($A16="Non-greek",1,INDEX(ModelOutput!$D$16:$D$26,MATCH($A16,ModelOutput!$C$16:$C$26,0))) -> 1 | K16: =IF($C16="Yes",1,INDEX(ModelOutput!$D$16:$D$26,MATCH($C16,ModelOutput!$C$16:$C$26,0))) -> 1 | L16: =IF($D16="2.0-3.0",1,INDEX(ModelOutput!$D$16:$D$26,MATCH($D16,ModelOutput!$C$16:$C$26,0))) -> 1 | M16: =IF($B16="On campus",1,INDEX(ModelOutput!$D$16:$D$26,MATCH($B16,ModelOutput!$C$16:$C$26,0))) -> 1 | N16: =IF($B16="On campus",1,INDEX(ModelOutput!$E$16:$E$26,MATCH($B16,ModelOutput!$C$16:$C$26,0))) -> 1 | O16: =IF($B16="On campus",1,INDEX(ModelOutput!$F$16:$F$26,MATCH($B16,ModelOutput!$C$16:$C$26,0))) -> 1 | P16: =IF($B16="On campus",1,INDEX(ModelOutput!$G$16:$G$26,MATCH($B16,ModelOutput!$C$16:$C$26,0))) -> 1 | Q16: =INDEX(ModelOutput!$D$9:$D$11,MATCH("Tier "&$F16,ModelOutput!$B$9:$B$11,0)) -> 36.175497 | R16: =INDEX(ModelOutput!$E$9:$E$11,MATCH("Tier "&$F16,ModelOutput!$B$9:$B$11,0)) -> 106.64708 | S16: =INDEX(ModelOutput!$F$9:$F$11,MATCH("Tier "&$F16,ModelOutput!$B$9:$B$11,0)) -> 123.72648 | T16: =INDEX(ModelOutput!$G$9:$G$11,MATCH("Tier "&$F16,ModelOutput!$B$9:$B$11,0)) -> 20.551544 | U16: =$Q16*$I16*$J16*$K16*$L16*$M16 -> 35.807456 | V16: =$R16*$I16*$J16*$K16*$L16*$N16 -> 105.56208 | W16: =$S16*$I16*$J16*$K16*$L16*$O16 -> 122.46772 | X16: =$T16*$I16*$J16*$K16*$L16*$P16 -> 20.342458 | Y16: =SUM(U16:X16) -> 284.17972 | Z16: =$Y16*GROSS_MULT+POLICY_FEE -> 503.76504 | AA16: =$Z16/CURRENT_FLAT-1 -> -0.6467855 | AB16: =MEDIAN(CURRENT_FLAT*(1-CAP_DOWN),$Z16,CURRENT_FLAT*(1+CAP_UP)) -> 1069.6723 | AC16: =IF($Z16>CURRENT_FLAT,ROUNDUP(LN($Z16/CURRENT_FLAT)/LN(1+CAP_UP),0),IF($Z16<CURRENT_FLAT,ROUNDUP(LN($Z16/CURRENT_FLAT)/LN(1-CAP_DOWN),0),0)) -> 4 | AD16: 284.17972 | AE16: =$Y16-$AD16 -> 7.3896445e-13 | AF16: =IF($E16="Freshman",4,IF($E16="Sophomore",3,IF($E16="Junior",2,IF($E16="Senior",1,2)))) -> 3
A17: Non-greek | B17: On campus | C17: Yes | D17: 2.0-3.0 | E17: Junior | F17: 2 | G17: Base | H17: 358 | I17: =IF($G17="Base",1,INDEX(ModelOutput!$D$16:$D$26,MATCH($G17,ModelOutput!$C$16:$C$26,0))) -> 1 | J17: =IF($A17="Non-greek",1,INDEX(ModelOutput!$D$16:$D$26,MATCH($A17,ModelOutput!$C$16:$C$26,0))) -> 1 | K17: =IF($C17="Yes",1,INDEX(ModelOutput!$D$16:$D$26,MATCH($C17,ModelOutput!$C$16:$C$26,0))) -> 1 | L17: =IF($D17="2.0-3.0",1,INDEX(ModelOutput!$D$16:$D$26,MATCH($D17,ModelOutput!$C$16:$C$26,0))) -> 1 | M17: =IF($B17="On campus",1,INDEX(ModelOutput!$D$16:$D$26,MATCH($B17,ModelOutput!$C$16:$C$26,0))) -> 1 | N17: =IF($B17="On campus",1,INDEX(ModelOutput!$E$16:$E$26,MATCH($B17,ModelOutput!$C$16:$C$26,0))) -> 1 | O17: =IF($B17="On campus",1,INDEX(ModelOutput!$F$16:$F$26,MATCH($B17,ModelOutput!$C$16:$C$26,0))) -> 1 | P17: =IF($B17="On campus",1,INDEX(ModelOutput!$G$16:$G$26,MATCH($B17,ModelOutput!$C$16:$C$26,0))) -> 1 | Q17: =INDEX(ModelOutput!$D$9:$D$11,MATCH("Tier "&$F17,ModelOutput!$B$9:$B$11,0)) -> 42.805151 | R17: =INDEX(ModelOutput!$E$9:$E$11,MATCH("Tier "&$F17,ModelOutput!$B$9:$B$11,0)) -> 126.19162 | S17: =INDEX(ModelOutput!$F$9:$F$11,MATCH("Tier "&$F17,ModelOutput!$B$9:$B$11,0)) -> 146.40105 | T17: =INDEX(ModelOutput!$G$9:$G$11,MATCH("Tier "&$F17,ModelOutput!$B$9:$B$11,0)) -> 24.317895 | U17: =$Q17*$I17*$J17*$K17*$L17*$M17 -> 42.805151 | V17: =$R17*$I17*$J17*$K17*$L17*$N17 -> 126.19162 | W17: =$S17*$I17*$J17*$K17*$L17*$O17 -> 146.40105 | X17: =$T17*$I17*$J17*$K17*$L17*$P17 -> 24.317895 | Y17: =SUM(U17:X17) -> 339.71571 | Z17: =$Y17*GROSS_MULT+POLICY_FEE -> 594.0709 | AA17: =$Z17/CURRENT_FLAT-1 -> -0.58346761 | AB17: =MEDIAN(CURRENT_FLAT*(1-CAP_DOWN),$Z17,CURRENT_FLAT*(1+CAP_UP)) -> 1069.6723 | AC17: =IF($Z17>CURRENT_FLAT,ROUNDUP(LN($Z17/CURRENT_FLAT)/LN(1+CAP_UP),0),IF($Z17<CURRENT_FLAT,ROUNDUP(LN($Z17/CURRENT_FLAT)/LN(1-CAP_DOWN),0),0)) -> 4 | AD17: 339.71571 | AE17: =$Y17-$AD17 -> 0 | AF17: =IF($E17="Freshman",4,IF($E17="Sophomore",3,IF($E17="Junior",2,IF($E17="Senior",1,2)))) -> 2
A18: Non-greek | B18: On campus | C18: Yes | D18: 2.0-3.0 | E18: Senior | F18: 3 | G18: Base | H18: 343 | I18: =IF($G18="Base",1,INDEX(ModelOutput!$D$16:$D$26,MATCH($G18,ModelOutput!$C$16:$C$26,0))) -> 1 | J18: =IF($A18="Non-greek",1,INDEX(ModelOutput!$D$16:$D$26,MATCH($A18,ModelOutput!$C$16:$C$26,0))) -> 1 | K18: =IF($C18="Yes",1,INDEX(ModelOutput!$D$16:$D$26,MATCH($C18,ModelOutput!$C$16:$C$26,0))) -> 1 | L18: =IF($D18="2.0-3.0",1,INDEX(ModelOutput!$D$16:$D$26,MATCH($D18,ModelOutput!$C$16:$C$26,0))) -> 1 | M18: =IF($B18="On campus",1,INDEX(ModelOutput!$D$16:$D$26,MATCH($B18,ModelOutput!$C$16:$C$26,0))) -> 1 | N18: =IF($B18="On campus",1,INDEX(ModelOutput!$E$16:$E$26,MATCH($B18,ModelOutput!$C$16:$C$26,0))) -> 1 | O18: =IF($B18="On campus",1,INDEX(ModelOutput!$F$16:$F$26,MATCH($B18,ModelOutput!$C$16:$C$26,0))) -> 1 | P18: =IF($B18="On campus",1,INDEX(ModelOutput!$G$16:$G$26,MATCH($B18,ModelOutput!$C$16:$C$26,0))) -> 1 | Q18: =INDEX(ModelOutput!$D$9:$D$11,MATCH("Tier "&$F18,ModelOutput!$B$9:$B$11,0)) -> 40.009437 | R18: =INDEX(ModelOutput!$E$9:$E$11,MATCH("Tier "&$F18,ModelOutput!$B$9:$B$11,0)) -> 117.94972 | S18: =INDEX(ModelOutput!$F$9:$F$11,MATCH("Tier "&$F18,ModelOutput!$B$9:$B$11,0)) -> 136.83923 | T18: =INDEX(ModelOutput!$G$9:$G$11,MATCH("Tier "&$F18,ModelOutput!$B$9:$B$11,0)) -> 22.729632 | U18: =$Q18*$I18*$J18*$K18*$L18*$M18 -> 40.009437 | V18: =$R18*$I18*$J18*$K18*$L18*$N18 -> 117.94972 | W18: =$S18*$I18*$J18*$K18*$L18*$O18 -> 136.83923 | X18: =$T18*$I18*$J18*$K18*$L18*$P18 -> 22.729632 | Y18: =SUM(U18:X18) -> 317.52802 | Z18: =$Y18*GROSS_MULT+POLICY_FEE -> 557.99198 | AA18: =$Z18/CURRENT_FLAT-1 -> -0.60876432 | AB18: =MEDIAN(CURRENT_FLAT*(1-CAP_DOWN),$Z18,CURRENT_FLAT*(1+CAP_UP)) -> 1069.6723 | AC18: =IF($Z18>CURRENT_FLAT,ROUNDUP(LN($Z18/CURRENT_FLAT)/LN(1+CAP_UP),0),IF($Z18<CURRENT_FLAT,ROUNDUP(LN($Z18/CURRENT_FLAT)/LN(1-CAP_DOWN),0),0)) -> 4 | AD18: 317.52802 | AE18: =$Y18-$AD18 -> -1.0231815e-12 | AF18: =IF($E18="Freshman",4,IF($E18="Sophomore",3,IF($E18="Junior",2,IF($E18="Senior",1,2)))) -> 1
A19: Non-greek | B19: On campus | C19: Yes | D19: 2.0-3.0 | E19: Grad student | F19: 3 | G19: Grad | H19: 146 | I19: =IF($G19="Base",1,INDEX(ModelOutput!$D$16:$D$26,MATCH($G19,ModelOutput!$C$16:$C$26,0))) -> 1.1906804 | J19: =IF($A19="Non-greek",1,INDEX(ModelOutput!$D$16:$D$26,MATCH($A19,ModelOutput!$C$16:$C$26,0))) -> 1 | K19: =IF($C19="Yes",1,INDEX(ModelOutput!$D$16:$D$26,MATCH($C19,ModelOutput!$C$16:$C$26,0))) -> 1 | L19: =IF($D19="2.0-3.0",1,INDEX(ModelOutput!$D$16:$D$26,MATCH($D19,ModelOutput!$C$16:$C$26,0))) -> 1 | M19: =IF($B19="On campus",1,INDEX(ModelOutput!$D$16:$D$26,MATCH($B19,ModelOutput!$C$16:$C$26,0))) -> 1 | N19: =IF($B19="On campus",1,INDEX(ModelOutput!$E$16:$E$26,MATCH($B19,ModelOutput!$C$16:$C$26,0))) -> 1 | O19: =IF($B19="On campus",1,INDEX(ModelOutput!$F$16:$F$26,MATCH($B19,ModelOutput!$C$16:$C$26,0))) -> 1 | P19: =IF($B19="On campus",1,INDEX(ModelOutput!$G$16:$G$26,MATCH($B19,ModelOutput!$C$16:$C$26,0))) -> 1 | Q19: =INDEX(ModelOutput!$D$9:$D$11,MATCH("Tier "&$F19,ModelOutput!$B$9:$B$11,0)) -> 40.009437 | R19: =INDEX(ModelOutput!$E$9:$E$11,MATCH("Tier "&$F19,ModelOutput!$B$9:$B$11,0)) -> 117.94972 | S19: =INDEX(ModelOutput!$F$9:$F$11,MATCH("Tier "&$F19,ModelOutput!$B$9:$B$11,0)) -> 136.83923 | T19: =INDEX(ModelOutput!$G$9:$G$11,MATCH("Tier "&$F19,ModelOutput!$B$9:$B$11,0)) -> 22.729632 | U19: =$Q19*$I19*$J19*$K19*$L19*$M19 -> 47.638454 | V19: =$R19*$I19*$J19*$K19*$L19*$N19 -> 140.44043 | W19: =$S19*$I19*$J19*$K19*$L19*$O19 -> 162.93179 | X19: =$T19*$I19*$J19*$K19*$L19*$P19 -> 27.063727 | Y19: =SUM(U19:X19) -> 378.0744 | Z19: =$Y19*GROSS_MULT+POLICY_FEE -> 656.44511 | AA19: =$Z19/CURRENT_FLAT-1 -> -0.53973398 | AB19: =MEDIAN(CURRENT_FLAT*(1-CAP_DOWN),$Z19,CURRENT_FLAT*(1+CAP_UP)) -> 1069.6723 | AC19: =IF($Z19>CURRENT_FLAT,ROUNDUP(LN($Z19/CURRENT_FLAT)/LN(1+CAP_UP),0),IF($Z19<CURRENT_FLAT,ROUNDUP(LN($Z19/CURRENT_FLAT)/LN(1-CAP_DOWN),0),0)) -> 3 | AD19: 378.0744 | AE19: =$Y19-$AD19 -> -6.2527761e-13 | AF19: =IF($E19="Freshman",4,IF($E19="Sophomore",3,IF($E19="Junior",2,IF($E19="Senior",1,2)))) -> 2
... A404: Greek | B404: Off 6+mi | C404: No | D404: 3.0+ | E404: Grad student | F404: 3 | G404: Grad | H404: 0 | I404: =IF($G404="Base",1,INDEX(ModelOutput!$D$16:$D$26,MATCH($G404,ModelOutput!$C$16:$C$26,0))) -> 1.1906804 | J404: =IF($A404="Non-greek",1,INDEX(ModelOutput!$D$16:$D$26,MATCH($A404,ModelOutput!$C$16:$C$26,0))) -> 4.3562312 | K404: =IF($C404="Yes",1,INDEX(ModelOutput!$D$16:$D$26,MATCH($C404,ModelOutput!$C$16:$C$26,0))) -> 1.5400748 | L404: =IF($D404="2.0-3.0",1,INDEX(ModelOutput!$D$16:$D$26,MATCH($D404,ModelOutput!$C$16:$C$26,0))) -> 0.87654762 | M404: =IF($B404="On campus",1,INDEX(ModelOutput!$D$16:$D$26,MATCH($B404,ModelOutput!$C$16:$C$26,0))) -> 2.2239289 | N404: =IF($B404="On campus",1,INDEX(ModelOutput!$E$16:$E$26,MATCH($B404,ModelOutput!$C$16:$C$26,0))) -> 2.1888545 | O404: =IF($B404="On campus",1,INDEX(ModelOutput!$F$16:$F$26,MATCH($B404,ModelOutput!$C$16:$C$26,0))) -> 2.8272586 | P404: =IF($B404="On campus",1,INDEX(ModelOutput!$G$16:$G$26,MATCH($B404,ModelOutput!$C$16:$C$26,0))) -> 3.5639395 | Q404: =INDEX(ModelOutput!$D$9:$D$11,MATCH("Tier "&$F404,ModelOutput!$B$9:$B$11,0)) -> 40.009437 | R404: =INDEX(ModelOutput!$E$9:$E$11,MATCH("Tier "&$F404,ModelOutput!$B$9:$B$11,0)) -> 117.94972 | S404: =INDEX(ModelOutput!$F$9:$F$11,MATCH("Tier "&$F404,ModelOutput!$B$9:$B$11,0)) -> 136.83923 | T404: =INDEX(ModelOutput!$G$9:$G$11,MATCH("Tier "&$F404,ModelOutput!$B$9:$B$11,0)) -> 22.729632 | U404: =$Q404*$I404*$J404*$K404*$L404*$M404 -> 623.0269 | V404: =$R404*$I404*$J404*$K404*$L404*$N404 -> 1807.7454 | W404: =$S404*$I404*$J404*$K404*$L404*$O404 -> 2708.9413 | X404: =$T404*$I404*$J404*$K404*$L404*$P404 -> 567.21299 | Y404: =SUM(U404:X404) -> 5706.9266 | Z404: =$Y404*GROSS_MULT+POLICY_FEE -> 9321.5742 | AA404: =$Z404/CURRENT_FLAT-1 -> 5.5358152 | AB404: =MEDIAN(CURRENT_FLAT*(1-CAP_DOWN),$Z404,CURRENT_FLAT*(1+CAP_UP)) -> 1782.7872 | AC404: =IF($Z404>CURRENT_FLAT,ROUNDUP(LN($Z404/CURRENT_FLAT)/LN(1+CAP_UP),0),IF($Z404<CURRENT_FLAT,ROUNDUP(LN($Z404/CURRENT_FLAT)/LN(1-CAP_DOWN),0),0)) -> 9 | AD404: 5706.9266 | AE404: =$Y404-$AD404 -> 0 | AF404: =IF($E404="Freshman",4,IF($E404="Sophomore",3,IF($E404="Junior",2,IF($E404="Senior",1,2)))) -> 2

Sheet Dislocation
B2: Dislocation & Capping
B3: How far each student moves off today's flat premium, and what capping that move costs.
B4: Today's flat premium is not given in the case. We use the average indicated.
B6: PREMIUM CHANGE DISTRIBUTION
B7: Change vs today | C7: Students | D7: Share of book | E7: Avg new premium | F7: Premium $
B8: Decrease > 50% | C8: =SUMIFS(Segments!$H$5:$H$404,Segments!$AA$5:$AA$404,"<-0.5") -> 3821 | D8: =C8/$C$16 -> 0.3821 | E8: =IFERROR(SUMPRODUCT(Segments!$H$5:$H$404,Segments!$Z$5:$Z$404,--(Segments!$AA$5:$AA$404<-0.5))/SUMPRODUCT(Segments!$H$5:$H$404,--(Segments!$AA$5:$AA$404<-0.5)),0) -> 548.89174 | F8: =SUMPRODUCT(Segments!$H$5:$H$404,Segments!$Z$5:$Z$404,--(Segments!$AA$5:$AA$404<-0.5)) -> 2097315.3
B9: Decrease 25-50% | C9: =SUMIFS(Segments!$H$5:$H$404,Segments!$AA$5:$AA$404,">=-0.5",Segments!$AA$5:$AA$404,"<-0.25") -> 1881 | D9: =C9/$C$16 -> 0.1881 | E9: =IFERROR(SUMPRODUCT(Segments!$H$5:$H$404,Segments!$Z$5:$Z$404,--(Segments!$AA$5:$AA$404>=-0.5)*--(Segments!$AA$5:$AA$404<-0.25))/SUMPRODUCT(Segments!$H$5:$H$404,--(Segments!$AA$5:$AA$404>=-0.5)*--(Segments!$AA$5:$AA$404<-0.25)),0) -> 866.1028 | F9: =SUMPRODUCT(Segments!$H$5:$H$404,Segments!$Z$5:$Z$404,--(Segments!$AA$5:$AA$404>=-0.5)*--(Segments!$AA$5:$AA$404<-0.25)) -> 1629139.4
B10: Decrease 10-25% | C10: =SUMIFS(Segments!$H$5:$H$404,Segments!$AA$5:$AA$404,">=-0.25",Segments!$AA$5:$AA$404,"<-0.1") -> 1034 | D10: =C10/$C$16 -> 0.1034 | E10: =IFERROR(SUMPRODUCT(Segments!$H$5:$H$404,Segments!$Z$5:$Z$404,--(Segments!$AA$5:$AA$404>=-0.25)*--(Segments!$AA$5:$AA$404<-0.1))/SUMPRODUCT(Segments!$H$5:$H$404,--(Segments!$AA$5:$AA$404>=-0.25)*--(Segments!$AA$5:$AA$404<-0.1)),0) -> 1163.0343 | F10: =SUMPRODUCT(Segments!$H$5:$H$404,Segments!$Z$5:$Z$404,--(Segments!$AA$5:$AA$404>=-0.25)*--(Segments!$AA$5:$AA$404<-0.1)) -> 1202577.4
B11: Within +/-10% | C11: =SUMIFS(Segments!$H$5:$H$404,Segments!$AA$5:$AA$404,">=-0.1",Segments!$AA$5:$AA$404,"<0.1") -> 579 | D11: =C11/$C$16 -> 0.0579 | E11: =IFERROR(SUMPRODUCT(Segments!$H$5:$H$404,Segments!$Z$5:$Z$404,--(Segments!$AA$5:$AA$404>=-0.1)*--(Segments!$AA$5:$AA$404<0.1))/SUMPRODUCT(Segments!$H$5:$H$404,--(Segments!$AA$5:$AA$404>=-0.1)*--(Segments!$AA$5:$AA$404<0.1)),0) -> 1397.6264 | F11: =SUMPRODUCT(Segments!$H$5:$H$404,Segments!$Z$5:$Z$404,--(Segments!$AA$5:$AA$404>=-0.1)*--(Segments!$AA$5:$AA$404<0.1)) -> 809225.69
B12: Increase 10-25% | C12: =SUMIFS(Segments!$H$5:$H$404,Segments!$AA$5:$AA$404,">=0.1",Segments!$AA$5:$AA$404,"<0.25") -> 334 | D12: =C12/$C$16 -> 0.0334 | E12: =IFERROR(SUMPRODUCT(Segments!$H$5:$H$404,Segments!$Z$5:$Z$404,--(Segments!$AA$5:$AA$404>=0.1)*--(Segments!$AA$5:$AA$404<0.25))/SUMPRODUCT(Segments!$H$5:$H$404,--(Segments!$AA$5:$AA$404>=0.1)*--(Segments!$AA$5:$AA$404<0.25)),0) -> 1665.0976 | F12: =SUMPRODUCT(Segments!$H$5:$H$404,Segments!$Z$5:$Z$404,--(Segments!$AA$5:$AA$404>=0.1)*--(Segments!$AA$5:$AA$404<0.25)) -> 556142.6
B13: Increase 25-50% | C13: =SUMIFS(Segments!$H$5:$H$404,Segments!$AA$5:$AA$404,">=0.25",Segments!$AA$5:$AA$404,"<0.5") -> 712 | D13: =C13/$C$16 -> 0.0712 | E13: =IFERROR(SUMPRODUCT(Segments!$H$5:$H$404,Segments!$Z$5:$Z$404,--(Segments!$AA$5:$AA$404>=0.25)*--(Segments!$AA$5:$AA$404<0.5))/SUMPRODUCT(Segments!$H$5:$H$404,--(Segments!$AA$5:$AA$404>=0.25)*--(Segments!$AA$5:$AA$404<0.5)),0) -> 1974.05 | F13: =SUMPRODUCT(Segments!$H$5:$H$404,Segments!$Z$5:$Z$404,--(Segments!$AA$5:$AA$404>=0.25)*--(Segments!$AA$5:$AA$404<0.5)) -> 1405523.6
B14: Increase 50-100% | C14: =SUMIFS(Segments!$H$5:$H$404,Segments!$AA$5:$AA$404,">=0.5",Segments!$AA$5:$AA$404,"<1.0") -> 613 | D14: =C14/$C$16 -> 0.0613 | E14: =IFERROR(SUMPRODUCT(Segments!$H$5:$H$404,Segments!$Z$5:$Z$404,--(Segments!$AA$5:$AA$404>=0.5)*--(Segments!$AA$5:$AA$404<1))/SUMPRODUCT(Segments!$H$5:$H$404,--(Segments!$AA$5:$AA$404>=0.5)*--(Segments!$AA$5:$AA$404<1)),0) -> 2414.4325 | F14: =SUMPRODUCT(Segments!$H$5:$H$404,Segments!$Z$5:$Z$404,--(Segments!$AA$5:$AA$404>=0.5)*--(Segments!$AA$5:$AA$404<1)) -> 1480047.1
B15: Increase > 100% | C15: =SUMIFS(Segments!$H$5:$H$404,Segments!$AA$5:$AA$404,">=1.0") -> 1026 | D15: =C15/$C$16 -> 0.1026 | E15: =IFERROR(SUMPRODUCT(Segments!$H$5:$H$404,Segments!$Z$5:$Z$404,--(Segments!$AA$5:$AA$404>=1))/SUMPRODUCT(Segments!$H$5:$H$404,--(Segments!$AA$5:$AA$404>=1)),0) -> 4953.5347 | F15: =SUMPRODUCT(Segments!$H$5:$H$404,Segments!$Z$5:$Z$404,--(Segments!$AA$5:$AA$404>=1)) -> 5082326.6
B16: TOTAL | C16: =SUM(C8:C15) -> 10000 | D16: =SUM(D8:D15) -> 1 | E16: =SUMPRODUCT(Segments!$H$5:$H$404,Segments!$Z$5:$Z$404)/SUM(Segments!$H$5:$H$404) -> 1426.2298 | F16: =SUMPRODUCT(Segments!$H$5:$H$404,Segments!$Z$5:$Z$404) -> 14262298
B18: WHO MOVES — BY GREEK STATUS AND LOCATION
B19: Segment | C19: Students | D19: Share of book | E19: Avg new premium | F19: Avg change
B20: Greek / Off campus | C20: =SUMPRODUCT(Segments!$H$5:$H$404,--(Segments!$A$5:$A$404="Greek")*--(Segments!$B$5:$B$404<>"On campus")) -> 656 | D20: =C20/SUM(Segments!$H$5:$H$404) -> 0.0656 | E20: =IFERROR(SUMPRODUCT(Segments!$H$5:$H$404,Segments!$Z$5:$Z$404,--(Segments!$A$5:$A$404="Greek")*--(Segments!$B$5:$B$404<>"On campus"))/SUMPRODUCT(Segments!$H$5:$H$404,--(Segments!$A$5:$A$404="Greek")*--(Segments!$B$5:$B$404<>"On campus")),0) -> 5781.6579 | F20: =IFERROR(SUMPRODUCT(Segments!$H$5:$H$404,Segments!$AA$5:$AA$404,--(Segments!$A$5:$A$404="Greek")*--(Segments!$B$5:$B$404<>"On campus"))/SUMPRODUCT(Segments!$H$5:$H$404,--(Segments!$A$5:$A$404="Greek")*--(Segments!$B$5:$B$404<>"On campus")),0) -> 3.0538054
B21: Greek / On campus | C21: =SUMPRODUCT(Segments!$H$5:$H$404,--(Segments!$A$5:$A$404="Greek")*--(Segments!$B$5:$B$404="On campus")) -> 1309 | D21: =C21/SUM(Segments!$H$5:$H$404) -> 0.1309 | E21: =IFERROR(SUMPRODUCT(Segments!$H$5:$H$404,Segments!$Z$5:$Z$404,--(Segments!$A$5:$A$404="Greek")*--(Segments!$B$5:$B$404="On campus"))/SUMPRODUCT(Segments!$H$5:$H$404,--(Segments!$A$5:$A$404="Greek")*--(Segments!$B$5:$B$404="On campus")),0) -> 2595.4098 | F21: =IFERROR(SUMPRODUCT(Segments!$H$5:$H$404,Segments!$AA$5:$AA$404,--(Segments!$A$5:$A$404="Greek")*--(Segments!$B$5:$B$404="On campus"))/SUMPRODUCT(Segments!$H$5:$H$404,--(Segments!$A$5:$A$404="Greek")*--(Segments!$B$5:$B$404="On campus")),0) -> 0.81976976
B22: Non-greek / Off campus | C22: =SUMPRODUCT(Segments!$H$5:$H$404,--(Segments!$A$5:$A$404="Non-greek")*--(Segments!$B$5:$B$404<>"On campus")) -> 2839 | D22: =C22/SUM(Segments!$H$5:$H$404) -> 0.2839 | E22: =IFERROR(SUMPRODUCT(Segments!$H$5:$H$404,Segments!$Z$5:$Z$404,--(Segments!$A$5:$A$404="Non-greek")*--(Segments!$B$5:$B$404<>"On campus"))/SUMPRODUCT(Segments!$H$5:$H$404,--(Segments!$A$5:$A$404="Non-greek")*--(Segments!$B$5:$B$404<>"On campus")),0) -> 1349.7789 | F22: =IFERROR(SUMPRODUCT(Segments!$H$5:$H$404,Segments!$AA$5:$AA$404,--(Segments!$A$5:$A$404="Non-greek")*--(Segments!$B$5:$B$404<>"On campus"))/SUMPRODUCT(Segments!$H$5:$H$404,--(Segments!$A$5:$A$404="Non-greek")*--(Segments!$B$5:$B$404<>"On campus")),0) -> -0.053603464
B23: Non-greek / On campus | C23: =SUMPRODUCT(Segments!$H$5:$H$404,--(Segments!$A$5:$A$404="Non-greek")*--(Segments!$B$5:$B$404="On campus")) -> 5196 | D23: =C23/SUM(Segments!$H$5:$H$404) -> 0.5196 | E23: =IFERROR(SUMPRODUCT(Segments!$H$5:$H$404,Segments!$Z$5:$Z$404,--(Segments!$A$5:$A$404="Non-greek")*--(Segments!$B$5:$B$404="On campus"))/SUMPRODUCT(Segments!$H$5:$H$404,--(Segments!$A$5:$A$404="Non-greek")*--(Segments!$B$5:$B$404="On campus")),0) -> 623.57897 | F23: =IFERROR(SUMPRODUCT(Segments!$H$5:$H$404,Segments!$AA$5:$AA$404,--(Segments!$A$5:$A$404="Non-greek")*--(Segments!$B$5:$B$404="On campus"))/SUMPRODUCT(Segments!$H$5:$H$404,--(Segments!$A$5:$A$404="Non-greek")*--(Segments!$B$5:$B$404="On campus")),0) -> -0.56277804
B25: CAPPING THE TRANSITION
B26: Indicated premium, year 1 (total) | C26: =SUMPRODUCT(Segments!$H$5:$H$404,Segments!$Z$5:$Z$404) -> 14262298 | H26: If everyone moved straight to the indicated rate
B27: Capped premium, year 1 (total) | C27: =SUMPRODUCT(Segments!$H$5:$H$404,Segments!$AB$5:$AB$404) -> 12858550 | H27: With the +/-25% cap applied
B28: Capping off-balance | C28: =C27/C26-1 -> -0.098423668 | H28: Premium given up in year 1 by capping
B29: Students capped on the way up | C29: =SUMPRODUCT(Segments!$H$5:$H$404,--(Segments!$Z$5:$Z$404>CURRENT_FLAT*(1+CAP_UP))) -> 2351
B30: Students capped on the way down | C30: =SUMPRODUCT(Segments!$H$5:$H$404,--(Segments!$Z$5:$Z$404<CURRENT_FLAT*(1-CAP_DOWN))) -> 5702
B31: Students reaching indicated before graduating | C31: =SUMPRODUCT(Segments!$H$5:$H$404,--(Segments!$AC$5:$AC$404<=Segments!$AF$5:$AF$404)) -> 4801
B32: Students graduating before they get there | C32: =SUM(Segments!$H$5:$H$404)-C31 -> 5199

Sheet ProFormaA
B2: Pro Forma — Plan A. Keep the flat rate
B3: Three-year projection. Students age a class each year, seniors graduate out, and retention responds to how our price compares with the competition.
B6: PROJECTED UNDERWRITING RESULT
B7: Line | C7: Year 1 | D7: Year 2 | E7: Year 3 | F7: 3-year total
B8: Policies in force | C8: =SUM(T$25:T$424) -> 8108.4562 | D8: =SUM(AH$25:AH$424) -> 7223.4592 | E8: =SUM(AV$25:AV$424) -> 6552.1824 | F8: =SUM(C8:E8) -> 21884.098
B9: of which new business | C9: =SUM(S$25:S$424) -> 2862.1809 | D9: =SUM(AG$25:AG$424) -> 2858.3024 | E9: =SUM(AU$25:AU$424) -> 2854.5276 | F9: =SUM(C9:E9) -> 8575.011
B10: Average premium | C10: =IFERROR(C11/C8,0) -> 1426.2298 | D10: =IFERROR(D11/D8,0) -> 1469.0167 | E10: =IFERROR(E11/E8,0) -> 1513.0872
B11: Written premium | C11: =SUM(V$25:V$424) -> 11564522 | D11: =SUM(AJ$25:AJ$424) -> 10611382 | E11: =SUM(AX$25:AX$424) -> 9914023.1 | F11: =SUM(C11:E11) -> 32089927
B12: Expected loss + LAE | C12: =SUM(W$25:W$424) -> 10474319 | D12: =SUM(AK$25:AK$424) -> 11480711 | E12: =SUM(AY$25:AY$424) -> 11663861 | F12: =SUM(C12:E12) -> 33618891
B13: Expenses | C13: =SUM(X$25:X$424) -> 2562292.7 | D13: =SUM(AL$25:AL$424) -> 2368439.2 | E13: =SUM(AZ$25:AZ$424) -> 2227327.4 | F13: =SUM(C13:E13) -> 7158059.4
B14: Underwriting profit | C14: =C11-C12-C13 -> -1472090.5 | D14: =D11-D12-D13 -> -3237768.1 | E14: =E11-E12-E13 -> -3977165.4 | F14: =SUM(C14:E14) -> -8687023.9
B15: Loss ratio | C15: =IFERROR(C12/C11,0) -> 0.90572872 | D15: =IFERROR(D12/D11,0) -> 1.0819242 | E15: =IFERROR(E12/E11,0) -> 1.1765013
B16: Expense ratio | C16: =IFERROR(C13/C11,0) -> 0.22156495 | D16: =IFERROR(D13/D11,0) -> 0.223198 | E16: =IFERROR(E13/E11,0) -> 0.22466434
B17: Combined ratio | C17: =IFERROR((C12+C13)/C11,0) -> 1.1272937 | D17: =IFERROR((D12+D13)/D11,0) -> 1.3051222 | E17: =IFERROR((E12+E13)/E11,0) -> 1.4011656 | F17: =IFERROR((SUM(C12:E12)+SUM(C13:E13))/SUM(C11:E11),0) -> 1.2707087
B18: High-risk share of book | C18: =IFERROR(SUMPRODUCT(T$25:T$424,--(L$25:L$424>2*Segments!$AH$3))/SUM(T$25:T$424),0) -> 0.17654516 | D18: =IFERROR(SUMPRODUCT(AH$25:AH$424,--(Z$25:Z$424>2*Segments!$AH$3))/SUM(AH$25:AH$424),0) -> 0.24486047 | E18: =IFERROR(SUMPRODUCT(AV$25:AV$424,--(AN$25:AN$424>2*Segments!$AH$3))/SUM(AV$25:AV$424),0) -> 0.28696252
B20: Combined ratio below 100% means the plan is profitable before investment income.
K23: YEAR 1 | Y23: YEAR 2 | AM23: YEAR 3
A24: Greek | B24: Distance band | C24: Sprinklered | D24: GPA band | E24: Class | F24: Tier | G24: Class adj | H24: Students (year 0) | I24: Loss cost (base) | J24: Offset | K24: Prev premium | L24: Loss cost (trended) | M24: Indicated premium | N24: Market price | O24: Charged — renewal | P24: Retention | Q24: Conversion | R24: Renewal policies | S24: New policies | T24: Total policies | U24: Avg charged | V24: Written premium | W24: Loss + LAE | X24: Expenses | Y24: Prev premium | Z24: Loss cost (trended) | AA24: Indicated premium | AB24: Market price | AC24: Charged — renewal | AD24: Retention | AE24: Conversion | AF24: Renewal policies | AG24: New policies | AH24: Total policies | AI24: Avg charged | AJ24: Written premium | AK24: Loss + LAE | AL24: Expenses | AM24: Prev premium | AN24: Loss cost (trended) | AO24: Indicated premium | AP24: Market price | AQ24: Charged — renewal | AR24: Retention | AS24: Conversion | AT24: Renewal policies | AU24: New policies | AV24: Total policies | AW24: Avg charged | AX24: Written premium | AY24: Loss + LAE | AZ24: Expenses
A25: =Segments!$A$5 -> Non-greek | B25: =Segments!$B$5 -> On campus | C25: =Segments!$C$5 -> Yes | D25: =Segments!$D$5 -> <1.0 | E25: =Segments!$E$5 -> Freshman | F25: =Segments!$F$5 -> 1 | G25: =Segments!$G$5 -> Base | H25: =Segments!$H$5 -> 61 | I25: =Segments!$Y$5 -> 321.9684 | J25: 0 | K25: =IF($J25=0,M25,CURRENT_FLAT) -> 565.21239 | L25: =$I25*(1+LOSS_TREND)^0 -> 321.9684 | M25: =L25*GROSS_MULT+POLICY_FEE -> 565.21239 | N25: =M25^MARKET_RISK_WEIGHT*(CURRENT_FLAT*(1+LOSS_TREND)^0)^(1-MARKET_RISK_WEIGHT) -> 897.84338 | O25: =CURRENT_FLAT*(1+LOSS_TREND)^0 -> 1426.2298 | P25: =MEDIAN(RET_FLOOR,BASE_RETENTION-ELAST_MARKET*(O25/N25-1)-ELAST_INCREASE*MAX(O25/K25-1,0),RET_CEIL) -> 0.3 | Q25: =MEDIAN(CONV_FLOOR,BASE_CONVERSION-ELAST_MARKET*(CURRENT_FLAT*(1+LOSS_TREND)^0/N25-1),CONV_CEIL) -> 0.055746904 | R25: =IF($J25=0,0,IF($J25=4,$H25*GRAD_CONTINUE,$H24)*P25) -> 0 | S25: =APPLICANTS_PER_YEAR*($H25/Segments!$AH$2)*Q25 -> 4.0806734 | T25: =R25+S25 -> 4.0806734 | U25: =IFERROR((R25*O25+S25*CURRENT_FLAT*(1+LOSS_TREND)^0)/T25,M25) -> 1426.2298 | V25: =R25*O25+S25*CURRENT_FLAT*(1+LOSS_TREND)^0 -> 5819.9778 | W25: =T25*L25*(1+LAE_RATIO) -> 1471.5096 | X25: =R25*O25*(PREMIUM_TAX+OTHER_VARIABLE+COMMISSION_RN)+S25*CURRENT_FLAT*(1+LOSS_TREND)^0*(PREMIUM_TAX+OTHER_VARIABLE+COMMISSION_NB)+T25*FIXED_PER_POLICY+S25*NB_ACQUISITION -> 1487.3053 | Y25: =IF($J25=0,AA25,IF($J25=4,U25,U24)) -> 580.91876 | Z25: =$I25*(1+LOSS_TREND)^1 -> 331.62746 | AA25: =Z25*GROSS_MULT+POLICY_FEE -> 580.91876 | AB25: =AA25^MARKET_RISK_WEIGHT*(CURRENT_FLAT*(1+LOSS_TREND)^1)^(1-MARKET_RISK_WEIGHT) -> 923.78534 | AC25: =CURRENT_FLAT*(1+LOSS_TREND)^1 -> 1469.0167 | AD25: =MEDIAN(RET_FLOOR,BASE_RETENTION-ELAST_MARKET*(AC25/AB25-1)-ELAST_INCREASE*MAX(AC25/Y25-1,0),RET_CEIL) -> 0.3 | AE25: =MEDIAN(CONV_FLOOR,BASE_CONVERSION-ELAST_MARKET*(CURRENT_FLAT*(1+LOSS_TREND)^1/AB25-1),CONV_CEIL) -> 0.05489284 | AF25: =IF($J25=0,0,IF($J25=4,T25*GRAD_CONTINUE,T24)*AD25) -> 0 | AG25: =APPLICANTS_PER_YEAR*($H25/Segments!$AH$2)*AE25 -> 4.0181559 | AH25: =AF25+AG25 -> 4.0181559 | AI25: =IFERROR((AF25*AC25+AG25*CURRENT_FLAT*(1+LOSS_TREND)^1)/AH25,AA25) -> 1469.0167 | AJ25: =AF25*AC25+AG25*CURRENT_FLAT*(1+LOSS_TREND)^1 -> 5902.738 | AK25: =AH25*Z25*(1+LAE_RATIO) -> 1492.4345 | AL25: =AF25*AC25*(PREMIUM_TAX+OTHER_VARIABLE+COMMISSION_RN)+AG25*CURRENT_FLAT*(1+LOSS_TREND)^1*(PREMIUM_TAX+OTHER_VARIABLE+COMMISSION_NB)+AH25*FIXED_PER_POLICY+AG25*NB_ACQUISITION -> 1503.0303 | AM25: =IF($J25=0,AO25,IF($J25=4,AI25,AI24)) -> 597.09633 | AN25: =$I25*(1+LOSS_TREND)^2 -> 341.57628 | AO25: =AN25*GROSS_MULT+POLICY_FEE -> 597.09633 | AP25: =AO25^MARKET_RISK_WEIGHT*(CURRENT_FLAT*(1+LOSS_TREND)^2)^(1-MARKET_RISK_WEIGHT) -> 950.50449 | AQ25: =CURRENT_FLAT*(1+LOSS_TREND)^2 -> 1513.0872 | AR25: =MEDIAN(RET_FLOOR,BASE_RETENTION-ELAST_MARKET*(AQ25/AP25-1)-ELAST_INCREASE*MAX(AQ25/AM25-1,0),RET_CEIL) -> 0.3 | AS25: =MEDIAN(CONV_FLOOR,BASE_CONVERSION-ELAST_MARKET*(CURRENT_FLAT*(1+LOSS_TREND)^2/AP25-1),CONV_CEIL) -> 0.054061011 | AT25: =IF($J25=0,0,IF($J25=4,AH25*GRAD_CONTINUE,AH24)*AR25) -> 0 | AU25: =APPLICANTS_PER_YEAR*($H25/Segments!$AH$2)*AS25 -> 3.957266 | AV25: =AT25+AU25 -> 3.957266 | AW25: =IFERROR((AT25*AQ25+AU25*CURRENT_FLAT*(1+LOSS_TREND)^2)/AV25,AO25) -> 1513.0872 | AX25: =AT25*AQ25+AU25*CURRENT_FLAT*(1+LOSS_TREND)^2 -> 5987.6884 | AY25: =AV25*AN25*(1+LAE_RATIO) -> 1513.9132 | AZ25: =AT25*AQ25*(PREMIUM_TAX+OTHER_VARIABLE+COMMISSION_RN)+AU25*CURRENT_FLAT*(1+LOSS_TREND)^2*(PREMIUM_TAX+OTHER_VARIABLE+COMMISSION_NB)+AV25*FIXED_PER_POLICY+AU25*NB_ACQUISITION -> 1519.3192
A26: =Segments!$A$6 -> Non-greek | B26: =Segments!$B$6 -> On campus | C26: =Segments!$C$6 -> Yes | D26: =Segments!$D$6 -> <1.0 | E26: =Segments!$E$6 -> Sophomore | F26: =Segments!$F$6 -> 1 | G26: =Segments!$G$6 -> Sophomore | H26: =Segments!$H$6 -> 79 | I26: =Segments!$Y$6 -> 318.69278 | J26: 1 | K26: =IF($J26=0,M26,CURRENT_FLAT) -> 1426.2298 | L26: =$I26*(1+LOSS_TREND)^0 -> 318.69278 | M26: =L26*GROSS_MULT+POLICY_FEE -> 559.88596 | N26: =M26^MARKET_RISK_WEIGHT*(CURRENT_FLAT*(1+LOSS_TREND)^0)^(1-MARKET_RISK_WEIGHT) -> 893.60284 | O26: =CURRENT_FLAT*(1+LOSS_TREND)^0 -> 1426.2298 | P26: =MEDIAN(RET_FLOOR,BASE_RETENTION-ELAST_MARKET*(O26/N26-1)-ELAST_INCREASE*MAX(O26/K26-1,0),RET_CEIL) -> 0.55197782 | Q26: =MEDIAN(CONV_FLOOR,BASE_CONVERSION-ELAST_MARKET*(CURRENT_FLAT*(1+LOSS_TREND)^0/N26-1),CONV_CEIL) -> 0.051977817 | R26: =IF($J26=0,0,IF($J26=4,$H26*GRAD_CONTINUE,$H25)*P26) -> 33.670647 | S26: =APPLICANTS_PER_YEAR*($H26/Segments!$AH$2)*Q26 -> 4.9274971 | T26: =R26+S26 -> 38.598144 | U26: =IFERROR((R26*O26+S26*CURRENT_FLAT*(1+LOSS_TREND)^0)/T26,M26) -> 1426.2298 | V26: =R26*O26+S26*CURRENT_FLAT*(1+LOSS_TREND)^0 -> 55049.822 | W26: =T26*L26*(1+LAE_RATIO) -> 13777.064 | X26: =R26*O26*(PREMIUM_TAX+OTHER_VARIABLE+COMMISSION_RN)+S26*CURRENT_FLAT*(1+LOSS_TREND)^0*(PREMIUM_TAX+OTHER_VARIABLE+COMMISSION_NB)+T26*FIXED_PER_POLICY+S26*NB_ACQUISITION -> 11545.538 | Y26: =IF($J26=0,AA26,IF($J26=4,U26,U25)) -> 1426.2298 | Z26: =$I26*(1+LOSS_TREND)^1 -> 328.25356 | AA26: =Z26*GROSS_MULT+POLICY_FEE -> 575.43254 | AB26: =AA26^MARKET_RISK_WEIGHT*(CURRENT_FLAT*(1+LOSS_TREND)^1)^(1-MARKET_RISK_WEIGHT) -> 919.41285 | AC26: =CURRENT_FLAT*(1+LOSS_TREND)^1 -> 1469.0167 | AD26: =MEDIAN(RET_FLOOR,BASE_RETENTION-ELAST_MARKET*(AC26/AB26-1)-ELAST_INCREASE*MAX(AC26/Y26-1,0),RET_CEIL) -> 0.54211152 | AE26: =MEDIAN(CONV_FLOOR,BASE_CONVERSION-ELAST_MARKET*(CURRENT_FLAT*(1+LOSS_TREND)^1/AB26-1),CONV_CEIL) -> 0.051111524 | AF26: =IF($J26=0,0,IF($J26=4,T26*GRAD_CONTINUE,T25)*AD26) -> 2.2121801 | AG26: =APPLICANTS_PER_YEAR*($H26/Segments!$AH$2)*AE26 -> 4.8453725 | AH26: =AF26+AG26 -> 7.0575525 | AI26: =IFERROR((AF26*AC26+AG26*CURRENT_FLAT*(1+LOSS_TREND)^1)/AH26,AA26) -> 1469.0167 | AJ26: =AF26*AC26+AG26*CURRENT_FLAT*(1+LOSS_TREND)^1 -> 10367.662 | AK26: =AH26*Z26*(1+LAE_RATIO) -> 2594.6667 | AL26: =AF26*AC26*(PREMIUM_TAX+OTHER_VARIABLE+COMMISSION_RN)+AG26*CURRENT_FLAT*(1+LOSS_TREND)^1*(PREMIUM_TAX+OTHER_VARIABLE+COMMISSION_NB)+AH26*FIXED_PER_POLICY+AG26*NB_ACQUISITION -> 2470.9012 | AM26: =IF($J26=0,AO26,IF($J26=4,AI26,AI25)) -> 1469.0167 | AN26: =$I26*(1+LOSS_TREND)^2 -> 338.10117 | AO26: =AN26*GROSS_MULT+POLICY_FEE -> 591.44552 | AP26: =AO26^MARKET_RISK_WEIGHT*(CURRENT_FLAT*(1+LOSS_TREND)^2)^(1-MARKET_RISK_WEIGHT) -> 945.9961 | AQ26: =CURRENT_FLAT*(1+LOSS_TREND)^2 -> 1513.0872 | AR26: =MEDIAN(RET_FLOOR,BASE_RETENTION-ELAST_MARKET*(AQ26/AP26-1)-ELAST_INCREASE*MAX(AQ26/AM26-1,0),RET_CEIL) -> 0.54126776 | AS26: =MEDIAN(CONV_FLOOR,BASE_CONVERSION-ELAST_MARKET*(CURRENT_FLAT*(1+LOSS_TREND)^2/AP26-1),CONV_CEIL) -> 0.050267758 | AT26: =IF($J26=0,0,IF($J26=4,AH26*GRAD_CONTINUE,AH25)*AR26) -> 2.1748982 | AU26: =APPLICANTS_PER_YEAR*($H26/Segments!$AH$2)*AS26 -> 4.7653835 | AV26: =AT26+AU26 -> 6.9402817 | AW26: =IFERROR((AT26*AQ26+AU26*CURRENT_FLAT*(1+LOSS_TREND)^2)/AV26,AO26) -> 1513.0872 | AX26: =AT26*AQ26+AU26*CURRENT_FLAT*(1+LOSS_TREND)^2 -> 10501.251 | AY26: =AV26*AN26*(1+LAE_RATIO) -> 2628.0994 | AZ26: =AT26*AQ26*(PREMIUM_TAX+OTHER_VARIABLE+COMMISSION_RN)+AU26*CURRENT_FLAT*(1+LOSS_TREND)^2*(PREMIUM_TAX+OTHER_VARIABLE+COMMISSION_NB)+AV26*FIXED_PER_POLICY+AU26*NB_ACQUISITION -> 2495.0421
A27: =Segments!$A$7 -> Non-greek | B27: =Segments!$B$7 -> On campus | C27: =Segments!$C$7 -> Yes | D27: =Segments!$D$7 -> <1.0 | E27: =Segments!$E$7 -> Junior | F27: =Segments!$F$7 -> 2 | G27: =Segments!$G$7 -> Base | H27: =Segments!$H$7 -> 79 | I27: =Segments!$Y$7 -> 380.97351 | J27: 2 | K27: =IF($J27=0,M27,CURRENT_FLAT) -> 1426.2298 | L27: =$I27*(1+LOSS_TREND)^0 -> 380.97351 | M27: =L27*GROSS_MULT+POLICY_FEE -> 661.15929 | N27: =M27^MARKET_RISK_WEIGHT*(CURRENT_FLAT*(1+LOSS_TREND)^0)^(1-MARKET_RISK_WEIGHT) -> 971.06389 | O27: =CURRENT_FLAT*(1+LOSS_TREND)^0 -> 1426.2298 | P27: =MEDIAN(RET_FLOOR,BASE_RETENTION-ELAST_MARKET*(O27/N27-1)-ELAST_INCREASE*MAX(O27/K27-1,0),RET_CEIL) -> 0.61563546 | Q27: =MEDIAN(CONV_FLOOR,BASE_CONVERSION-ELAST_MARKET*(CURRENT_FLAT*(1+LOSS_TREND)^0/N27-1),CONV_CEIL) -> 0.11563546 | R27: =IF($J27=0,0,IF($J27=4,$H27*GRAD_CONTINUE,$H26)*P27) -> 48.635201 | S27: =APPLICANTS_PER_YEAR*($H27/Segments!$AH$2)*Q27 -> 10.962241 | T27: =R27+S27 -> 59.597442 | U27: =IFERROR((R27*O27+S27*CURRENT_FLAT*(1+LOSS_TREND)^0)/T27,M27) -> 1426.2298 | V27: =R27*O27+S27*CURRENT_FLAT*(1+LOSS_TREND)^0 -> 84999.647 | W27: =T27*L27*(1+LAE_RATIO) -> 25429.652 | X27: =R27*O27*(PREMIUM_TAX+OTHER_VARIABLE+COMMISSION_RN)+S27*CURRENT_FLAT*(1+LOSS_TREND)^0*(PREMIUM_TAX+OTHER_VARIABLE+COMMISSION_NB)+T27*FIXED_PER_POLICY+S27*NB_ACQUISITION -> 18078.152 | Y27: =IF($J27=0,AA27,IF($J27=4,U27,U26)) -> 1426.2298 | Z27: =$I27*(1+LOSS_TREND)^1 -> 392.40271 | AA27: =Z27*GROSS_MULT+POLICY_FEE -> 679.74407 | AB27: =AA27^MARKET_RISK_WEIGHT*(CURRENT_FLAT*(1+LOSS_TREND)^1)^(1-MARKET_RISK_WEIGHT) -> 999.27743 | AC27: =CURRENT_FLAT*(1+LOSS_TREND)^1 -> 1469.0167 | AD27: =MEDIAN(RET_FLOOR,BASE_RETENTION-ELAST_MARKET*(AC27/AB27-1)-ELAST_INCREASE*MAX(AC27/Y27-1,0),RET_CEIL) -> 0.60596054 | AE27: =MEDIAN(CONV_FLOOR,BASE_CONVERSION-ELAST_MARKET*(CURRENT_FLAT*(1+LOSS_TREND)^1/AB27-1),CONV_CEIL) -> 0.11496054 | AF27: =IF($J27=0,0,IF($J27=4,T27*GRAD_CONTINUE,T26)*AD27) -> 23.388952 | AG27: =APPLICANTS_PER_YEAR*($H27/Segments!$AH$2)*AE27 -> 10.89826 | AH27: =AF27+AG27 -> 34.287212 | AI27: =IFERROR((AF27*AC27+AG27*CURRENT_FLAT*(1+LOSS_TREND)^1)/AH27,AA27) -> 1469.0167 | AJ27: =AF27*AC27+AG27*CURRENT_FLAT*(1+LOSS_TREND)^1 -> 50368.486 | AK27: =AH27*Z27*(1+LAE_RATIO) -> 15068.922 | AL27: =AF27*AC27*(PREMIUM_TAX+OTHER_VARIABLE+COMMISSION_RN)+AG27*CURRENT_FLAT*(1+LOSS_TREND)^1*(PREMIUM_TAX+OTHER_VARIABLE+COMMISSION_NB)+AH27*FIXED_PER_POLICY+AG27*NB_ACQUISITION -> 11038.185 | AM27: =IF($J27=0,AO27,IF($J27=4,AI27,AI26)) -> 1469.0167 | AN27: =$I27*(1+LOSS_TREND)^2 -> 404.1748 | AO27: =AN27*GROSS_MULT+POLICY_FEE -> 698.88639 | AP27: =AO27^MARKET_RISK_WEIGHT*(CURRENT_FLAT*(1+LOSS_TREND)^2)^(1-MARKET_RISK_WEIGHT) -> 1028.3365 | AQ27: =CURRENT_FLAT*(1+LOSS_TREND)^2 -> 1513.0872 | AR27: =MEDIAN(RET_FLOOR,BASE_RETENTION-ELAST_MARKET*(AQ27/AP27-1)-ELAST_INCREASE*MAX(AQ27/AM27-1,0),RET_CEIL) -> 0.60530351 | AS27: =MEDIAN(CONV_FLOOR,BASE_CONVERSION-ELAST_MARKET*(CURRENT_FLAT*(1+LOSS_TREND)^2/AP27-1),CONV_CEIL) -> 0.11430351 | AT27: =IF($J27=0,0,IF($J27=4,AH27*GRAD_CONTINUE,AH26)*AR27) -> 4.2719613 | AU27: =APPLICANTS_PER_YEAR*($H27/Segments!$AH$2)*AS27 -> 10.835973 | AV27: =AT27+AU27 -> 15.107934 | AW27: =IFERROR((AT27*AQ27+AU27*CURRENT_FLAT*(1+LOSS_TREND)^2)/AV27,AO27) -> 1513.0872 | AX27: =AT27*AQ27+AU27*CURRENT_FLAT*(1+LOSS_TREND)^2 -> 22859.621 | AY27: =AV27*AN27*(1+LAE_RATIO) -> 6838.9956 | AZ27: =AT27*AQ27*(PREMIUM_TAX+OTHER_VARIABLE+COMMISSION_RN)+AU27*CURRENT_FLAT*(1+LOSS_TREND)^2*(PREMIUM_TAX+OTHER_VARIABLE+COMMISSION_NB)+AV27*FIXED_PER_POLICY+AU27*NB_ACQUISITION -> 5467.3783
A28: =Segments!$A$8 -> Non-greek | B28: =Segments!$B$8 -> On campus | C28: =Segments!$C$8 -> Yes | D28: =Segments!$D$8 -> <1.0 | E28: =Segments!$E$8 -> Senior | F28: =Segments!$F$8 -> 3 | G28: =Segments!$G$8 -> Base | H28: =Segments!$H$8 -> 58 | I28: =Segments!$Y$8 -> 356.09116 | J28: 3 | K28: =IF($J28=0,M28,CURRENT_FLAT) -> 1426.2298 | L28: =$I28*(1+LOSS_TREND)^0 -> 356.09116 | M28: =L28*GROSS_MULT+POLICY_FEE -> 620.69865 | N28: =M28^MARKET_RISK_WEIGHT*(CURRENT_FLAT*(1+LOSS_TREND)^0)^(1-MARKET_RISK_WEIGHT) -> 940.88198 | O28: =CURRENT_FLAT*(1+LOSS_TREND)^0 -> 1426.2298 | P28: =MEDIAN(RET_FLOOR,BASE_RETENTION-ELAST_MARKET*(O28/N28-1)-ELAST_INCREASE*MAX(O28/K28-1,0),RET_CEIL) -> 0.59207828 | Q28: =MEDIAN(CONV_FLOOR,BASE_CONVERSION-ELAST_MARKET*(CURRENT_FLAT*(1+LOSS_TREND)^0/N28-1),CONV_CEIL) -> 0.092078282 | R28: =IF($J28=0,0,IF($J28=4,$H28*GRAD_CONTINUE,$H27)*P28) -> 46.774184 | S28: =APPLICANTS_PER_YEAR*($H28/Segments!$AH$2)*Q28 -> 6.4086484 | T28: =R28+S28 -> 53.182833 | U28: =IFERROR((R28*O28+S28*CURRENT_FLAT*(1+LOSS_TREND)^0)/T28,M28) -> 1426.2298 | V28: =R28*O28+S28*CURRENT_FLAT*(1+LOSS_TREND)^0 -> 75850.94 | W28: =T28*L28*(1+LAE_RATIO) -> 21210.489 | X28: =R28*O28*(PREMIUM_TAX+OTHER_VARIABLE+COMMISSION_RN)+S28*CURRENT_FLAT*(1+LOSS_TREND)^0*(PREMIUM_TAX+OTHER_VARIABLE+COMMISSION_NB)+T28*FIXED_PER_POLICY+S28*NB_ACQUISITION -> 15879.608 | Y28: =IF($J28=0,AA28,IF($J28=4,U28,U27)) -> 1426.2298 | Z28: =$I28*(1+LOSS_TREND)^1 -> 366.7739 | AA28: =Z28*GROSS_MULT+POLICY_FEE -> 638.06961 | AB28: =AA28^MARKET_RISK_WEIGHT*(CURRENT_FLAT*(1+LOSS_TREND)^1)^(1-MARKET_RISK_WEIGHT) -> 968.16058 | AC28: =CURRENT_FLAT*(1+LOSS_TREND)^1 -> 1469.0167 | AD28: =MEDIAN(RET_FLOOR,BASE_RETENTION-ELAST_MARKET*(AC28/AB28-1)-ELAST_INCREASE*MAX(AC28/Y28-1,0),RET_CEIL) -> 0.58233625 | AE28: =MEDIAN(CONV_FLOOR,BASE_CONVERSION-ELAST_MARKET*(CURRENT_FLAT*(1+LOSS_TREND)^1/AB28-1),CONV_CEIL) -> 0.091336248 | AF28: =IF($J28=0,0,IF($J28=4,T28*GRAD_CONTINUE,T27)*AD28) -> 34.705751 | AG28: =APPLICANTS_PER_YEAR*($H28/Segments!$AH$2)*AE28 -> 6.3570029 | AH28: =AF28+AG28 -> 41.062754 | AI28: =IFERROR((AF28*AC28+AG28*CURRENT_FLAT*(1+LOSS_TREND)^1)/AH28,AA28) -> 1469.0167 | AJ28: =AF28*AC28+AG28*CURRENT_FLAT*(1+LOSS_TREND)^1 -> 60321.87 | AK28: =AH28*Z28*(1+LAE_RATIO) -> 16868.036 | AL28: =AF28*AC28*(PREMIUM_TAX+OTHER_VARIABLE+COMMISSION_RN)+AG28*CURRENT_FLAT*(1+LOSS_TREND)^1*(PREMIUM_TAX+OTHER_VARIABLE+COMMISSION_NB)+AH28*FIXED_PER_POLICY+AG28*NB_ACQUISITION -> 12707.863 | AM28: =IF($J28=0,AO28,IF($J28=4,AI28,AI27)) -> 1469.0167 | AN28: =$I28*(1+LOSS_TREND)^2 -> 377.77711 | AO28: =AN28*GROSS_MULT+POLICY_FEE -> 655.9617 | AP28: =AO28^MARKET_RISK_WEIGHT*(CURRENT_FLAT*(1+LOSS_TREND)^2)^(1-MARKET_RISK_WEIGHT) -> 996.25661 | AQ28: =CURRENT_FLAT*(1+LOSS_TREND)^2 -> 1513.0872 | AR28: =MEDIAN(RET_FLOOR,BASE_RETENTION-ELAST_MARKET*(AQ28/AP28-1)-ELAST_INCREASE*MAX(AQ28/AM28-1,0),RET_CEIL) -> 0.58161374 | AS28: =MEDIAN(CONV_FLOOR,BASE_CONVERSION-ELAST_MARKET*(CURRENT_FLAT*(1+LOSS_TREND)^2/AP28-1),CONV_CEIL) -> 0.090613738 | AT28: =IF($J28=0,0,IF($J28=4,AH28*GRAD_CONTINUE,AH27)*AR28) -> 19.941914 | AU28: =APPLICANTS_PER_YEAR*($H28/Segments!$AH$2)*AS28 -> 6.3067161 | AV28: =AT28+AU28 -> 26.24863 | AW28: =IFERROR((AT28*AQ28+AU28*CURRENT_FLAT*(1+LOSS_TREND)^2)/AV28,AO28) -> 1513.0872 | AX28: =AT28*AQ28+AU28*CURRENT_FLAT*(1+LOSS_TREND)^2 -> 39716.465 | AY28: =AV28*AN28*(1+LAE_RATIO) -> 11106.067 | AZ28: =AT28*AQ28*(PREMIUM_TAX+OTHER_VARIABLE+COMMISSION_RN)+AU28*CURRENT_FLAT*(1+LOSS_TREND)^2*(PREMIUM_TAX+OTHER_VARIABLE+COMMISSION_NB)+AV28*FIXED_PER_POLICY+AU28*NB_ACQUISITION -> 8523.0437
A29: =Segments!$A$9 -> Non-greek | B29: =Segments!$B$9 -> On campus | C29: =Segments!$C$9 -> Yes | D29: =Segments!$D$9 -> <1.0 | E29: =Segments!$E$9 -> Grad student | F29: =Segments!$F$9 -> 3 | G29: =Segments!$G$9 -> Grad | H29: =Segments!$H$9 -> 48 | I29: =Segments!$Y$9 -> 423.99078 | J29: 4 | K29: =IF($J29=0,M29,CURRENT_FLAT) -> 1426.2298 | L29: =$I29*(1+LOSS_TREND)^0 -> 423.99078 | M29: =L29*GROSS_MULT+POLICY_FEE -> 731.10872 | N29: =M29^MARKET_RISK_WEIGHT*(CURRENT_FLAT*(1+LOSS_TREND)^0)^(1-MARKET_RISK_WEIGHT) -> 1021.141 | O29: =CURRENT_FLAT*(1+LOSS_TREND)^0 -> 1426.2298 | P29: =MEDIAN(RET_FLOOR,BASE_RETENTION-ELAST_MARKET*(O29/N29-1)-ELAST_INCREASE*MAX(O29/K29-1,0),RET_CEIL) -> 0.65164898 | Q29: =MEDIAN(CONV_FLOOR,BASE_CONVERSION-ELAST_MARKET*(CURRENT_FLAT*(1+LOSS_TREND)^0/N29-1),CONV_CEIL) -> 0.15164898 | R29: =IF($J29=0,0,IF($J29=4,$H29*GRAD_CONTINUE,$H28)*P29) -> 15.639576 | S29: =APPLICANTS_PER_YEAR*($H29/Segments!$AH$2)*Q29 -> 8.7349813 | T29: =R29+S29 -> 24.374557 | U29: =IFERROR((R29*O29+S29*CURRENT_FLAT*(1+LOSS_TREND)^0)/T29,M29) -> 1426.2298 | V29: =R29*O29+S29*CURRENT_FLAT*(1+LOSS_TREND)^0 -> 34763.719 | W29: =T29*L29*(1+LAE_RATIO) -> 11574.738 | X29: =R29*O29*(PREMIUM_TAX+OTHER_VARIABLE+COMMISSION_RN)+S29*CURRENT_FLAT*(1+LOSS_TREND)^0*(PREMIUM_TAX+OTHER_VARIABLE+COMMISSION_NB)+T29*FIXED_PER_POLICY+S29*NB_ACQUISITION -> 7712.2417 | Y29: =IF($J29=0,AA29,IF($J29=4,U29,U28)) -> 1426.2298 | Z29: =$I29*(1+LOSS_TREND)^1 -> 436.7105 | AA29: =Z29*GROSS_MULT+POLICY_FEE -> 751.79198 | AB29: =AA29^MARKET_RISK_WEIGHT*(CURRENT_FLAT*(1+LOSS_TREND)^1)^(1-MARKET_RISK_WEIGHT) -> 1050.902 | AC29: =CURRENT_FLAT*(1+LOSS_TREND)^1 -> 1469.0167 | AD29: =MEDIAN(RET_FLOOR,BASE_RETENTION-ELAST_MARKET*(AC29/AB29-1)-ELAST_INCREASE*MAX(AC29/Y29-1,0),RET_CEIL) -> 0.64206865 | AE29: =MEDIAN(CONV_FLOOR,BASE_CONVERSION-ELAST_MARKET*(CURRENT_FLAT*(1+LOSS_TREND)^1/AB29-1),CONV_CEIL) -> 0.15106865 | AF29: =IF($J29=0,0,IF($J29=4,T29*GRAD_CONTINUE,T28)*AD29) -> 7.8250694 | AG29: =APPLICANTS_PER_YEAR*($H29/Segments!$AH$2)*AE29 -> 8.7015542 | AH29: =AF29+AG29 -> 16.526624 | AI29: =IFERROR((AF29*AC29+AG29*CURRENT_FLAT*(1+LOSS_TREND)^1)/AH29,AA29) -> 1469.0167 | AJ29: =AF29*AC29+AG29*CURRENT_FLAT*(1+LOSS_TREND)^1 -> 24277.886 | AK29: =AH29*Z29*(1+LAE_RATIO) -> 8083.432 | AL29: =AF29*AC29*(PREMIUM_TAX+OTHER_VARIABLE+COMMISSION_RN)+AG29*CURRENT_FLAT*(1+LOSS_TREND)^1*(PREMIUM_TAX+OTHER_VARIABLE+COMMISSION_NB)+AH29*FIXED_PER_POLICY+AG29*NB_ACQUISITION -> 5583.9872 | AM29: =IF($J29=0,AO29,IF($J29=4,AI29,AI28)) -> 1469.0167 | AN29: =$I29*(1+LOSS_TREND)^2 -> 449.81181 | AO29: =AN29*GROSS_MULT+POLICY_FEE -> 773.09574 | AP29: =AO29^MARKET_RISK_WEIGHT*(CURRENT_FLAT*(1+LOSS_TREND)^2)^(1-MARKET_RISK_WEIGHT) -> 1081.555 | AQ29: =CURRENT_FLAT*(1+LOSS_TREND)^2 -> 1513.0872 | AR29: =MEDIAN(RET_FLOOR,BASE_RETENTION-ELAST_MARKET*(AQ29/AP29-1)-ELAST_INCREASE*MAX(AQ29/AM29-1,0),RET_CEIL) -> 0.64150384 | AS29: =MEDIAN(CONV_FLOOR,BASE_CONVERSION-ELAST_MARKET*(CURRENT_FLAT*(1+LOSS_TREND)^2/AP29-1),CONV_CEIL) -> 0.15050384 | AT29: =IF($J29=0,0,IF($J29=4,AH29*GRAD_CONTINUE,AH28)*AR29) -> 5.3009462 | AU29: =APPLICANTS_PER_YEAR*($H29/Segments!$AH$2)*AS29 -> 8.6690209 | AV29: =AT29+AU29 -> 13.969967 | AW29: =IFERROR((AT29*AQ29+AU29*CURRENT_FLAT*(1+LOSS_TREND)^2)/AV29,AO29) -> 1513.0872 | AX29: =AT29*AQ29+AU29*CURRENT_FLAT*(1+LOSS_TREND)^2 -> 21137.778 | AY29: =AV29*AN29*(1+LAE_RATIO) -> 7037.919 | AZ29: =AT29*AQ29*(PREMIUM_TAX+OTHER_VARIABLE+COMMISSION_RN)+AU29*CURRENT_FLAT*(1+LOSS_TREND)^2*(PREMIUM_TAX+OTHER_VARIABLE+COMMISSION_NB)+AV29*FIXED_PER_POLICY+AU29*NB_ACQUISITION -> 4950.2594
A30: =Segments!$A$10 -> Non-greek | B30: =Segments!$B$10 -> On campus | C30: =Segments!$C$10 -> Yes | D30: =Segments!$D$10 -> 1.0-2.0 | E30: =Segments!$E$10 -> Freshman | F30: =Segments!$F$10 -> 1 | G30: =Segments!$G$10 -> Base | H30: =Segments!$H$10 -> 188 | I30: =Segments!$Y$10 -> 292.16092 | J30: 0 | K30: =IF($J30=0,M30,CURRENT_FLAT) -> 516.7431 | L30: =$I30*(1+LOSS_TREND)^0 -> 292.16092 | M30: =L30*GROSS_MULT+POLICY_FEE -> 516.7431 | N30: =M30^MARKET_RISK_WEIGHT*(CURRENT_FLAT*(1+LOSS_TREND)^0)^(1-MARKET_RISK_WEIGHT) -> 858.48377 | O30: =CURRENT_FLAT*(1+LOSS_TREND)^0 -> 1426.2298 | P30: =MEDIAN(RET_FLOOR,BASE_RETENTION-ELAST_MARKET*(O30/N30-1)-ELAST_INCREASE*MAX(O30/K30-1,0),RET_CEIL) -> 0.3 | Q30: =MEDIAN(CONV_FLOOR,BASE_CONVERSION-ELAST_MARKET*(CURRENT_FLAT*(1+LOSS_TREND)^0/N30-1),CONV_CEIL) -> 0.02 | R30: =IF($J30=0,0,IF($J30=4,$H30*GRAD_CONTINUE,$H29)*P30) -> 0 | S30: =APPLICANTS_PER_YEAR*($H30/Segments!$AH$2)*Q30 -> 4.512 | T30: =R30+S30 -> 4.512 | U30: =IFERROR((R30*O30+S30*CURRENT_FLAT*(1+LOSS_TREND)^0)/T30,M30) -> 1426.2298 | V30: =R30*O30+S30*CURRENT_FLAT*(1+LOSS_TREND)^0 -> 6435.1487 | W30: =T30*L30*(1+LAE_RATIO) -> 1476.4177 | X30: =R30*O30*(PREMIUM_TAX+OTHER_VARIABLE+COMMISSION_RN)+S30*CURRENT_FLAT*(1+LOSS_TREND)^0*(PREMIUM_TAX+OTHER_VARIABLE+COMMISSION_NB)+T30*FIXED_PER_POLICY+S30*NB_ACQUISITION -> 1644.5133 | Y30: =IF($J30=0,AA30,IF($J30=4,U30,U29)) -> 530.99539 | Z30: =$I30*(1+LOSS_TREND)^1 -> 300.92574 | AA30: =Z30*GROSS_MULT+POLICY_FEE -> 530.99539 | AB30: =AA30^MARKET_RISK_WEIGHT*(CURRENT_FLAT*(1+LOSS_TREND)^1)^(1-MARKET_RISK_WEIGHT) -> 883.19934 | AC30: =CURRENT_FLAT*(1+LOSS_TREND)^1 -> 1469.0167 | AD30: =MEDIAN(RET_FLOOR,BASE_RETENTION-ELAST_MARKET*(AC30/AB30-1)-ELAST_INCREASE*MAX(AC30/Y30-1,0),RET_CEIL) -> 0.3 | AE30: =MEDIAN(CONV_FLOOR,BASE_CONVERSION-ELAST_MARKET*(CURRENT_FLAT*(1+LOSS_TREND)^1/AB30-1),CONV_CEIL) -> 0.02 | AF30: =IF($J30=0,0,IF($J30=4,T30*GRAD_CONTINUE,T29)*AD30) -> 0 | AG30: =APPLICANTS_PER_YEAR*($H30/Segments!$AH$2)*AE30 -> 4.512 | AH30: =AF30+AG30 -> 4.512 | AI30: =IFERROR((AF30*AC30+AG30*CURRENT_FLAT*(1+LOSS_TREND)^1)/AH30,AA30) -> 1469.0167 | AJ30: =AF30*AC30+AG30*CURRENT_FLAT*(1+LOSS_TREND)^1 -> 6628.2032 | AK30: =AH30*Z30*(1+LAE_RATIO) -> 1520.7102 | AL30: =AF30*AC30*(PREMIUM_TAX+OTHER_VARIABLE+COMMISSION_RN)+AG30*CURRENT_FLAT*(1+LOSS_TREND)^1*(PREMIUM_TAX+OTHER_VARIABLE+COMMISSION_NB)+AH30*FIXED_PER_POLICY+AG30*NB_ACQUISITION -> 1687.7575 | AM30: =IF($J30=0,AO30,IF($J30=4,AI30,AI29)) -> 545.67525 | AN30: =$I30*(1+LOSS_TREND)^2 -> 309.95352 | AO30: =AN30*GROSS_MULT+POLICY_FEE -> 545.67525 | AP30: =AO30^MARKET_RISK_WEIGHT*(CURRENT_FLAT*(1+LOSS_TREND)^2)^(1-MARKET_RISK_WEIGHT) -> 908.65517 | AQ30: =CURRENT_FLAT*(1+LOSS_TREND)^2 -> 1513.0872 | AR30: =MEDIAN(RET_FLOOR,BASE_RETENTION-ELAST_MARKET*(AQ30/AP30-1)-ELAST_INCREASE*MAX(AQ30/AM30-1,0),RET_CEIL) -> 0.3 | AS30: =MEDIAN(CONV_FLOOR,BASE_CONVERSION-ELAST_MARKET*(CURRENT_FLAT*(1+LOSS_TREND)^2/AP30-1),CONV_CEIL) -> 0.02 | AT30: =IF($J30=0,0,IF($J30=4,AH30*GRAD_CONTINUE,AH29)*AR30) -> 0 | AU30: =APPLICANTS_PER_YEAR*($H30/Segments!$AH$2)*AS30 -> 4.512 | AV30: =AT30+AU30 -> 4.512 | AW30: =IFERROR((AT30*AQ30+AU30*CURRENT_FLAT*(1+LOSS_TREND)^2)/AV30,AO30) -> 1513.0872 | AX30: =AT30*AQ30+AU30*CURRENT_FLAT*(1+LOSS_TREND)^2 -> 6827.0493 | AY30: =AV30*AN30*(1+LAE_RATIO) -> 1566.3315 | AZ30: =AT30*AQ30*(PREMIUM_TAX+OTHER_VARIABLE+COMMISSION_RN)+AU30*CURRENT_FLAT*(1+LOSS_TREND)^2*(PREMIUM_TAX+OTHER_VARIABLE+COMMISSION_NB)+AV30*FIXED_PER_POLICY+AU30*NB_ACQUISITION -> 1732.299
A31: =Segments!$A$11 -> Non-greek | B31: =Segments!$B$11 -> On campus | C31: =Segments!$C$11 -> Yes | D31: =Segments!$D$11 -> 1.0-2.0 | E31: =Segments!$E$11 -> Sophomore | F31: =Segments!$F$11 -> 1 | G31: =Segments!$G$11 -> Sophomore | H31: =Segments!$H$11 -> 216 | I31: =Segments!$Y$11 -> 289.18854 | J31: 1 | K31: =IF($J31=0,M31,CURRENT_FLAT) -> 1426.2298 | L31: =$I31*(1+LOSS_TREND)^0 -> 289.18854 | M31: =L31*GROSS_MULT+POLICY_FEE -> 511.90978 | N31: =M31^MARKET_RISK_WEIGHT*(CURRENT_FLAT*(1+LOSS_TREND)^0)^(1-MARKET_RISK_WEIGHT) -> 854.45946 | O31: =CURRENT_FLAT*(1+LOSS_TREND)^0 -> 1426.2298 | P31: =MEDIAN(RET_FLOOR,BASE_RETENTION-ELAST_MARKET*(O31/N31-1)-ELAST_INCREASE*MAX(O31/K31-1,0),RET_CEIL) -> 0.51541987 | Q31: =MEDIAN(CONV_FLOOR,BASE_CONVERSION-ELAST_MARKET*(CURRENT_FLAT*(1+LOSS_TREND)^0/N31-1),CONV_CEIL) -> 0.02 | R31: =IF($J31=0,0,IF($J31=4,$H31*GRAD_CONTINUE,$H30)*P31) -> 96.898936 | S31: =APPLICANTS_PER_YEAR*($H31/Segments!$AH$2)*Q31 -> 5.184 | T31: =R31+S31 -> 102.08294 | U31: =IFERROR((R31*O31+S31*CURRENT_FLAT*(1+LOSS_TREND)^0)/T31,M31) -> 1426.2298 | V31: =R31*O31+S31*CURRENT_FLAT*(1+LOSS_TREND)^0 -> 145593.72 | W31: =T31*L31*(1+LAE_RATIO) -> 33063.761 | X31: =R31*O31*(PREMIUM_TAX+OTHER_VARIABLE+COMMISSION_RN)+S31*CURRENT_FLAT*(1+LOSS_TREND)^0*(PREMIUM_TAX+OTHER_VARIABLE+COMMISSION_NB)+T31*FIXED_PER_POLICY+S31*NB_ACQUISITION -> 29947.247 | Y31: =IF($J31=0,AA31,IF($J31=4,U31,U30)) -> 1426.2298 | Z31: =$I31*(1+LOSS_TREND)^1 -> 297.8642 | AA31: =Z31*GROSS_MULT+POLICY_FEE -> 526.01708 | AB31: =AA31^MARKET_RISK_WEIGHT*(CURRENT_FLAT*(1+LOSS_TREND)^1)^(1-MARKET_RISK_WEIGHT) -> 879.0494 | AC31: =CURRENT_FLAT*(1+LOSS_TREND)^1 -> 1469.0167 | AD31: =MEDIAN(RET_FLOOR,BASE_RETENTION-ELAST_MARKET*(AC31/AB31-1)-ELAST_INCREASE*MAX(AC31/Y31-1,0),RET_CEIL) -> 0.50542883 | AE31: =MEDIAN(CONV_FLOOR,BASE_CONVERSION-ELAST_MARKET*(CURRENT_FLAT*(1+LOSS_TREND)^1/AB31-1),CONV_CEIL) -> 0.02 | AF31: =IF($J31=0,0,IF($J31=4,T31*GRAD_CONTINUE,T30)*AD31) -> 2.2804949 | AG31: =APPLICANTS_PER_YEAR*($H31/Segments!$AH$2)*AE31 -> 5.184 | AH31: =AF31+AG31 -> 7.4644949 | AI31: =IFERROR((AF31*AC31+AG31*CURRENT_FLAT*(1+LOSS_TREND)^1)/AH31,AA31) -> 1469.0167 | AJ31: =AF31*AC31+AG31*CURRENT_FLAT*(1+LOSS_TREND)^1 -> 10965.467 | AK31: =AH31*Z31*(1+LAE_RATIO) -> 2490.2145 | AL31: =AF31*AC31*(PREMIUM_TAX+OTHER_VARIABLE+COMMISSION_RN)+AG31*CURRENT_FLAT*(1+LOSS_TREND)^1*(PREMIUM_TAX+OTHER_VARIABLE+COMMISSION_NB)+AH31*FIXED_PER_POLICY+AG31*NB_ACQUISITION -> 2617.9016 | AM31: =IF($J31=0,AO31,IF($J31=4,AI31,AI30)) -> 1469.0167 | AN31: =$I31*(1+LOSS_TREND)^2 -> 306.80013 | AO31: =AN31*GROSS_MULT+POLICY_FEE -> 540.54759 | AP31: =AO31^MARKET_RISK_WEIGHT*(CURRENT_FLAT*(1+LOSS_TREND)^2)^(1-MARKET_RISK_WEIGHT) -> 904.37582 | AQ31: =CURRENT_FLAT*(1+LOSS_TREND)^2 -> 1513.0872 | AR31: =MEDIAN(RET_FLOOR,BASE_RETENTION-ELAST_MARKET*(AQ31/AP31-1)-ELAST_INCREASE*MAX(AQ31/AM31-1,0),RET_CEIL) -> 0.50446328 | AS31: =MEDIAN(CONV_FLOOR,BASE_CONVERSION-ELAST_MARKET*(CURRENT_FLAT*(1+LOSS_TREND)^2/AP31-1),CONV_CEIL) -> 0.02 | AT31: =IF($J31=0,0,IF($J31=4,AH31*GRAD_CONTINUE,AH30)*AR31) -> 2.2761383 | AU31: =APPLICANTS_PER_YEAR*($H31/Segments!$AH$2)*AS31 -> 5.184 | AV31: =AT31+AU31 -> 7.4601383 | AW31: =IFERROR((AT31*AQ31+AU31*CURRENT_FLAT*(1+LOSS_TREND)^2)/AV31,AO31) -> 1513.0872 | AX31: =AT31*AQ31+AU31*CURRENT_FLAT*(1+LOSS_TREND)^2 -> 11287.84 | AY31: =AV31*AN31*(1+LAE_RATIO) -> 2563.4239 | AZ31: =AT31*AQ31*(PREMIUM_TAX+OTHER_VARIABLE+COMMISSION_RN)+AU31*CURRENT_FLAT*(1+LOSS_TREND)^2*(PREMIUM_TAX+OTHER_VARIABLE+COMMISSION_NB)+AV31*FIXED_PER_POLICY+AU31*NB_ACQUISITION -> 2686.739
A32: =Segments!$A$12 -> Non-greek | B32: =Segments!$B$12 -> On campus | C32: =Segments!$C$12 -> Yes | D32: =Segments!$D$12 -> 1.0-2.0 | E32: =Segments!$E$12 -> Junior | F32: =Segments!$F$12 -> 2 | G32: =Segments!$G$12 -> Base | H32: =Segments!$H$12 -> 194 | I32: =Segments!$Y$12 -> 345.70339 | J32: 2 | K32: =IF($J32=0,M32,CURRENT_FLAT) -> 1426.2298 | L32: =$I32*(1+LOSS_TREND)^0 -> 345.70339 | M32: =L32*GROSS_MULT+POLICY_FEE -> 603.80734 | N32: =M32^MARKET_RISK_WEIGHT*(CURRENT_FLAT*(1+LOSS_TREND)^0)^(1-MARKET_RISK_WEIGHT) -> 927.99138 | O32: =CURRENT_FLAT*(1+LOSS_TREND)^0 -> 1426.2298 | P32: =MEDIAN(RET_FLOOR,BASE_RETENTION-ELAST_MARKET*(O32/N32-1)-ELAST_INCREASE*MAX(O32/K32-1,0),RET_CEIL) -> 0.5815501 | Q32: =MEDIAN(CONV_FLOOR,BASE_CONVERSION-ELAST_MARKET*(CURRENT_FLAT*(1+LOSS_TREND)^0/N32-1),CONV_CEIL) -> 0.081550096 | R32: =IF($J32=0,0,IF($J32=4,$H32*GRAD_CONTINUE,$H31)*P32) -> 125.61482 | S32: =APPLICANTS_PER_YEAR*($H32/Segments!$AH$2)*Q32 -> 18.984862 | T32: =R32+S32 -> 144.59968 | U32: =IFERROR((R32*O32+S32*CURRENT_FLAT*(1+LOSS_TREND)^0)/T32,M32) -> 1426.2298 | V32: =R32*O32+S32*CURRENT_FLAT*(1+LOSS_TREND)^0 -> 206232.37 | W32: =T32*L32*(1+LAE_RATIO) -> 55987.233 | X32: =R32*O32*(PREMIUM_TAX+OTHER_VARIABLE+COMMISSION_RN)+S32*CURRENT_FLAT*(1+LOSS_TREND)^0*(PREMIUM_TAX+OTHER_VARIABLE+COMMISSION_NB)+T32*FIXED_PER_POLICY+S32*NB_ACQUISITION -> 43292.221 | Y32: =IF($J32=0,AA32,IF($J32=4,U32,U31)) -> 1426.2298 | Z32: =$I32*(1+LOSS_TREND)^1 -> 356.0745 | AA32: =Z32*GROSS_MULT+POLICY_FEE -> 620.67156 | AB32: =AA32^MARKET_RISK_WEIGHT*(CURRENT_FLAT*(1+LOSS_TREND)^1)^(1-MARKET_RISK_WEIGHT) -> 954.87008 | AC32: =CURRENT_FLAT*(1+LOSS_TREND)^1 -> 1469.0167 | AD32: =MEDIAN(RET_FLOOR,BASE_RETENTION-ELAST_MARKET*(AC32/AB32-1)-ELAST_INCREASE*MAX(AC32/Y32-1,0),RET_CEIL) -> 0.57177668 | AE32: =MEDIAN(CONV_FLOOR,BASE_CONVERSION-ELAST_MARKET*(CURRENT_FLAT*(1+LOSS_TREND)^1/AB32-1),CONV_CEIL) -> 0.080776676 | AF32: =IF($J32=0,0,IF($J32=4,T32*GRAD_CONTINUE,T31)*AD32) -> 58.368642 | AG32: =APPLICANTS_PER_YEAR*($H32/Segments!$AH$2)*AE32 -> 18.80481 | AH32: =AF32+AG32 -> 77.173452 | AI32: =IFERROR((AF32*AC32+AG32*CURRENT_FLAT*(1+LOSS_TREND)^1)/AH32,AA32) -> 1469.0167 | AJ32: =AF32*AC32+AG32*CURRENT_FLAT*(1+LOSS_TREND)^1 -> 113369.09 | AK32: =AH32*Z32*(1+LAE_RATIO) -> 30777.038 | AL32: =AF32*AC32*(PREMIUM_TAX+OTHER_VARIABLE+COMMISSION_RN)+AG32*CURRENT_FLAT*(1+LOSS_TREND)^1*(PREMIUM_TAX+OTHER_VARIABLE+COMMISSION_NB)+AH32*FIXED_PER_POLICY+AG32*NB_ACQUISITION -> 24407.207 | AM32: =IF($J32=0,AO32,IF($J32=4,AI32,AI31)) -> 1469.0167 | AN32: =$I32*(1+LOSS_TREND)^2 -> 366.75673 | AO32: =AN32*GROSS_MULT+POLICY_FEE -> 638.0417 | AP32: =AO32^MARKET_RISK_WEIGHT*(CURRENT_FLAT*(1+LOSS_TREND)^2)^(1-MARKET_RISK_WEIGHT) -> 982.55418 | AQ32: =CURRENT_FLAT*(1+LOSS_TREND)^2 -> 1513.0872 | AR32: =MEDIAN(RET_FLOOR,BASE_RETENTION-ELAST_MARKET*(AQ32/AP32-1)-ELAST_INCREASE*MAX(AQ32/AM32-1,0),RET_CEIL) -> 0.57102354 | AS32: =MEDIAN(CONV_FLOOR,BASE_CONVERSION-ELAST_MARKET*(CURRENT_FLAT*(1+LOSS_TREND)^2/AP32-1),CONV_CEIL) -> 0.080023545 | AT32: =IF($J32=0,0,IF($J32=4,AH32*GRAD_CONTINUE,AH31)*AR32) -> 4.2624023 | AU32: =APPLICANTS_PER_YEAR*($H32/Segments!$AH$2)*AS32 -> 18.629481 | AV32: =AT32+AU32 -> 22.891884 | AW32: =IFERROR((AT32*AQ32+AU32*CURRENT_FLAT*(1+LOSS_TREND)^2)/AV32,AO32) -> 1513.0872 | AX32: =AT32*AQ32+AU32*CURRENT_FLAT*(1+LOSS_TREND)^2 -> 34637.415 | AY32: =AV32*AN32*(1+LAE_RATIO) -> 9403.2427 | AZ32: =AT32*AQ32*(PREMIUM_TAX+OTHER_VARIABLE+COMMISSION_RN)+AU32*CURRENT_FLAT*(1+LOSS_TREND)^2*(PREMIUM_TAX+OTHER_VARIABLE+COMMISSION_NB)+AV32*FIXED_PER_POLICY+AU32*NB_ACQUISITION -> 8456.6272
A33: =Segments!$A$13 -> Non-greek | B33: =Segments!$B$13 -> On campus | C33: =Segments!$C$13 -> Yes | D33: =Segments!$D$13 -> 1.0-2.0 | E33: =Segments!$E$13 -> Senior | F33: =Segments!$F$13 -> 3 | G33: =Segments!$G$13 -> Base | H33: =Segments!$H$13 -> 209 | I33: =Segments!$Y$13 -> 323.12463 | J33: 3 | K33: =IF($J33=0,M33,CURRENT_FLAT) -> 1426.2298 | L33: =$I33*(1+LOSS_TREND)^0 -> 323.12463 | M33: =L33*GROSS_MULT+POLICY_FEE -> 567.0925 | N33: =M33^MARKET_RISK_WEIGHT*(CURRENT_FLAT*(1+LOSS_TREND)^0)^(1-MARKET_RISK_WEIGHT) -> 899.33543 | O33: =CURRENT_FLAT*(1+LOSS_TREND)^0 -> 1426.2298 | P33: =MEDIAN(RET_FLOOR,BASE_RETENTION-ELAST_MARKET*(O33/N33-1)-ELAST_INCREASE*MAX(O33/K33-1,0),RET_CEIL) -> 0.55706461 | Q33: =MEDIAN(CONV_FLOOR,BASE_CONVERSION-ELAST_MARKET*(CURRENT_FLAT*(1+LOSS_TREND)^0/N33-1),CONV_CEIL) -> 0.057064609 | R33: =IF($J33=0,0,IF($J33=4,$H33*GRAD_CONTINUE,$H32)*P33) -> 108.07053 | S33: =APPLICANTS_PER_YEAR*($H33/Segments!$AH$2)*Q33 -> 14.311804 | T33: =R33+S33 -> 122.38234 | U33: =IFERROR((R33*O33+S33*CURRENT_FLAT*(1+LOSS_TREND)^0)/T33,M33) -> 1426.2298 | V33: =R33*O33+S33*CURRENT_FLAT*(1+LOSS_TREND)^0 -> 174545.33 | W33: =T33*L33*(1+LAE_RATIO) -> 44290.117 | X33: =R33*O33*(PREMIUM_TAX+OTHER_VARIABLE+COMMISSION_RN)+S33*CURRENT_FLAT*(1+LOSS_TREND)^0*(PREMIUM_TAX+OTHER_VARIABLE+COMMISSION_NB)+T33*FIXED_PER_POLICY+S33*NB_ACQUISITION -> 36508.927 | Y33: =IF($J33=0,AA33,IF($J33=4,U33,U32)) -> 1426.2298 | Z33: =$I33*(1+LOSS_TREND)^1 -> 332.81837 | AA33: =Z33*GROSS_MULT+POLICY_FEE -> 582.85528 | AB33: =AA33^MARKET_RISK_WEIGHT*(CURRENT_FLAT*(1+LOSS_TREND)^1)^(1-MARKET_RISK_WEIGHT) -> 925.32379 | AC33: =CURRENT_FLAT*(1+LOSS_TREND)^1 -> 1469.0167 | AD33: =MEDIAN(RET_FLOOR,BASE_RETENTION-ELAST_MARKET*(AC33/AB33-1)-ELAST_INCREASE*MAX(AC33/Y33-1,0),RET_CEIL) -> 0.54721479 | AE33: =MEDIAN(CONV_FLOOR,BASE_CONVERSION-ELAST_MARKET*(CURRENT_FLAT*(1+LOSS_TREND)^1/AB33-1),CONV_CEIL) -> 0.056214794 | AF33: =IF($J33=0,0,IF($J33=4,T33*GRAD_CONTINUE,T32)*AD33) -> 79.127086 | AG33: =APPLICANTS_PER_YEAR*($H33/Segments!$AH$2)*AE33 -> 14.09867 | AH33: =AF33+AG33 -> 93.225756 | AI33: =IFERROR((AF33*AC33+AG33*CURRENT_FLAT*(1+LOSS_TREND)^1)/AH33,AA33) -> 1469.0167 | AJ33: =AF33*AC33+AG33*CURRENT_FLAT*(1+LOSS_TREND)^1 -> 136950.19 | AK33: =AH33*Z33*(1+LAE_RATIO) -> 34750.513 | AL33: =AF33*AC33*(PREMIUM_TAX+OTHER_VARIABLE+COMMISSION_RN)+AG33*CURRENT_FLAT*(1+LOSS_TREND)^1*(PREMIUM_TAX+OTHER_VARIABLE+COMMISSION_NB)+AH33*FIXED_PER_POLICY+AG33*NB_ACQUISITION -> 28825.459 | AM33: =IF($J33=0,AO33,IF($J33=4,AI33,AI32)) -> 1469.0167 | AN33: =$I33*(1+LOSS_TREND)^2 -> 342.80292 | AO33: =AN33*GROSS_MULT+POLICY_FEE -> 599.09093 | AP33: =AO33^MARKET_RISK_WEIGHT*(CURRENT_FLAT*(1+LOSS_TREND)^2)^(1-MARKET_RISK_WEIGHT) -> 952.09075 | AQ33: =CURRENT_FLAT*(1+LOSS_TREND)^2 -> 1513.0872 | AR33: =MEDIAN(RET_FLOOR,BASE_RETENTION-ELAST_MARKET*(AQ33/AP33-1)-ELAST_INCREASE*MAX(AQ33/AM33-1,0),RET_CEIL) -> 0.54638711 | AS33: =MEDIAN(CONV_FLOOR,BASE_CONVERSION-ELAST_MARKET*(CURRENT_FLAT*(1+LOSS_TREND)^2/AP33-1),CONV_CEIL) -> 0.055387111 | AT33: =IF($J33=0,0,IF($J33=4,AH33*GRAD_CONTINUE,AH32)*AR33) -> 42.16658 | AU33: =APPLICANTS_PER_YEAR*($H33/Segments!$AH$2)*AS33 -> 13.891088 | AV33: =AT33+AU33 -> 56.057667 | AW33: =IFERROR((AT33*AQ33+AU33*CURRENT_FLAT*(1+LOSS_TREND)^2)/AV33,AO33) -> 1513.0872 | AX33: =AT33*AQ33+AU33*CURRENT_FLAT*(1+LOSS_TREND)^2 -> 84820.137 | AY33: =AV33*AN33*(1+LAE_RATIO) -> 21522.74 | AZ33: =AT33*AQ33*(PREMIUM_TAX+OTHER_VARIABLE+COMMISSION_RN)+AU33*CURRENT_FLAT*(1+LOSS_TREND)^2*(PREMIUM_TAX+OTHER_VARIABLE+COMMISSION_NB)+AV33*FIXED_PER_POLICY+AU33*NB_ACQUISITION -> 18235.081
A34: =Segments!$A$14 -> Non-greek | B34: =Segments!$B$14 -> On campus | C34: =Segments!$C$14 -> Yes | D34: =Segments!$D$14 -> 1.0-2.0 | E34: =Segments!$E$14 -> Grad student | F34: =Segments!$F$14 -> 3 | G34: =Segments!$G$14 -> Grad | H34: =Segments!$H$14 -> 113 | I34: =Segments!$Y$14 -> 384.73817 | J34: 4 | K34: =IF($J34=0,M34,CURRENT_FLAT) -> 1426.2298 | L34: =$I34*(1+LOSS_TREND)^0 -> 384.73817 | M34: =L34*GROSS_MULT+POLICY_FEE -> 667.28092 | N34: =M34^MARKET_RISK_WEIGHT*(CURRENT_FLAT*(1+LOSS_TREND)^0)^(1-MARKET_RISK_WEIGHT) -> 975.54904 | O34: =CURRENT_FLAT*(1+LOSS_TREND)^0 -> 1426.2298 | P34: =MEDIAN(RET_FLOOR,BASE_RETENTION-ELAST_MARKET*(O34/N34-1)-ELAST_INCREASE*MAX(O34/K34-1,0),RET_CEIL) -> 0.61901174 | Q34: =MEDIAN(CONV_FLOOR,BASE_CONVERSION-ELAST_MARKET*(CURRENT_FLAT*(1+LOSS_TREND)^0/N34-1),CONV_CEIL) -> 0.11901174 | R34: =IF($J34=0,0,IF($J34=4,$H34*GRAD_CONTINUE,$H33)*P34) -> 34.974164 | S34: =APPLICANTS_PER_YEAR*($H34/Segments!$AH$2)*Q34 -> 16.137993 | T34: =R34+S34 -> 51.112156 | U34: =IFERROR((R34*O34+S34*CURRENT_FLAT*(1+LOSS_TREND)^0)/T34,M34) -> 1426.2298 | V34: =R34*O34+S34*CURRENT_FLAT*(1+LOSS_TREND)^0 -> 72897.679 | W34: =T34*L34*(1+LAE_RATIO) -> 22024.573 | X34: =R34*O34*(PREMIUM_TAX+OTHER_VARIABLE+COMMISSION_RN)+S34*CURRENT_FLAT*(1+LOSS_TREND)^0*(PREMIUM_TAX+OTHER_VARIABLE+COMMISSION_NB)+T34*FIXED_PER_POLICY+S34*NB_ACQUISITION -> 16008.931 | Y34: =IF($J34=0,AA34,IF($J34=4,U34,U33)) -> 1426.2298 | Z34: =$I34*(1+LOSS_TREND)^1 -> 396.28031 | AA34: =Z34*GROSS_MULT+POLICY_FEE -> 686.04935 | AB34: =AA34^MARKET_RISK_WEIGHT*(CURRENT_FLAT*(1+LOSS_TREND)^1)^(1-MARKET_RISK_WEIGHT) -> 1003.9014 | AC34: =CURRENT_FLAT*(1+LOSS_TREND)^1 -> 1469.0167 | AD34: =MEDIAN(RET_FLOOR,BASE_RETENTION-ELAST_MARKET*(AC34/AB34-1)-ELAST_INCREASE*MAX(AC34/Y34-1,0),RET_CEIL) -> 0.60934611 | AE34: =MEDIAN(CONV_FLOOR,BASE_CONVERSION-ELAST_MARKET*(CURRENT_FLAT*(1+LOSS_TREND)^1/AB34-1),CONV_CEIL) -> 0.11834611 | AF34: =IF($J34=0,0,IF($J34=4,T34*GRAD_CONTINUE,T33)*AD34) -> 15.572497 | AG34: =APPLICANTS_PER_YEAR*($H34/Segments!$AH$2)*AE34 -> 16.047732 | AH34: =AF34+AG34 -> 31.620229 | AI34: =IFERROR((AF34*AC34+AG34*CURRENT_FLAT*(1+LOSS_TREND)^1)/AH34,AA34) -> 1469.0167 | AJ34: =AF34*AC34+AG34*CURRENT_FLAT*(1+LOSS_TREND)^1 -> 46450.643 | AK34: =AH34*Z34*(1+LAE_RATIO) -> 14034.131 | AL34: =AF34*AC34*(PREMIUM_TAX+OTHER_VARIABLE+COMMISSION_RN)+AG34*CURRENT_FLAT*(1+LOSS_TREND)^1*(PREMIUM_TAX+OTHER_VARIABLE+COMMISSION_NB)+AH34*FIXED_PER_POLICY+AG34*NB_ACQUISITION -> 10637.873 | AM34: =IF($J34=0,AO34,IF($J34=4,AI34,AI33)) -> 1469.0167 | AN34: =$I34*(1+LOSS_TREND)^2 -> 408.16872 | AO34: =AN34*GROSS_MULT+POLICY_FEE -> 705.38083 | AP34: =AO34^MARKET_RISK_WEIGHT*(CURRENT_FLAT*(1+LOSS_TREND)^2)^(1-MARKET_RISK_WEIGHT) -> 1033.1034 | AQ34: =CURRENT_FLAT*(1+LOSS_TREND)^2 -> 1513.0872 | AR34: =MEDIAN(RET_FLOOR,BASE_RETENTION-ELAST_MARKET*(AQ34/AP34-1)-ELAST_INCREASE*MAX(AQ34/AM34-1,0),RET_CEIL) -> 0.60869812 | AS34: =MEDIAN(CONV_FLOOR,BASE_CONVERSION-ELAST_MARKET*(CURRENT_FLAT*(1+LOSS_TREND)^2/AP34-1),CONV_CEIL) -> 0.11769812 | AT34: =IF($J34=0,0,IF($J34=4,AH34*GRAD_CONTINUE,AH33)*AR34) -> 9.6235868 | AU34: =APPLICANTS_PER_YEAR*($H34/Segments!$AH$2)*AS34 -> 15.959864 | AV34: =AT34+AU34 -> 25.583451 | AW34: =IFERROR((AT34*AQ34+AU34*CURRENT_FLAT*(1+LOSS_TREND)^2)/AV34,AO34) -> 1513.0872 | AX34: =AT34*AQ34+AU34*CURRENT_FLAT*(1+LOSS_TREND)^2 -> 38709.992 | AY34: =AV34*AN34*(1+LAE_RATIO) -> 11695.448 | AZ34: =AT34*AQ34*(PREMIUM_TAX+OTHER_VARIABLE+COMMISSION_RN)+AU34*CURRENT_FLAT*(1+LOSS_TREND)^2*(PREMIUM_TAX+OTHER_VARIABLE+COMMISSION_NB)+AV34*FIXED_PER_POLICY+AU34*NB_ACQUISITION -> 9072.0574
A35: =Segments!$A$15 -> Non-greek | B35: =Segments!$B$15 -> On campus | C35: =Segments!$C$15 -> Yes | D35: =Segments!$D$15 -> 2.0-3.0 | E35: =Segments!$E$15 -> Freshman | F35: =Segments!$F$15 -> 1 | G35: =Segments!$G$15 -> Base | H35: =Segments!$H$15 -> 348 | I35: =Segments!$Y$15 -> 287.10061 | J35: 0 | K35: =IF($J35=0,M35,CURRENT_FLAT) -> 508.51464 | L35: =$I35*(1+LOSS_TREND)^0 -> 287.10061 | M35: =L35*GROSS_MULT+POLICY_FEE -> 508.51464 | N35: =M35^MARKET_RISK_WEIGHT*(CURRENT_FLAT*(1+LOSS_TREND)^0)^(1-MARKET_RISK_WEIGHT) -> 851.62123 | O35: =CURRENT_FLAT*(1+LOSS_TREND)^0 -> 1426.2298 | P35: =MEDIAN(RET_FLOOR,BASE_RETENTION-ELAST_MARKET*(O35/N35-1)-ELAST_INCREASE*MAX(O35/K35-1,0),RET_CEIL) -> 0.3 | Q35: =MEDIAN(CONV_FLOOR,BASE_CONVERSION-ELAST_MARKET*(CURRENT_FLAT*(1+LOSS_TREND)^0/N35-1),CONV_CEIL) -> 0.02 | R35: =IF($J35=0,0,IF($J35=4,$H35*GRAD_CONTINUE,$H34)*P35) -> 0 | S35: =APPLICANTS_PER_YEAR*($H35/Segments!$AH$2)*Q35 -> 8.352 | T35: =R35+S35 -> 8.352 | U35: =IFERROR((R35*O35+S35*CURRENT_FLAT*(1+LOSS_TREND)^0)/T35,M35) -> 1426.2298 | V35: =R35*O35+S35*CURRENT_FLAT*(1+LOSS_TREND)^0 -> 11911.871 | W35: =T35*L35*(1+LAE_RATIO) -> 2685.608 | X35: =R35*O35*(PREMIUM_TAX+OTHER_VARIABLE+COMMISSION_RN)+S35*CURRENT_FLAT*(1+LOSS_TREND)^0*(PREMIUM_TAX+OTHER_VARIABLE+COMMISSION_NB)+T35*FIXED_PER_POLICY+S35*NB_ACQUISITION -> 3044.0991 | Y35: =IF($J35=0,AA35,IF($J35=4,U35,U34)) -> 522.52008 | Z35: =$I35*(1+LOSS_TREND)^1 -> 295.71363 | AA35: =Z35*GROSS_MULT+POLICY_FEE -> 522.52008 | AB35: =AA35^MARKET_RISK_WEIGHT*(CURRENT_FLAT*(1+LOSS_TREND)^1)^(1-MARKET_RISK_WEIGHT) -> 876.12254 | AC35: =CURRENT_FLAT*(1+LOSS_TREND)^1 -> 1469.0167 | AD35: =MEDIAN(RET_FLOOR,BASE_RETENTION-ELAST_MARKET*(AC35/AB35-1)-ELAST_INCREASE*MAX(AC35/Y35-1,0),RET_CEIL) -> 0.3 | AE35: =MEDIAN(CONV_FLOOR,BASE_CONVERSION-ELAST_MARKET*(CURRENT_FLAT*(1+LOSS_TREND)^1/AB35-1),CONV_CEIL) -> 0.02 | AF35: =IF($J35=0,0,IF($J35=4,T35*GRAD_CONTINUE,T34)*AD35) -> 0 | AG35: =APPLICANTS_PER_YEAR*($H35/Segments!$AH$2)*AE35 -> 8.352 | AH35: =AF35+AG35 -> 8.352 | AI35: =IFERROR((AF35*AC35+AG35*CURRENT_FLAT*(1+LOSS_TREND)^1)/AH35,AA35) -> 1469.0167 | AJ35: =AF35*AC35+AG35*CURRENT_FLAT*(1+LOSS_TREND)^1 -> 12269.227 | AK35: =AH35*Z35*(1+LAE_RATIO) -> 2766.1762 | AL35: =AF35*AC35*(PREMIUM_TAX+OTHER_VARIABLE+COMMISSION_RN)+AG35*CURRENT_FLAT*(1+LOSS_TREND)^1*(PREMIUM_TAX+OTHER_VARIABLE+COMMISSION_NB)+AH35*FIXED_PER_POLICY+AG35*NB_ACQUISITION -> 3124.1469 | AM35: =IF($J35=0,AO35,IF($J35=4,AI35,AI34)) -> 536.94568 | AN35: =$I35*(1+LOSS_TREND)^2 -> 304.58504 | AO35: =AN35*GROSS_MULT+POLICY_FEE -> 536.94568 | AP35: =AO35^MARKET_RISK_WEIGHT*(CURRENT_FLAT*(1+LOSS_TREND)^2)^(1-MARKET_RISK_WEIGHT) -> 901.35765 | AQ35: =CURRENT_FLAT*(1+LOSS_TREND)^2 -> 1513.0872 | AR35: =MEDIAN(RET_FLOOR,BASE_RETENTION-ELAST_MARKET*(AQ35/AP35-1)-ELAST_INCREASE*MAX(AQ35/AM35-1,0),RET_CEIL) -> 0.3 | AS35: =MEDIAN(CONV_FLOOR,BASE_CONVERSION-ELAST_MARKET*(CURRENT_FLAT*(1+LOSS_TREND)^2/AP35-1),CONV_CEIL) -> 0.02 | AT35: =IF($J35=0,0,IF($J35=4,AH35*GRAD_CONTINUE,AH34)*AR35) -> 0 | AU35: =APPLICANTS_PER_YEAR*($H35/Segments!$AH$2)*AS35 -> 8.352 | AV35: =AT35+AU35 -> 8.352 | AW35: =IFERROR((AT35*AQ35+AU35*CURRENT_FLAT*(1+LOSS_TREND)^2)/AV35,AO35) -> 1513.0872 | AX35: =AT35*AQ35+AU35*CURRENT_FLAT*(1+LOSS_TREND)^2 -> 12637.304 | AY35: =AV35*AN35*(1+LAE_RATIO) -> 2849.1615 | AZ35: =AT35*AQ35*(PREMIUM_TAX+OTHER_VARIABLE+COMMISSION_RN)+AU35*CURRENT_FLAT*(1+LOSS_TREND)^2*(PREMIUM_TAX+OTHER_VARIABLE+COMMISSION_NB)+AV35*FIXED_PER_POLICY+AU35*NB_ACQUISITION -> 3206.5961
A36: =Segments!$A$16 -> Non-greek | B36: =Segments!$B$16 -> On campus | C36: =Segments!$C$16 -> Yes | D36: =Segments!$D$16 -> 2.0-3.0 | E36: =Segments!$E$16 -> Sophomore | F36: =Segments!$F$16 -> 1 | G36: =Segments!$G$16 -> Sophomore | H36: =Segments!$H$16 -> 328 | I36: =Segments!$Y$16 -> 284.17972 | J36: 1 | K36: =IF($J36=0,M36,CURRENT_FLAT) -> 1426.2298 | L36: =$I36*(1+LOSS_TREND)^0 -> 284.17972 | M36: =L36*GROSS_MULT+POLICY_FEE -> 503.76504 | N36: =M36^MARKET_RISK_WEIGHT*(CURRENT_FLAT*(1+LOSS_TREND)^0)^(1-MARKET_RISK_WEIGHT) -> 847.63477 | O36: =CURRENT_FLAT*(1+LOSS_TREND)^0 -> 1426.2298 | P36: =MEDIAN(RET_FLOOR,BASE_RETENTION-ELAST_MARKET*(O36/N36-1)-ELAST_INCREASE*MAX(O36/K36-1,0),RET_CEIL) -> 0.50870029 | Q36: =MEDIAN(CONV_FLOOR,BASE_CONVERSION-ELAST_MARKET*(CURRENT_FLAT*(1+LOSS_TREND)^0/N36-1),CONV_CEIL) -> 0.02 | R36: =IF($J36=0,0,IF($J36=4,$H36*GRAD_CONTINUE,$H35)*P36) -> 177.0277 | S36: =APPLICANTS_PER_YEAR*($H36/Segments!$AH$2)*Q36 -> 7.872 | T36: =R36+S36 -> 184.8997 | U36: =IFERROR((R36*O36+S36*CURRENT_FLAT*(1+LOSS_TREND)^0)/T36,M36) -> 1426.2298 | V36: =R36*O36+S36*CURRENT_FLAT*(1+LOSS_TREND)^0 -> 263709.46 | W36: =T36*L36*(1+LAE_RATIO) -> 58850.114 | X36: =R36*O36*(PREMIUM_TAX+OTHER_VARIABLE+COMMISSION_RN)+S36*CURRENT_FLAT*(1+LOSS_TREND)^0*(PREMIUM_TAX+OTHER_VARIABLE+COMMISSION_NB)+T36*FIXED_PER_POLICY+S36*NB_ACQUISITION -> 54128.836 | Y36: =IF($J36=0,AA36,IF($J36=4,U36,U35)) -> 1426.2298 | Z36: =$I36*(1+LOSS_TREND)^1 -> 292.70511 | AA36: =Z36*GROSS_MULT+POLICY_FEE -> 517.62799 | AB36: =AA36^MARKET_RISK_WEIGHT*(CURRENT_FLAT*(1+LOSS_TREND)^1)^(1-MARKET_RISK_WEIGHT) -> 872.01155 | AC36: =CURRENT_FLAT*(1+LOSS_TREND)^1 -> 1469.0167 | AD36: =MEDIAN(RET_FLOOR,BASE_RETENTION-ELAST_MARKET*(AC36/AB36-1)-ELAST_INCREASE*MAX(AC36/Y36-1,0),RET_CEIL) -> 0.49868509 | AE36: =MEDIAN(CONV_FLOOR,BASE_CONVERSION-ELAST_MARKET*(CURRENT_FLAT*(1+LOSS_TREND)^1/AB36-1),CONV_CEIL) -> 0.02 | AF36: =IF($J36=0,0,IF($J36=4,T36*GRAD_CONTINUE,T35)*AD36) -> 4.1650179 | AG36: =APPLICANTS_PER_YEAR*($H36/Segments!$AH$2)*AE36 -> 7.872 | AH36: =AF36+AG36 -> 12.037018 | AI36: =IFERROR((AF36*AC36+AG36*CURRENT_FLAT*(1+LOSS_TREND)^1)/AH36,AA36) -> 1469.0167 | AJ36: =AF36*AC36+AG36*CURRENT_FLAT*(1+LOSS_TREND)^1 -> 17682.58 | AK36: =AH36*Z36*(1+LAE_RATIO) -> 3946.0922 | AL36: =AF36*AC36*(PREMIUM_TAX+OTHER_VARIABLE+COMMISSION_RN)+AG36*CURRENT_FLAT*(1+LOSS_TREND)^1*(PREMIUM_TAX+OTHER_VARIABLE+COMMISSION_NB)+AH36*FIXED_PER_POLICY+AG36*NB_ACQUISITION -> 4184.2914 | AM36: =IF($J36=0,AO36,IF($J36=4,AI36,AI35)) -> 1469.0167 | AN36: =$I36*(1+LOSS_TREND)^2 -> 301.48626 | AO36: =AN36*GROSS_MULT+POLICY_FEE -> 531.90683 | AP36: =AO36^MARKET_RISK_WEIGHT*(CURRENT_FLAT*(1+LOSS_TREND)^2)^(1-MARKET_RISK_WEIGHT) -> 897.11839 | AQ36: =CURRENT_FLAT*(1+LOSS_TREND)^2 -> 1513.0872 | AR36: =MEDIAN(RET_FLOOR,BASE_RETENTION-ELAST_MARKET*(AQ36/AP36-1)-ELAST_INCREASE*MAX(AQ36/AM36-1,0),RET_CEIL) -> 0.49769593 | AS36: =MEDIAN(CONV_FLOOR,BASE_CONVERSION-ELAST_MARKET*(CURRENT_FLAT*(1+LOSS_TREND)^2/AP36-1),CONV_CEIL) -> 0.02 | AT36: =IF($J36=0,0,IF($J36=4,AH36*GRAD_CONTINUE,AH35)*AR36) -> 4.1567564 | AU36: =APPLICANTS_PER_YEAR*($H36/Segments!$AH$2)*AS36 -> 7.872 | AV36: =AT36+AU36 -> 12.028756 | AW36: =IFERROR((AT36*AQ36+AU36*CURRENT_FLAT*(1+LOSS_TREND)^2)/AV36,AO36) -> 1513.0872 | AX36: =AT36*AQ36+AU36*CURRENT_FLAT*(1+LOSS_TREND)^2 -> 18200.557 | AY36: =AV36*AN36*(1+LAE_RATIO) -> 4061.6854 | AZ36: =AT36*AQ36*(PREMIUM_TAX+OTHER_VARIABLE+COMMISSION_RN)+AU36*CURRENT_FLAT*(1+LOSS_TREND)^2*(PREMIUM_TAX+OTHER_VARIABLE+COMMISSION_NB)+AV36*FIXED_PER_POLICY+AU36*NB_ACQUISITION -> 4294.1662
A37: =Segments!$A$17 -> Non-greek | B37: =Segments!$B$17 -> On campus | C37: =Segments!$C$17 -> Yes | D37: =Segments!$D$17 -> 2.0-3.0 | E37: =Segments!$E$17 -> Junior | F37: =Segments!$F$17 -> 2 | G37: =Segments!$G$17 -> Base | H37: =Segments!$H$17 -> 358 | I37: =Segments!$Y$17 -> 339.71571 | J37: 2 | K37: =IF($J37=0,M37,CURRENT_FLAT) -> 1426.2298 | L37: =$I37*(1+LOSS_TREND)^0 -> 339.71571 | M37: =L37*GROSS_MULT+POLICY_FEE -> 594.0709 | N37: =M37^MARKET_RISK_WEIGHT*(CURRENT_FLAT*(1+LOSS_TREND)^0)^(1-MARKET_RISK_WEIGHT) -> 920.47901 | O37: =CURRENT_FLAT*(1+LOSS_TREND)^0 -> 1426.2298 | P37: =MEDIAN(RET_FLOOR,BASE_RETENTION-ELAST_MARKET*(O37/N37-1)-ELAST_INCREASE*MAX(O37/K37-1,0),RET_CEIL) -> 0.57527849 | Q37: =MEDIAN(CONV_FLOOR,BASE_CONVERSION-ELAST_MARKET*(CURRENT_FLAT*(1+LOSS_TREND)^0/N37-1),CONV_CEIL) -> 0.075278492 | R37: =IF($J37=0,0,IF($J37=4,$H37*GRAD_CONTINUE,$H36)*P37) -> 188.69135 | S37: =APPLICANTS_PER_YEAR*($H37/Segments!$AH$2)*Q37 -> 32.33964 | T37: =R37+S37 -> 221.03099 | U37: =IFERROR((R37*O37+S37*CURRENT_FLAT*(1+LOSS_TREND)^0)/T37,M37) -> 1426.2298 | V37: =R37*O37+S37*CURRENT_FLAT*(1+LOSS_TREND)^0 -> 315240.97 | W37: =T37*L37*(1+LAE_RATIO) -> 84098.223 | X37: =R37*O37*(PREMIUM_TAX+OTHER_VARIABLE+COMMISSION_RN)+S37*CURRENT_FLAT*(1+LOSS_TREND)^0*(PREMIUM_TAX+OTHER_VARIABLE+COMMISSION_NB)+T37*FIXED_PER_POLICY+S37*NB_ACQUISITION -> 66423.986 | Y37: =IF($J37=0,AA37,IF($J37=4,U37,U36)) -> 1426.2298 | Z37: =$I37*(1+LOSS_TREND)^1 -> 349.90719 | AA37: =Z37*GROSS_MULT+POLICY_FEE -> 610.64303 | AB37: =AA37^MARKET_RISK_WEIGHT*(CURRENT_FLAT*(1+LOSS_TREND)^1)^(1-MARKET_RISK_WEIGHT) -> 947.12448 | AC37: =CURRENT_FLAT*(1+LOSS_TREND)^1 -> 1469.0167 | AD37: =MEDIAN(RET_FLOOR,BASE_RETENTION-ELAST_MARKET*(AC37/AB37-1)-ELAST_INCREASE*MAX(AC37/Y37-1,0),RET_CEIL) -> 0.56548596 | AE37: =MEDIAN(CONV_FLOOR,BASE_CONVERSION-ELAST_MARKET*(CURRENT_FLAT*(1+LOSS_TREND)^1/AB37-1),CONV_CEIL) -> 0.074485961 | AF37: =IF($J37=0,0,IF($J37=4,T37*GRAD_CONTINUE,T36)*AD37) -> 104.55818 | AG37: =APPLICANTS_PER_YEAR*($H37/Segments!$AH$2)*AE37 -> 31.999169 | AH37: =AF37+AG37 -> 136.55735 | AI37: =IFERROR((AF37*AC37+AG37*CURRENT_FLAT*(1+LOSS_TREND)^1)/AH37,AA37) -> 1469.0167 | AJ37: =AF37*AC37+AG37*CURRENT_FLAT*(1+LOSS_TREND)^1 -> 200605.03 | AK37: =AH37*Z37*(1+LAE_RATIO) -> 53516.287 | AL37: =AF37*AC37*(PREMIUM_TAX+OTHER_VARIABLE+COMMISSION_RN)+AG37*CURRENT_FLAT*(1+LOSS_TREND)^1*(PREMIUM_TAX+OTHER_VARIABLE+COMMISSION_NB)+AH37*FIXED_PER_POLICY+AG37*NB_ACQUISITION -> 43090.733 | AM37: =IF($J37=0,AO37,IF($J37=4,AI37,AI36)) -> 1469.0167 | AN37: =$I37*(1+LOSS_TREND)^2 -> 360.4044 | AO37: =AN37*GROSS_MULT+POLICY_FEE -> 627.71232 | AP37: =AO37^MARKET_RISK_WEIGHT*(CURRENT_FLAT*(1+LOSS_TREND)^2)^(1-MARKET_RISK_WEIGHT) -> 974.56834 | AQ37: =CURRENT_FLAT*(1+LOSS_TREND)^2 -> 1513.0872 | AR37: =MEDIAN(RET_FLOOR,BASE_RETENTION-ELAST_MARKET*(AQ37/AP37-1)-ELAST_INCREASE*MAX(AQ37/AM37-1,0),RET_CEIL) -> 0.56471418 | AS37: =MEDIAN(CONV_FLOOR,BASE_CONVERSION-ELAST_MARKET*(CURRENT_FLAT*(1+LOSS_TREND)^2/AP37-1),CONV_CEIL) -> 0.073714182 | AT37: =IF($J37=0,0,IF($J37=4,AH37*GRAD_CONTINUE,AH36)*AR37) -> 6.7974747 | AU37: =APPLICANTS_PER_YEAR*($H37/Segments!$AH$2)*AS37 -> 31.667613 | AV37: =AT37+AU37 -> 38.465087 | AW37: =IFERROR((AT37*AQ37+AU37*CURRENT_FLAT*(1+LOSS_TREND)^2)/AV37,AO37) -> 1513.0872 | AX37: =AT37*AQ37+AU37*CURRENT_FLAT*(1+LOSS_TREND)^2 -> 58201.03 | AY37: =AV37*AN37*(1+LAE_RATIO) -> 15526.545 | AZ37: =AT37*AQ37*(PREMIUM_TAX+OTHER_VARIABLE+COMMISSION_RN)+AU37*CURRENT_FLAT*(1+LOSS_TREND)^2*(PREMIUM_TAX+OTHER_VARIABLE+COMMISSION_NB)+AV37*FIXED_PER_POLICY+AU37*NB_ACQUISITION -> 14238.042
A38: =Segments!$A$18 -> Non-greek | B38: =Segments!$B$18 -> On campus | C38: =Segments!$C$18 -> Yes | D38: =Segments!$D$18 -> 2.0-3.0 | E38: =Segments!$E$18 -> Senior | F38: =Segments!$F$18 -> 3 | G38: =Segments!$G$18 -> Base | H38: =Segments!$H$18 -> 343 | I38: =Segments!$Y$18 -> 317.52802 | J38: 3 | K38: =IF($J38=0,M38,CURRENT_FLAT) -> 1426.2298 | L38: =$I38*(1+LOSS_TREND)^0 -> 317.52802 | M38: =L38*GROSS_MULT+POLICY_FEE -> 557.99198 | N38: =M38^MARKET_RISK_WEIGHT*(CURRENT_FLAT*(1+LOSS_TREND)^0)^(1-MARKET_RISK_WEIGHT) -> 892.09011 | O38: =CURRENT_FLAT*(1+LOSS_TREND)^0 -> 1426.2298 | P38: =MEDIAN(RET_FLOOR,BASE_RETENTION-ELAST_MARKET*(O38/N38-1)-ELAST_INCREASE*MAX(O38/K38-1,0),RET_CEIL) -> 0.55062461 | Q38: =MEDIAN(CONV_FLOOR,BASE_CONVERSION-ELAST_MARKET*(CURRENT_FLAT*(1+LOSS_TREND)^0/N38-1),CONV_CEIL) -> 0.050624605 | R38: =IF($J38=0,0,IF($J38=4,$H38*GRAD_CONTINUE,$H37)*P38) -> 197.12361 | S38: =APPLICANTS_PER_YEAR*($H38/Segments!$AH$2)*Q38 -> 20.837087 | T38: =R38+S38 -> 217.9607 | U38: =IFERROR((R38*O38+S38*CURRENT_FLAT*(1+LOSS_TREND)^0)/T38,M38) -> 1426.2298 | V38: =R38*O38+S38*CURRENT_FLAT*(1+LOSS_TREND)^0 -> 310862.03 | W38: =T38*L38*(1+LAE_RATIO) -> 77513.663 | X38: =R38*O38*(PREMIUM_TAX+OTHER_VARIABLE+COMMISSION_RN)+S38*CURRENT_FLAT*(1+LOSS_TREND)^0*(PREMIUM_TAX+OTHER_VARIABLE+COMMISSION_NB)+T38*FIXED_PER_POLICY+S38*NB_ACQUISITION -> 64673.212 | Y38: =IF($J38=0,AA38,IF($J38=4,U38,U37)) -> 1426.2298 | Z38: =$I38*(1+LOSS_TREND)^1 -> 327.05386 | AA38: =Z38*GROSS_MULT+POLICY_FEE -> 573.48174 | AB38: =AA38^MARKET_RISK_WEIGHT*(CURRENT_FLAT*(1+LOSS_TREND)^1)^(1-MARKET_RISK_WEIGHT) -> 917.85305 | AC38: =CURRENT_FLAT*(1+LOSS_TREND)^1 -> 1469.0167 | AD38: =MEDIAN(RET_FLOOR,BASE_RETENTION-ELAST_MARKET*(AC38/AB38-1)-ELAST_INCREASE*MAX(AC38/Y38-1,0),RET_CEIL) -> 0.54075389 | AE38: =MEDIAN(CONV_FLOOR,BASE_CONVERSION-ELAST_MARKET*(CURRENT_FLAT*(1+LOSS_TREND)^1/AB38-1),CONV_CEIL) -> 0.049753893 | AF38: =IF($J38=0,0,IF($J38=4,T38*GRAD_CONTINUE,T37)*AD38) -> 119.52337 | AG38: =APPLICANTS_PER_YEAR*($H38/Segments!$AH$2)*AE38 -> 20.478702 | AH38: =AF38+AG38 -> 140.00207 | AI38: =IFERROR((AF38*AC38+AG38*CURRENT_FLAT*(1+LOSS_TREND)^1)/AH38,AA38) -> 1469.0167 | AJ38: =AF38*AC38+AG38*CURRENT_FLAT*(1+LOSS_TREND)^1 -> 205665.37 | AK38: =AH38*Z38*(1+LAE_RATIO) -> 51282.802 | AL38: =AF38*AC38*(PREMIUM_TAX+OTHER_VARIABLE+COMMISSION_RN)+AG38*CURRENT_FLAT*(1+LOSS_TREND)^1*(PREMIUM_TAX+OTHER_VARIABLE+COMMISSION_NB)+AH38*FIXED_PER_POLICY+AG38*NB_ACQUISITION -> 43235.689 | AM38: =IF($J38=0,AO38,IF($J38=4,AI38,AI37)) -> 1469.0167 | AN38: =$I38*(1+LOSS_TREND)^2 -> 336.86547 | AO38: =AN38*GROSS_MULT+POLICY_FEE -> 589.43619 | AP38: =AO38^MARKET_RISK_WEIGHT*(CURRENT_FLAT*(1+LOSS_TREND)^2)^(1-MARKET_RISK_WEIGHT) -> 944.38781 | AQ38: =CURRENT_FLAT*(1+LOSS_TREND)^2 -> 1513.0872 | AR38: =MEDIAN(RET_FLOOR,BASE_RETENTION-ELAST_MARKET*(AQ38/AP38-1)-ELAST_INCREASE*MAX(AQ38/AM38-1,0),RET_CEIL) -> 0.53990581 | AS38: =MEDIAN(CONV_FLOOR,BASE_CONVERSION-ELAST_MARKET*(CURRENT_FLAT*(1+LOSS_TREND)^2/AP38-1),CONV_CEIL) -> 0.048905813 | AT38: =IF($J38=0,0,IF($J38=4,AH38*GRAD_CONTINUE,AH37)*AR38) -> 73.728109 | AU38: =APPLICANTS_PER_YEAR*($H38/Segments!$AH$2)*AS38 -> 20.129633 | AV38: =AT38+AU38 -> 93.857741 | AW38: =IFERROR((AT38*AQ38+AU38*CURRENT_FLAT*(1+LOSS_TREND)^2)/AV38,AO38) -> 1513.0872 | AX38: =AT38*AQ38+AU38*CURRENT_FLAT*(1+LOSS_TREND)^2 -> 142014.94 | AY38: =AV38*AN38*(1+LAE_RATIO) -> 35411.524 | AZ38: =AT38*AQ38*(PREMIUM_TAX+OTHER_VARIABLE+COMMISSION_RN)+AU38*CURRENT_FLAT*(1+LOSS_TREND)^2*(PREMIUM_TAX+OTHER_VARIABLE+COMMISSION_NB)+AV38*FIXED_PER_POLICY+AU38*NB_ACQUISITION -> 30287.246
A39: =Segments!$A$19 -> Non-greek | B39: =Segments!$B$19 -> On campus | C39: =Segments!$C$19 -> Yes | D39: =Segments!$D$19 -> 2.0-3.0 | E39: =Segments!$E$19 -> Grad student | F39: =Segments!$F$19 -> 3 | G39: =Segments!$G$19 -> Grad | H39: =Segments!$H$19 -> 146 | I39: =Segments!$Y$19 -> 378.0744 | J39: 4 | K39: =IF($J39=0,M39,CURRENT_FLAT) -> 1426.2298 | L39: =$I39*(1+LOSS_TREND)^0 -> 378.0744 | M39: =L39*GROSS_MULT+POLICY_FEE -> 656.44511 | N39: =M39^MARKET_RISK_WEIGHT*(CURRENT_FLAT*(1+LOSS_TREND)^0)^(1-MARKET_RISK_WEIGHT) -> 967.59576 | O39: =CURRENT_FLAT*(1+LOSS_TREND)^0 -> 1426.2298 | P39: =MEDIAN(RET_FLOOR,BASE_RETENTION-ELAST_MARKET*(O39/N39-1)-ELAST_INCREASE*MAX(O39/K39-1,0),RET_CEIL) -> 0.6130033 | Q39: =MEDIAN(CONV_FLOOR,BASE_CONVERSION-ELAST_MARKET*(CURRENT_FLAT*(1+LOSS_TREND)^0/N39-1),CONV_CEIL) -> 0.1130033 | R39: =IF($J39=0,0,IF($J39=4,$H39*GRAD_CONTINUE,$H38)*P39) -> 44.749241 | S39: =APPLICANTS_PER_YEAR*($H39/Segments!$AH$2)*Q39 -> 19.798177 | T39: =R39+S39 -> 64.547418 | U39: =IFERROR((R39*O39+S39*CURRENT_FLAT*(1+LOSS_TREND)^0)/T39,M39) -> 1426.2298 | V39: =R39*O39+S39*CURRENT_FLAT*(1+LOSS_TREND)^0 -> 92059.45 | W39: =T39*L39*(1+LAE_RATIO) -> 27332.173 | X39: =R39*O39*(PREMIUM_TAX+OTHER_VARIABLE+COMMISSION_RN)+S39*CURRENT_FLAT*(1+LOSS_TREND)^0*(PREMIUM_TAX+OTHER_VARIABLE+COMMISSION_NB)+T39*FIXED_PER_POLICY+S39*NB_ACQUISITION -> 20173.425 | Y39: =IF($J39=0,AA39,IF($J39=4,U39,U38)) -> 1426.2298 | Z39: =$I39*(1+LOSS_TREND)^1 -> 389.41663 | AA39: =Z39*GROSS_MULT+POLICY_FEE -> 674.88846 | AB39: =AA39^MARKET_RISK_WEIGHT*(CURRENT_FLAT*(1+LOSS_TREND)^1)^(1-MARKET_RISK_WEIGHT) -> 995.70196 | AC39: =CURRENT_FLAT*(1+LOSS_TREND)^1 -> 1469.0167 | AD39: =MEDIAN(RET_FLOOR,BASE_RETENTION-ELAST_MARKET*(AC39/AB39-1)-ELAST_INCREASE*MAX(AC39/Y39-1,0),RET_CEIL) -> 0.60332109 | AE39: =MEDIAN(CONV_FLOOR,BASE_CONVERSION-ELAST_MARKET*(CURRENT_FLAT*(1+LOSS_TREND)^1/AB39-1),CONV_CEIL) -> 0.11232109 | AF39: =IF($J39=0,0,IF($J39=4,T39*GRAD_CONTINUE,T38)*AD39) -> 19.471409 | AG39: =APPLICANTS_PER_YEAR*($H39/Segments!$AH$2)*AE39 -> 19.678656 | AH39: =AF39+AG39 -> 39.150065 | AI39: =IFERROR((AF39*AC39+AG39*CURRENT_FLAT*(1+LOSS_TREND)^1)/AH39,AA39) -> 1469.0167 | AJ39: =AF39*AC39+AG39*CURRENT_FLAT*(1+LOSS_TREND)^1 -> 57512.098 | AK39: =AH39*Z39*(1+LAE_RATIO) -> 17075.169 | AL39: =AF39*AC39*(PREMIUM_TAX+OTHER_VARIABLE+COMMISSION_RN)+AG39*CURRENT_FLAT*(1+LOSS_TREND)^1*(PREMIUM_TAX+OTHER_VARIABLE+COMMISSION_NB)+AH39*FIXED_PER_POLICY+AG39*NB_ACQUISITION -> 13156.544 | AM39: =IF($J39=0,AO39,IF($J39=4,AI39,AI38)) -> 1469.0167 | AN39: =$I39*(1+LOSS_TREND)^2 -> 401.09913 | AO39: =AN39*GROSS_MULT+POLICY_FEE -> 693.88512 | AP39: =AO39^MARKET_RISK_WEIGHT*(CURRENT_FLAT*(1+LOSS_TREND)^2)^(1-MARKET_RISK_WEIGHT) -> 1024.6505 | AQ39: =CURRENT_FLAT*(1+LOSS_TREND)^2 -> 1513.0872 | AR39: =MEDIAN(RET_FLOOR,BASE_RETENTION-ELAST_MARKET*(AQ39/AP39-1)-ELAST_INCREASE*MAX(AQ39/AM39-1,0),RET_CEIL) -> 0.60265695 | AS39: =MEDIAN(CONV_FLOOR,BASE_CONVERSION-ELAST_MARKET*(CURRENT_FLAT*(1+LOSS_TREND)^2/AP39-1),CONV_CEIL) -> 0.11165695 | AT39: =IF($J39=0,0,IF($J39=4,AH39*GRAD_CONTINUE,AH38)*AR39) -> 11.797029 | AU39: =APPLICANTS_PER_YEAR*($H39/Segments!$AH$2)*AS39 -> 19.562297 | AV39: =AT39+AU39 -> 31.359327 | AW39: =IFERROR((AT39*AQ39+AU39*CURRENT_FLAT*(1+LOSS_TREND)^2)/AV39,AO39) -> 1513.0872 | AX39: =AT39*AQ39+AU39*CURRENT_FLAT*(1+LOSS_TREND)^2 -> 47449.395 | AY39: =AV39*AN39*(1+LAE_RATIO) -> 14087.582 | AZ39: =AT39*AQ39*(PREMIUM_TAX+OTHER_VARIABLE+COMMISSION_RN)+AU39*CURRENT_FLAT*(1+LOSS_TREND)^2*(PREMIUM_TAX+OTHER_VARIABLE+COMMISSION_NB)+AV39*FIXED_PER_POLICY+AU39*NB_ACQUISITION -> 11120.161
A40: =Segments!$A$20 -> Non-greek | B40: =Segments!$B$20 -> On campus | C40: =Segments!$C$20 -> Yes | D40: =Segments!$D$20 -> 3.0+ | E40: =Segments!$E$20 -> Freshman | F40: =Segments!$F$20 -> 1 | G40: =Segments!$G$20 -> Base | H40: =Segments!$H$20 -> 217 | I40: =Segments!$Y$20 -> 251.65735 | J40: 0 | K40: =IF($J40=0,M40,CURRENT_FLAT) -> 450.88114 | L40: =$I40*(1+LOSS_TREND)^0 -> 251.65735 | M40: =L40*GROSS_MULT+POLICY_FEE -> 450.88114 | N40: =M40^MARKET_RISK_WEIGHT*(CURRENT_FLAT*(1+LOSS_TREND)^0)^(1-MARKET_RISK_WEIGHT) -> 801.91029 | O40: =CURRENT_FLAT*(1+LOSS_TREND)^0 -> 1426.2298 | P40: =MEDIAN(RET_FLOOR,BASE_RETENTION-ELAST_MARKET*(O40/N40-1)-ELAST_INCREASE*MAX(O40/K40-1,0),RET_CEIL) -> 0.3 | Q40: =MEDIAN(CONV_FLOOR,BASE_CONVERSION-ELAST_MARKET*(CURRENT_FLAT*(1+LOSS_TREND)^0/N40-1),CONV_CEIL) -> 0.02 | R40: =IF($J40=0,0,IF($J40=4,$H40*GRAD_CONTINUE,$H39)*P40) -> 0 | S40: =APPLICANTS_PER_YEAR*($H40/Segments!$AH$2)*Q40 -> 5.208 | T40: =R40+S40 -> 5.208 | U40: =IFERROR((R40*O40+S40*CURRENT_FLAT*(1+LOSS_TREND)^0)/T40,M40) -> 1426.2298 | V40: =R40*O40+S40*CURRENT_FLAT*(1+LOSS_TREND)^0 -> 7427.8047 | W40: =T40*L40*(1+LAE_RATIO) -> 1467.9073 | X40: =R40*O40*(PREMIUM_TAX+OTHER_VARIABLE+COMMISSION_RN)+S40*CURRENT_FLAT*(1+LOSS_TREND)^0*(PREMIUM_TAX+OTHER_VARIABLE+COMMISSION_NB)+T40*FIXED_PER_POLICY+S40*NB_ACQUISITION -> 1898.1882 | Y40: =IF($J40=0,AA40,IF($J40=4,U40,U39)) -> 463.15758 | Z40: =$I40*(1+LOSS_TREND)^1 -> 259.20707 | AA40: =Z40*GROSS_MULT+POLICY_FEE -> 463.15758 | AB40: =AA40^MARKET_RISK_WEIGHT*(CURRENT_FLAT*(1+LOSS_TREND)^1)^(1-MARKET_RISK_WEIGHT) -> 824.85526 | AC40: =CURRENT_FLAT*(1+LOSS_TREND)^1 -> 1469.0167 | AD40: =MEDIAN(RET_FLOOR,BASE_RETENTION-ELAST_MARKET*(AC40/AB40-1)-ELAST_INCREASE*MAX(AC40/Y40-1,0),RET_CEIL) -> 0.3 | AE40: =MEDIAN(CONV_FLOOR,BASE_CONVERSION-ELAST_MARKET*(CURRENT_FLAT*(1+LOSS_TREND)^1/AB40-1),CONV_CEIL) -> 0.02 | AF40: =IF($J40=0,0,IF($J40=4,T40*GRAD_CONTINUE,T39)*AD40) -> 0 | AG40: =APPLICANTS_PER_YEAR*($H40/Segments!$AH$2)*AE40 -> 5.208 | AH40: =AF40+AG40 -> 5.208 | AI40: =IFERROR((AF40*AC40+AG40*CURRENT_FLAT*(1+LOSS_TREND)^1)/AH40,AA40) -> 1469.0167 | AJ40: =AF40*AC40+AG40*CURRENT_FLAT*(1+LOSS_TREND)^1 -> 7650.6388 | AK40: =AH40*Z40*(1+LAE_RATIO) -> 1511.9445 | AL40: =AF40*AC40*(PREMIUM_TAX+OTHER_VARIABLE+COMMISSION_RN)+AG40*CURRENT_FLAT*(1+LOSS_TREND)^1*(PREMIUM_TAX+OTHER_VARIABLE+COMMISSION_NB)+AH40*FIXED_PER_POLICY+AG40*NB_ACQUISITION -> 1948.1031 | AM40: =IF($J40=0,AO40,IF($J40=4,AI40,AI39)) -> 475.80231 | AN40: =$I40*(1+LOSS_TREND)^2 -> 266.98329 | AO40: =AN40*GROSS_MULT+POLICY_FEE -> 475.80231 | AP40: =AO40^MARKET_RISK_WEIGHT*(CURRENT_FLAT*(1+LOSS_TREND)^2)^(1-MARKET_RISK_WEIGHT) -> 848.4871 | AQ40: =CURRENT_FLAT*(1+LOSS_TREND)^2 -> 1513.0872 | AR40: =MEDIAN(RET_FLOOR,BASE_RETENTION-ELAST_MARKET*(AQ40/AP40-1)-ELAST_INCREASE*MAX(AQ40/AM40-1,0),RET_CEIL) -> 0.3 | AS40: =MEDIAN(CONV_FLOOR,BASE_CONVERSION-ELAST_MARKET*(CURRENT_FLAT*(1+LOSS_TREND)^2/AP40-1),CONV_CEIL) -> 0.02 | AT40: =IF($J40=0,0,IF($J40=4,AH40*GRAD_CONTINUE,AH39)*AR40) -> 0 | AU40: =APPLICANTS_PER_YEAR*($H40/Segments!$AH$2)*AS40 -> 5.208 | AV40: =AT40+AU40 -> 5.208 | AW40: =IFERROR((AT40*AQ40+AU40*CURRENT_FLAT*(1+LOSS_TREND)^2)/AV40,AO40) -> 1513.0872 | AX40: =AT40*AQ40+AU40*CURRENT_FLAT*(1+LOSS_TREND)^2 -> 7880.158 | AY40: =AV40*AN40*(1+LAE_RATIO) -> 1557.3028 | AZ40: =AT40*AQ40*(PREMIUM_TAX+OTHER_VARIABLE+COMMISSION_RN)+AU40*CURRENT_FLAT*(1+LOSS_TREND)^2*(PREMIUM_TAX+OTHER_VARIABLE+COMMISSION_NB)+AV40*FIXED_PER_POLICY+AU40*NB_ACQUISITION -> 1999.5154
A41: =Segments!$A$21 -> Non-greek | B41: =Segments!$B$21 -> On campus | C41: =Segments!$C$21 -> Yes | D41: =Segments!$D$21 -> 3.0+ | E41: =Segments!$E$21 -> Sophomore | F41: =Segments!$F$21 -> 1 | G41: =Segments!$G$21 -> Sophomore | H41: =Segments!$H$21 -> 216 | I41: =Segments!$Y$21 -> 249.09705 | J41: 1 | K41: =IF($J41=0,M41,CURRENT_FLAT) -> 1426.2298 | L41: =$I41*(1+LOSS_TREND)^0 -> 249.09705 | M41: =L41*GROSS_MULT+POLICY_FEE -> 446.7179 | N41: =M41^MARKET_RISK_WEIGHT*(CURRENT_FLAT*(1+LOSS_TREND)^0)^(1-MARKET_RISK_WEIGHT) -> 798.19945 | O41: =CURRENT_FLAT*(1+LOSS_TREND)^0 -> 1426.2298 | P41: =MEDIAN(RET_FLOOR,BASE_RETENTION-ELAST_MARKET*(O41/N41-1)-ELAST_INCREASE*MAX(O41/K41-1,0),RET_CEIL) -> 0.45659562 | Q41: =MEDIAN(CONV_FLOOR,BASE_CONVERSION-ELAST_MARKET*(CURRENT_FLAT*(1+LOSS_TREND)^0/N41-1),CONV_CEIL) -> 0.02 | R41: =IF($J41=0,0,IF($J41=4,$H41*GRAD_CONTINUE,$H40)*P41) -> 99.081249 | S41: =APPLICANTS_PER_YEAR*($H41/Segments!$AH$2)*Q41 -> 5.184 | T41: =R41+S41 -> 104.26525 | U41: =IFERROR((R41*O41+S41*CURRENT_FLAT*(1+LOSS_TREND)^0)/T41,M41) -> 1426.2298 | V41: =R41*O41+S41*CURRENT_FLAT*(1+LOSS_TREND)^0 -> 148706.2 | W41: =T41*L41*(1+LAE_RATIO) -> 29088.826 | X41: =R41*O41*(PREMIUM_TAX+OTHER_VARIABLE+COMMISSION_RN)+S41*CURRENT_FLAT*(1+LOSS_TREND)^0*(PREMIUM_TAX+OTHER_VARIABLE+COMMISSION_NB)+T41*FIXED_PER_POLICY+S41*NB_ACQUISITION -> 30579.152 | Y41: =IF($J41=0,AA41,IF($J41=4,U41,U40)) -> 1426.2298 | Z41: =$I41*(1+LOSS_TREND)^1 -> 256.56997 | AA41: =Z41*GROSS_MULT+POLICY_FEE -> 458.86943 | AB41: =AA41^MARKET_RISK_WEIGHT*(CURRENT_FLAT*(1+LOSS_TREND)^1)^(1-MARKET_RISK_WEIGHT) -> 821.02792 | AC41: =CURRENT_FLAT*(1+LOSS_TREND)^1 -> 1469.0167 | AD41: =MEDIAN(RET_FLOOR,BASE_RETENTION-ELAST_MARKET*(AC41/AB41-1)-ELAST_INCREASE*MAX(AC41/Y41-1,0),RET_CEIL) -> 0.44637959 | AE41: =MEDIAN(CONV_FLOOR,BASE_CONVERSION-ELAST_MARKET*(CURRENT_FLAT*(1+LOSS_TREND)^1/AB41-1),CONV_CEIL) -> 0.02 | AF41: =IF($J41=0,0,IF($J41=4,T41*GRAD_CONTINUE,T40)*AD41) -> 2.3247449 | AG41: =APPLICANTS_PER_YEAR*($H41/Segments!$AH$2)*AE41 -> 5.184 | AH41: =AF41+AG41 -> 7.5087449 | AI41: =IFERROR((AF41*AC41+AG41*CURRENT_FLAT*(1+LOSS_TREND)^1)/AH41,AA41) -> 1469.0167 | AJ41: =AF41*AC41+AG41*CURRENT_FLAT*(1+LOSS_TREND)^1 -> 11030.471 | AK41: =AH41*Z41*(1+LAE_RATIO) -> 2157.7006 | AL41: =AF41*AC41*(PREMIUM_TAX+OTHER_VARIABLE+COMMISSION_RN)+AG41*CURRENT_FLAT*(1+LOSS_TREND)^1*(PREMIUM_TAX+OTHER_VARIABLE+COMMISSION_NB)+AH41*FIXED_PER_POLICY+AG41*NB_ACQUISITION -> 2631.0724 | AM41: =IF($J41=0,AO41,IF($J41=4,AI41,AI40)) -> 1469.0167 | AN41: =$I41*(1+LOSS_TREND)^2 -> 264.26706 | AO41: =AN41*GROSS_MULT+POLICY_FEE -> 471.38551 | AP41: =AO41^MARKET_RISK_WEIGHT*(CURRENT_FLAT*(1+LOSS_TREND)^2)^(1-MARKET_RISK_WEIGHT) -> 844.53974 | AQ41: =CURRENT_FLAT*(1+LOSS_TREND)^2 -> 1513.0872 | AR41: =MEDIAN(RET_FLOOR,BASE_RETENTION-ELAST_MARKET*(AQ41/AP41-1)-ELAST_INCREASE*MAX(AQ41/AM41-1,0),RET_CEIL) -> 0.44519422 | AS41: =MEDIAN(CONV_FLOOR,BASE_CONVERSION-ELAST_MARKET*(CURRENT_FLAT*(1+LOSS_TREND)^2/AP41-1),CONV_CEIL) -> 0.02 | AT41: =IF($J41=0,0,IF($J41=4,AH41*GRAD_CONTINUE,AH40)*AR41) -> 2.3185715 | AU41: =APPLICANTS_PER_YEAR*($H41/Segments!$AH$2)*AS41 -> 5.184 | AV41: =AT41+AU41 -> 7.5025715 | AW41: =IFERROR((AT41*AQ41+AU41*CURRENT_FLAT*(1+LOSS_TREND)^2)/AV41,AO41) -> 1513.0872 | AX41: =AT41*AQ41+AU41*CURRENT_FLAT*(1+LOSS_TREND)^2 -> 11352.045 | AY41: =AV41*AN41*(1+LAE_RATIO) -> 2220.6044 | AZ41: =AT41*AQ41*(PREMIUM_TAX+OTHER_VARIABLE+COMMISSION_RN)+AU41*CURRENT_FLAT*(1+LOSS_TREND)^2*(PREMIUM_TAX+OTHER_VARIABLE+COMMISSION_NB)+AV41*FIXED_PER_POLICY+AU41*NB_ACQUISITION -> 2699.7224
A42: =Segments!$A$22 -> Non-greek | B42: =Segments!$B$22 -> On campus | C42: =Segments!$C$22 -> Yes | D42: =Segments!$D$22 -> 3.0+ | E42: =Segments!$E$22 -> Junior | F42: =Segments!$F$22 -> 2 | G42: =Segments!$G$22 -> Base | H42: =Segments!$H$22 -> 207 | I42: =Segments!$Y$22 -> 297.777 | J42: 2 | K42: =IF($J42=0,M42,CURRENT_FLAT) -> 1426.2298 | L42: =$I42*(1+LOSS_TREND)^0 -> 297.777 | M42: =L42*GROSS_MULT+POLICY_FEE -> 525.87528 | N42: =M42^MARKET_RISK_WEIGHT*(CURRENT_FLAT*(1+LOSS_TREND)^0)^(1-MARKET_RISK_WEIGHT) -> 866.03637 | O42: =CURRENT_FLAT*(1+LOSS_TREND)^0 -> 1426.2298 | P42: =MEDIAN(RET_FLOOR,BASE_RETENTION-ELAST_MARKET*(O42/N42-1)-ELAST_INCREASE*MAX(O42/K42-1,0),RET_CEIL) -> 0.52657628 | Q42: =MEDIAN(CONV_FLOOR,BASE_CONVERSION-ELAST_MARKET*(CURRENT_FLAT*(1+LOSS_TREND)^0/N42-1),CONV_CEIL) -> 0.026576279 | R42: =IF($J42=0,0,IF($J42=4,$H42*GRAD_CONTINUE,$H41)*P42) -> 113.74048 | S42: =APPLICANTS_PER_YEAR*($H42/Segments!$AH$2)*Q42 -> 6.6015477 | T42: =R42+S42 -> 120.34202 | U42: =IFERROR((R42*O42+S42*CURRENT_FLAT*(1+LOSS_TREND)^0)/T42,M42) -> 1426.2298 | V42: =R42*O42+S42*CURRENT_FLAT*(1+LOSS_TREND)^0 -> 171635.38 | W42: =T42*L42*(1+LAE_RATIO) -> 40135.297 | X42: =R42*O42*(PREMIUM_TAX+OTHER_VARIABLE+COMMISSION_RN)+S42*CURRENT_FLAT*(1+LOSS_TREND)^0*(PREMIUM_TAX+OTHER_VARIABLE+COMMISSION_NB)+T42*FIXED_PER_POLICY+S42*NB_ACQUISITION -> 35340.502 | Y42: =IF($J42=0,AA42,IF($J42=4,U42,U41)) -> 1426.2298 | Z42: =$I42*(1+LOSS_TREND)^1 -> 306.71031 | AA42: =Z42*GROSS_MULT+POLICY_FEE -> 540.40154 | AB42: =AA42^MARKET_RISK_WEIGHT*(CURRENT_FLAT*(1+LOSS_TREND)^1)^(1-MARKET_RISK_WEIGHT) -> 890.98758 | AC42: =CURRENT_FLAT*(1+LOSS_TREND)^1 -> 1469.0167 | AD42: =MEDIAN(RET_FLOOR,BASE_RETENTION-ELAST_MARKET*(AC42/AB42-1)-ELAST_INCREASE*MAX(AC42/Y42-1,0),RET_CEIL) -> 0.5166245 | AE42: =MEDIAN(CONV_FLOOR,BASE_CONVERSION-ELAST_MARKET*(CURRENT_FLAT*(1+LOSS_TREND)^1/AB42-1),CONV_CEIL) -> 0.0256245 | AF42: =IF($J42=0,0,IF($J42=4,T42*GRAD_CONTINUE,T41)*AD42) -> 53.865982 | AG42: =APPLICANTS_PER_YEAR*($H42/Segments!$AH$2)*AE42 -> 6.3651259 | AH42: =AF42+AG42 -> 60.231108 | AI42: =IFERROR((AF42*AC42+AG42*CURRENT_FLAT*(1+LOSS_TREND)^1)/AH42,AA42) -> 1469.0167 | AJ42: =AF42*AC42+AG42*CURRENT_FLAT*(1+LOSS_TREND)^1 -> 88480.502 | AK42: =AH42*Z42*(1+LAE_RATIO) -> 20690.322 | AL42: =AF42*AC42*(PREMIUM_TAX+OTHER_VARIABLE+COMMISSION_RN)+AG42*CURRENT_FLAT*(1+LOSS_TREND)^1*(PREMIUM_TAX+OTHER_VARIABLE+COMMISSION_NB)+AH42*FIXED_PER_POLICY+AG42*NB_ACQUISITION -> 18413.832 | AM42: =IF($J42=0,AO42,IF($J42=4,AI42,AI41)) -> 1469.0167 | AN42: =$I42*(1+LOSS_TREND)^2 -> 315.91162 | AO42: =AN42*GROSS_MULT+POLICY_FEE -> 555.36359 | AP42: =AO42^MARKET_RISK_WEIGHT*(CURRENT_FLAT*(1+LOSS_TREND)^2)^(1-MARKET_RISK_WEIGHT) -> 916.68616 | AQ42: =CURRENT_FLAT*(1+LOSS_TREND)^2 -> 1513.0872 | AR42: =MEDIAN(RET_FLOOR,BASE_RETENTION-ELAST_MARKET*(AQ42/AP42-1)-ELAST_INCREASE*MAX(AQ42/AM42-1,0),RET_CEIL) -> 0.51569728 | AS42: =MEDIAN(CONV_FLOOR,BASE_CONVERSION-ELAST_MARKET*(CURRENT_FLAT*(1+LOSS_TREND)^2/AP42-1),CONV_CEIL) -> 0.024697279 | AT42: =IF($J42=0,0,IF($J42=4,AH42*GRAD_CONTINUE,AH41)*AR42) -> 3.8722393 | AU42: =APPLICANTS_PER_YEAR*($H42/Segments!$AH$2)*AS42 -> 6.134804 | AV42: =AT42+AU42 -> 10.007043 | AW42: =IFERROR((AT42*AQ42+AU42*CURRENT_FLAT*(1+LOSS_TREND)^2)/AV42,AO42) -> 1513.0872 | AX42: =AT42*AQ42+AU42*CURRENT_FLAT*(1+LOSS_TREND)^2 -> 15141.529 | AY42: =AV42*AN42*(1+LAE_RATIO) -> 3540.7022 | AZ42: =AT42*AQ42*(PREMIUM_TAX+OTHER_VARIABLE+COMMISSION_RN)+AU42*CURRENT_FLAT*(1+LOSS_TREND)^2*(PREMIUM_TAX+OTHER_VARIABLE+COMMISSION_NB)+AV42*FIXED_PER_POLICY+AU42*NB_ACQUISITION -> 3540.1472
A43: =Segments!$A$23 -> Non-greek | B43: =Segments!$B$23 -> On campus | C43: =Segments!$C$23 -> Yes | D43: =Segments!$D$23 -> 3.0+ | E43: =Segments!$E$23 -> Senior | F43: =Segments!$F$23 -> 3 | G43: =Segments!$G$23 -> Base | H43: =Segments!$H$23 -> 197 | I43: =Segments!$Y$23 -> 278.32843 | J43: 3 | K43: =IF($J43=0,M43,CURRENT_FLAT) -> 1426.2298 | L43: =$I43*(1+LOSS_TREND)^0 -> 278.32843 | M43: =L43*GROSS_MULT+POLICY_FEE -> 494.25039 | N43: =M43^MARKET_RISK_WEIGHT*(CURRENT_FLAT*(1+LOSS_TREND)^0)^(1-MARKET_RISK_WEIGHT) -> 839.59194 | O43: =CURRENT_FLAT*(1+LOSS_TREND)^0 -> 1426.2298 | P43: =MEDIAN(RET_FLOOR,BASE_RETENTION-ELAST_MARKET*(O43/N43-1)-ELAST_INCREASE*MAX(O43/K43-1,0),RET_CEIL) -> 0.50064109 | Q43: =MEDIAN(CONV_FLOOR,BASE_CONVERSION-ELAST_MARKET*(CURRENT_FLAT*(1+LOSS_TREND)^0/N43-1),CONV_CEIL) -> 0.02 | R43: =IF($J43=0,0,IF($J43=4,$H43*GRAD_CONTINUE,$H42)*P43) -> 103.63271 | S43: =APPLICANTS_PER_YEAR*($H43/Segments!$AH$2)*Q43 -> 4.728 | T43: =R43+S43 -> 108.36071 | U43: =IFERROR((R43*O43+S43*CURRENT_FLAT*(1+LOSS_TREND)^0)/T43,M43) -> 1426.2298 | V43: =R43*O43+S43*CURRENT_FLAT*(1+LOSS_TREND)^0 -> 154547.27 | W43: =T43*L43*(1+LAE_RATIO) -> 33779.049 | X43: =R43*O43*(PREMIUM_TAX+OTHER_VARIABLE+COMMISSION_RN)+S43*CURRENT_FLAT*(1+LOSS_TREND)^0*(PREMIUM_TAX+OTHER_VARIABLE+COMMISSION_NB)+T43*FIXED_PER_POLICY+S43*NB_ACQUISITION -> 31730.86 | Y43: =IF($J43=0,AA43,IF($J43=4,U43,U42)) -> 1426.2298 | Z43: =$I43*(1+LOSS_TREND)^1 -> 286.67828 | AA43: =Z43*GROSS_MULT+POLICY_FEE -> 507.8279 | AB43: =AA43^MARKET_RISK_WEIGHT*(CURRENT_FLAT*(1+LOSS_TREND)^1)^(1-MARKET_RISK_WEIGHT) -> 863.71734 | AC43: =CURRENT_FLAT*(1+LOSS_TREND)^1 -> 1469.0167 | AD43: =MEDIAN(RET_FLOOR,BASE_RETENTION-ELAST_MARKET*(AC43/AB43-1)-ELAST_INCREASE*MAX(AC43/Y43-1,0),RET_CEIL) -> 0.4905964 | AE43: =MEDIAN(CONV_FLOOR,BASE_CONVERSION-ELAST_MARKET*(CURRENT_FLAT*(1+LOSS_TREND)^1/AB43-1),CONV_CEIL) -> 0.02 | AF43: =IF($J43=0,0,IF($J43=4,T43*GRAD_CONTINUE,T42)*AD43) -> 59.039364 | AG43: =APPLICANTS_PER_YEAR*($H43/Segments!$AH$2)*AE43 -> 4.728 | AH43: =AF43+AG43 -> 63.767364 | AI43: =IFERROR((AF43*AC43+AG43*CURRENT_FLAT*(1+LOSS_TREND)^1)/AH43,AA43) -> 1469.0167 | AJ43: =AF43*AC43+AG43*CURRENT_FLAT*(1+LOSS_TREND)^1 -> 93675.321 | AK43: =AH43*Z43*(1+LAE_RATIO) -> 20474.404 | AL43: =AF43*AC43*(PREMIUM_TAX+OTHER_VARIABLE+COMMISSION_RN)+AG43*CURRENT_FLAT*(1+LOSS_TREND)^1*(PREMIUM_TAX+OTHER_VARIABLE+COMMISSION_NB)+AH43*FIXED_PER_POLICY+AG43*NB_ACQUISITION -> 19341.276 | AM43: =IF($J43=0,AO43,IF($J43=4,AI43,AI42)) -> 1469.0167 | AN43: =$I43*(1+LOSS_TREND)^2 -> 295.27863 | AO43: =AN43*GROSS_MULT+POLICY_FEE -> 521.81274 | AP43: =AO43^MARKET_RISK_WEIGHT*(CURRENT_FLAT*(1+LOSS_TREND)^2)^(1-MARKET_RISK_WEIGHT) -> 888.56522 | AQ43: =CURRENT_FLAT*(1+LOSS_TREND)^2 -> 1513.0872 | AR43: =MEDIAN(RET_FLOOR,BASE_RETENTION-ELAST_MARKET*(AQ43/AP43-1)-ELAST_INCREASE*MAX(AQ43/AM43-1,0),RET_CEIL) -> 0.48957844 | AS43: =MEDIAN(CONV_FLOOR,BASE_CONVERSION-ELAST_MARKET*(CURRENT_FLAT*(1+LOSS_TREND)^2/AP43-1),CONV_CEIL) -> 0.02 | AT43: =IF($J43=0,0,IF($J43=4,AH43*GRAD_CONTINUE,AH42)*AR43) -> 29.487852 | AU43: =APPLICANTS_PER_YEAR*($H43/Segments!$AH$2)*AS43 -> 4.728 | AV43: =AT43+AU43 -> 34.215852 | AW43: =IFERROR((AT43*AQ43+AU43*CURRENT_FLAT*(1+LOSS_TREND)^2)/AV43,AO43) -> 1513.0872 | AX43: =AT43*AQ43+AU43*CURRENT_FLAT*(1+LOSS_TREND)^2 -> 51771.567 | AY43: =AV43*AN43*(1+LAE_RATIO) -> 11315.595 | AZ43: =AT43*AQ43*(PREMIUM_TAX+OTHER_VARIABLE+COMMISSION_RN)+AU43*CURRENT_FLAT*(1+LOSS_TREND)^2*(PREMIUM_TAX+OTHER_VARIABLE+COMMISSION_NB)+AV43*FIXED_PER_POLICY+AU43*NB_ACQUISITION -> 10837.729
A44: =Segments!$A$24 -> Non-greek | B44: =Segments!$B$24 -> On campus | C44: =Segments!$C$24 -> Yes | D44: =Segments!$D$24 -> 3.0+ | E44: =Segments!$E$24 -> Grad student | F44: =Segments!$F$24 -> 3 | G44: =Segments!$G$24 -> Grad | H44: =Segments!$H$24 -> 86 | I44: =Segments!$Y$24 -> 331.40021 | J44: 4 | K44: =IF($J44=0,M44,CURRENT_FLAT) -> 1426.2298 | L44: =$I44*(1+LOSS_TREND)^0 -> 331.40021 | M44: =L44*GROSS_MULT+POLICY_FEE -> 580.54924 | N44: =M44^MARKET_RISK_WEIGHT*(CURRENT_FLAT*(1+LOSS_TREND)^0)^(1-MARKET_RISK_WEIGHT) -> 909.9432 | O44: =CURRENT_FLAT*(1+LOSS_TREND)^0 -> 1426.2298 | P44: =MEDIAN(RET_FLOOR,BASE_RETENTION-ELAST_MARKET*(O44/N44-1)-ELAST_INCREASE*MAX(O44/K44-1,0),RET_CEIL) -> 0.56630835 | Q44: =MEDIAN(CONV_FLOOR,BASE_CONVERSION-ELAST_MARKET*(CURRENT_FLAT*(1+LOSS_TREND)^0/N44-1),CONV_CEIL) -> 0.066308346 | R44: =IF($J44=0,0,IF($J44=4,$H44*GRAD_CONTINUE,$H43)*P44) -> 24.351259 | S44: =APPLICANTS_PER_YEAR*($H44/Segments!$AH$2)*Q44 -> 6.8430213 | T44: =R44+S44 -> 31.19428 | U44: =IFERROR((R44*O44+S44*CURRENT_FLAT*(1+LOSS_TREND)^0)/T44,M44) -> 1426.2298 | V44: =R44*O44+S44*CURRENT_FLAT*(1+LOSS_TREND)^0 -> 44490.211 | W44: =T44*L44*(1+LAE_RATIO) -> 11578.326 | X44: =R44*O44*(PREMIUM_TAX+OTHER_VARIABLE+COMMISSION_RN)+S44*CURRENT_FLAT*(1+LOSS_TREND)^0*(PREMIUM_TAX+OTHER_VARIABLE+COMMISSION_NB)+T44*FIXED_PER_POLICY+S44*NB_ACQUISITION -> 9545.2013 | Y44: =IF($J44=0,AA44,IF($J44=4,U44,U43)) -> 1426.2298 | Z44: =$I44*(1+LOSS_TREND)^1 -> 341.34222 | AA44: =Z44*GROSS_MULT+POLICY_FEE -> 596.71572 | AB44: =AA44^MARKET_RISK_WEIGHT*(CURRENT_FLAT*(1+LOSS_TREND)^1)^(1-MARKET_RISK_WEIGHT) -> 936.26136 | AC44: =CURRENT_FLAT*(1+LOSS_TREND)^1 -> 1469.0167 | AD44: =MEDIAN(RET_FLOOR,BASE_RETENTION-ELAST_MARKET*(AC44/AB44-1)-ELAST_INCREASE*MAX(AC44/Y44-1,0),RET_CEIL) -> 0.55648794 | AE44: =MEDIAN(CONV_FLOOR,BASE_CONVERSION-ELAST_MARKET*(CURRENT_FLAT*(1+LOSS_TREND)^1/AB44-1),CONV_CEIL) -> 0.065487937 | AF44: =IF($J44=0,0,IF($J44=4,T44*GRAD_CONTINUE,T43)*AD44) -> 8.6796203 | AG44: =APPLICANTS_PER_YEAR*($H44/Segments!$AH$2)*AE44 -> 6.7583551 | AH44: =AF44+AG44 -> 15.437975 | AI44: =IFERROR((AF44*AC44+AG44*CURRENT_FLAT*(1+LOSS_TREND)^1)/AH44,AA44) -> 1469.0167 | AJ44: =AF44*AC44+AG44*CURRENT_FLAT*(1+LOSS_TREND)^1 -> 22678.643 | AK44: =AH44*Z44*(1+LAE_RATIO) -> 5901.9887 | AL44: =AF44*AC44*(PREMIUM_TAX+OTHER_VARIABLE+COMMISSION_RN)+AG44*CURRENT_FLAT*(1+LOSS_TREND)^1*(PREMIUM_TAX+OTHER_VARIABLE+COMMISSION_NB)+AH44*FIXED_PER_POLICY+AG44*NB_ACQUISITION -> 5111.4667 | AM44: =IF($J44=0,AO44,IF($J44=4,AI44,AI43)) -> 1469.0167 | AN44: =$I44*(1+LOSS_TREND)^2 -> 351.58248 | AO44: =AN44*GROSS_MULT+POLICY_FEE -> 613.36719 | AP44: =AO44^MARKET_RISK_WEIGHT*(CURRENT_FLAT*(1+LOSS_TREND)^2)^(1-MARKET_RISK_WEIGHT) -> 963.36807 | AQ44: =CURRENT_FLAT*(1+LOSS_TREND)^2 -> 1513.0872 | AR44: =MEDIAN(RET_FLOOR,BASE_RETENTION-ELAST_MARKET*(AQ44/AP44-1)-ELAST_INCREASE*MAX(AQ44/AM44-1,0),RET_CEIL) -> 0.55568895 | AS44: =MEDIAN(CONV_FLOOR,BASE_CONVERSION-ELAST_MARKET*(CURRENT_FLAT*(1+LOSS_TREND)^2/AP44-1),CONV_CEIL) -> 0.064688953 | AT44: =IF($J44=0,0,IF($J44=4,AH44*GRAD_CONTINUE,AH43)*AR44) -> 4.2893562 | AU44: =APPLICANTS_PER_YEAR*($H44/Segments!$AH$2)*AS44 -> 6.6759 | AV44: =AT44+AU44 -> 10.965256 | AW44: =IFERROR((AT44*AQ44+AU44*CURRENT_FLAT*(1+LOSS_TREND)^2)/AV44,AO44) -> 1513.0872 | AX44: =AT44*AQ44+AU44*CURRENT_FLAT*(1+LOSS_TREND)^2 -> 16591.388 | AY44: =AV44*AN44*(1+LAE_RATIO) -> 4317.815 | AZ44: =AT44*AQ44*(PREMIUM_TAX+OTHER_VARIABLE+COMMISSION_RN)+AU44*CURRENT_FLAT*(1+LOSS_TREND)^2*(PREMIUM_TAX+OTHER_VARIABLE+COMMISSION_NB)+AV44*FIXED_PER_POLICY+AU44*NB_ACQUISITION -> 3875.5177
A45: =Segments!$A$25 -> Non-greek | B45: =Segments!$B$25 -> On campus | C45: =Segments!$C$25 -> No | D45: =Segments!$D$25 -> <1.0 | E45: =Segments!$E$25 -> Freshman | F45: =Segments!$F$25 -> 1 | G45: =Segments!$G$25 -> Base | H45: =Segments!$H$25 -> 24 | I45: =Segments!$Y$25 -> 495.85541 | J45: 0 | K45: =IF($J45=0,M45,CURRENT_FLAT) -> 847.96622 | L45: =$I45*(1+LOSS_TREND)^0 -> 495.85541 | M45: =L45*GROSS_MULT+POLICY_FEE -> 847.96622 | N45: =M45^MARKET_RISK_WEIGHT*(CURRENT_FLAT*(1+LOSS_TREND)^0)^(1-MARKET_RISK_WEIGHT) -> 1099.7248 | O45: =CURRENT_FLAT*(1+LOSS_TREND)^0 -> 1426.2298 | P45: =MEDIAN(RET_FLOOR,BASE_RETENTION-ELAST_MARKET*(O45/N45-1)-ELAST_INCREASE*MAX(O45/K45-1,0),RET_CEIL) -> 0.496969 | Q45: =MEDIAN(CONV_FLOOR,BASE_CONVERSION-ELAST_MARKET*(CURRENT_FLAT*(1+LOSS_TREND)^0/N45-1),CONV_CEIL) -> 0.20155152 | R45: =IF($J45=0,0,IF($J45=4,$H45*GRAD_CONTINUE,$H44)*P45) -> 0 | S45: =APPLICANTS_PER_YEAR*($H45/Segments!$AH$2)*Q45 -> 5.8046837 | T45: =R45+S45 -> 5.8046837 | U45: =IFERROR((R45*O45+S45*CURRENT_FLAT*(1+LOSS_TREND)^0)/T45,M45) -> 1426.2298 | V45: =R45*O45+S45*CURRENT_FLAT*(1+LOSS_TREND)^0 -> 8278.8128 | W45: =T45*L45*(1+LAE_RATIO) -> 3223.6779 | X45: =R45*O45*(PREMIUM_TAX+OTHER_VARIABLE+COMMISSION_RN)+S45*CURRENT_FLAT*(1+LOSS_TREND)^0*(PREMIUM_TAX+OTHER_VARIABLE+COMMISSION_NB)+T45*FIXED_PER_POLICY+S45*NB_ACQUISITION -> 2115.6648 | Y45: =IF($J45=0,AA45,IF($J45=4,U45,U44)) -> 872.15521 | Z45: =$I45*(1+LOSS_TREND)^1 -> 510.73107 | AA45: =Z45*GROSS_MULT+POLICY_FEE -> 872.15521 | AB45: =AA45^MARKET_RISK_WEIGHT*(CURRENT_FLAT*(1+LOSS_TREND)^1)^(1-MARKET_RISK_WEIGHT) -> 1131.9057 | AC45: =CURRENT_FLAT*(1+LOSS_TREND)^1 -> 1469.0167 | AD45: =MEDIAN(RET_FLOOR,BASE_RETENTION-ELAST_MARKET*(AC45/AB45-1)-ELAST_INCREASE*MAX(AC45/Y45-1,0),RET_CEIL) -> 0.49578129 | AE45: =MEDIAN(CONV_FLOOR,BASE_CONVERSION-ELAST_MARKET*(CURRENT_FLAT*(1+LOSS_TREND)^1/AB45-1),CONV_CEIL) -> 0.201087 | AF45: =IF($J45=0,0,IF($J45=4,T45*GRAD_CONTINUE,T44)*AD45) -> 0 | AG45: =APPLICANTS_PER_YEAR*($H45/Segments!$AH$2)*AE45 -> 5.7913055 | AH45: =AF45+AG45 -> 5.7913055 | AI45: =IFERROR((AF45*AC45+AG45*CURRENT_FLAT*(1+LOSS_TREND)^1)/AH45,AA45) -> 1469.0167 | AJ45: =AF45*AC45+AG45*CURRENT_FLAT*(1+LOSS_TREND)^1 -> 8507.5243 | AK45: =AH45*Z45*(1+LAE_RATIO) -> 3312.7356 | AL45: =AF45*AC45*(PREMIUM_TAX+OTHER_VARIABLE+COMMISSION_RN)+AG45*CURRENT_FLAT*(1+LOSS_TREND)^1*(PREMIUM_TAX+OTHER_VARIABLE+COMMISSION_NB)+AH45*FIXED_PER_POLICY+AG45*NB_ACQUISITION -> 2166.2942 | AM45: =IF($J45=0,AO45,IF($J45=4,AI45,AI44)) -> 897.06986 | AN45: =$I45*(1+LOSS_TREND)^2 -> 526.053 | AO45: =AN45*GROSS_MULT+POLICY_FEE -> 897.06986 | AP45: =AO45^MARKET_RISK_WEIGHT*(CURRENT_FLAT*(1+LOSS_TREND)^2)^(1-MARKET_RISK_WEIGHT) -> 1165.0515 | AQ45: =CURRENT_FLAT*(1+LOSS_TREND)^2 -> 1513.0872 | AR45: =MEDIAN(RET_FLOOR,BASE_RETENTION-ELAST_MARKET*(AQ45/AP45-1)-ELAST_INCREASE*MAX(AQ45/AM45-1,0),RET_CEIL) -> 0.49462524 | AS45: =MEDIAN(CONV_FLOOR,BASE_CONVERSION-ELAST_MARKET*(CURRENT_FLAT*(1+LOSS_TREND)^2/AP45-1),CONV_CEIL) -> 0.20063505 | AT45: =IF($J45=0,0,IF($J45=4,AH45*GRAD_CONTINUE,AH44)*AR45) -> 0 | AU45: =APPLICANTS_PER_YEAR*($H45/Segments!$AH$2)*AS45 -> 5.7782894 | AV45: =AT45+AU45 -> 5.7782894 | AW45: =IFERROR((AT45*AQ45+AU45*CURRENT_FLAT*(1+LOSS_TREND)^2)/AV45,AO45) -> 1513.0872 | AX45: =AT45*AQ45+AU45*CURRENT_FLAT*(1+LOSS_TREND)^2 -> 8743.0555 | AY45: =AV45*AN45*(1+LAE_RATIO) -> 3404.4489 | AZ45: =AT45*AQ45*(PREMIUM_TAX+OTHER_VARIABLE+COMMISSION_RN)+AU45*CURRENT_FLAT*(1+LOSS_TREND)^2*(PREMIUM_TAX+OTHER_VARIABLE+COMMISSION_NB)+AV45*FIXED_PER_POLICY+AU45*NB_ACQUISITION -> 2218.4675
A46: =Segments!$A$26 -> Non-greek | B46: =Segments!$B$26 -> On campus | C46: =Segments!$C$26 -> No | D46: =Segments!$D$26 -> <1.0 | E46: =Segments!$E$26 -> Sophomore | F46: =Segments!$F$26 -> 1 | G46: =Segments!$G$26 -> Sophomore | H46: =Segments!$H$26 -> 19 | I46: =Segments!$Y$26 -> 490.8107 | J46: 1 | K46: =IF($J46=0,M46,CURRENT_FLAT) -> 1426.2298 | L46: =$I46*(1+LOSS_TREND)^0 -> 490.8107 | M46: =L46*GROSS_MULT+POLICY_FEE -> 839.76312 | N46: =M46^MARKET_RISK_WEIGHT*(CURRENT_FLAT*(1+LOSS_TREND)^0)^(1-MARKET_RISK_WEIGHT) -> 1094.3926 | O46: =CURRENT_FLAT*(1+LOSS_TREND)^0 -> 1426.2298 | P46: =MEDIAN(RET_FLOOR,BASE_RETENTION-ELAST_MARKET*(O46/N46-1)-ELAST_INCREASE*MAX(O46/K46-1,0),RET_CEIL) -> 0.69839208 | Q46: =MEDIAN(CONV_FLOOR,BASE_CONVERSION-ELAST_MARKET*(CURRENT_FLAT*(1+LOSS_TREND)^0/N46-1),CONV_CEIL) -> 0.19839208 | R46: =IF($J46=0,0,IF($J46=4,$H46*GRAD_CONTINUE,$H45)*P46) -> 16.76141 | S46: =APPLICANTS_PER_YEAR*($H46/Segments!$AH$2)*Q46 -> 4.5233394 | T46: =R46+S46 -> 21.284749 | U46: =IFERROR((R46*O46+S46*CURRENT_FLAT*(1+LOSS_TREND)^0)/T46,M46) -> 1426.2298 | V46: =R46*O46+S46*CURRENT_FLAT*(1+LOSS_TREND)^0 -> 30356.943 | W46: =T46*L46*(1+LAE_RATIO) -> 11700.397 | X46: =R46*O46*(PREMIUM_TAX+OTHER_VARIABLE+COMMISSION_RN)+S46*CURRENT_FLAT*(1+LOSS_TREND)^0*(PREMIUM_TAX+OTHER_VARIABLE+COMMISSION_NB)+T46*FIXED_PER_POLICY+S46*NB_ACQUISITION -> 6502.037 | Y46: =IF($J46=0,AA46,IF($J46=4,U46,U45)) -> 1426.2298 | Z46: =$I46*(1+LOSS_TREND)^1 -> 505.53502 | AA46: =Z46*GROSS_MULT+POLICY_FEE -> 863.70602 | AB46: =AA46^MARKET_RISK_WEIGHT*(CURRENT_FLAT*(1+LOSS_TREND)^1)^(1-MARKET_RISK_WEIGHT) -> 1126.4096 | AC46: =CURRENT_FLAT*(1+LOSS_TREND)^1 -> 1469.0167 | AD46: =MEDIAN(RET_FLOOR,BASE_RETENTION-ELAST_MARKET*(AC46/AB46-1)-ELAST_INCREASE*MAX(AC46/Y46-1,0),RET_CEIL) -> 0.68892073 | AE46: =MEDIAN(CONV_FLOOR,BASE_CONVERSION-ELAST_MARKET*(CURRENT_FLAT*(1+LOSS_TREND)^1/AB46-1),CONV_CEIL) -> 0.19792073 | AF46: =IF($J46=0,0,IF($J46=4,T46*GRAD_CONTINUE,T45)*AD46) -> 3.998967 | AG46: =APPLICANTS_PER_YEAR*($H46/Segments!$AH$2)*AE46 -> 4.5125927 | AH46: =AF46+AG46 -> 8.5115596 | AI46: =IFERROR((AF46*AC46+AG46*CURRENT_FLAT*(1+LOSS_TREND)^1)/AH46,AA46) -> 1469.0167 | AJ46: =AF46*AC46+AG46*CURRENT_FLAT*(1+LOSS_TREND)^1 -> 12503.623 | AK46: =AH46*Z46*(1+LAE_RATIO) -> 4819.2384 | AL46: =AF46*AC46*(PREMIUM_TAX+OTHER_VARIABLE+COMMISSION_RN)+AG46*CURRENT_FLAT*(1+LOSS_TREND)^1*(PREMIUM_TAX+OTHER_VARIABLE+COMMISSION_NB)+AH46*FIXED_PER_POLICY+AG46*NB_ACQUISITION -> 2878.2483 | AM46: =IF($J46=0,AO46,IF($J46=4,AI46,AI45)) -> 1469.0167 | AN46: =$I46*(1+LOSS_TREND)^2 -> 520.70107 | AO46: =AN46*GROSS_MULT+POLICY_FEE -> 888.3672 | AP46: =AO46^MARKET_RISK_WEIGHT*(CURRENT_FLAT*(1+LOSS_TREND)^2)^(1-MARKET_RISK_WEIGHT) -> 1159.3865 | AQ46: =CURRENT_FLAT*(1+LOSS_TREND)^2 -> 1513.0872 | AR46: =MEDIAN(RET_FLOOR,BASE_RETENTION-ELAST_MARKET*(AQ46/AP46-1)-ELAST_INCREASE*MAX(AQ46/AM46-1,0),RET_CEIL) -> 0.68846213 | AS46: =MEDIAN(CONV_FLOOR,BASE_CONVERSION-ELAST_MARKET*(CURRENT_FLAT*(1+LOSS_TREND)^2/AP46-1),CONV_CEIL) -> 0.19746213 | AT46: =IF($J46=0,0,IF($J46=4,AH46*GRAD_CONTINUE,AH45)*AR46) -> 3.9870945 | AU46: =APPLICANTS_PER_YEAR*($H46/Segments!$AH$2)*AS46 -> 4.5021366 | AV46: =AT46+AU46 -> 8.4892311 | AW46: =IFERROR((AT46*AQ46+AU46*CURRENT_FLAT*(1+LOSS_TREND)^2)/AV46,AO46) -> 1513.0872 | AX46: =AT46*AQ46+AU46*CURRENT_FLAT*(1+LOSS_TREND)^2 -> 12844.947 | AY46: =AV46*AN46*(1+LAE_RATIO) -> 4950.7939 | AZ46: =AT46*AQ46*(PREMIUM_TAX+OTHER_VARIABLE+COMMISSION_RN)+AU46*CURRENT_FLAT*(1+LOSS_TREND)^2*(PREMIUM_TAX+OTHER_VARIABLE+COMMISSION_NB)+AV46*FIXED_PER_POLICY+AU46*NB_ACQUISITION -> 2948.4573
A47: =Segments!$A$27 -> Non-greek | B47: =Segments!$B$27 -> On campus | C47: =Segments!$C$27 -> No | D47: =Segments!$D$27 -> <1.0 | E47: =Segments!$E$27 -> Junior | F47: =Segments!$F$27 -> 2 | G47: =Segments!$G$27 -> Base | H47: =Segments!$H$27 -> 31 | I47: =Segments!$Y$27 -> 586.72768 | J47: 2 | K47: =IF($J47=0,M47,CURRENT_FLAT) -> 1426.2298 | L47: =$I47*(1+LOSS_TREND)^0 -> 586.72768 | M47: =L47*GROSS_MULT+POLICY_FEE -> 995.73162 | N47: =M47^MARKET_RISK_WEIGHT*(CURRENT_FLAT*(1+LOSS_TREND)^0)^(1-MARKET_RISK_WEIGHT) -> 1191.6971 | O47: =CURRENT_FLAT*(1+LOSS_TREND)^0 -> 1426.2298 | P47: =MEDIAN(RET_FLOOR,BASE_RETENTION-ELAST_MARKET*(O47/N47-1)-ELAST_INCREASE*MAX(O47/K47-1,0),RET_CEIL) -> 0.75159722 | Q47: =MEDIAN(CONV_FLOOR,BASE_CONVERSION-ELAST_MARKET*(CURRENT_FLAT*(1+LOSS_TREND)^0/N47-1),CONV_CEIL) -> 0.25159722 | R47: =IF($J47=0,0,IF($J47=4,$H47*GRAD_CONTINUE,$H46)*P47) -> 14.280347 | S47: =APPLICANTS_PER_YEAR*($H47/Segments!$AH$2)*Q47 -> 9.3594165 | T47: =R47+S47 -> 23.639764 | U47: =IFERROR((R47*O47+S47*CURRENT_FLAT*(1+LOSS_TREND)^0)/T47,M47) -> 1426.2298 | V47: =R47*O47+S47*CURRENT_FLAT*(1+LOSS_TREND)^0 -> 33715.735 | W47: =T47*L47*(1+LAE_RATIO) -> 15534.516 | X47: =R47*O47*(PREMIUM_TAX+OTHER_VARIABLE+COMMISSION_RN)+S47*CURRENT_FLAT*(1+LOSS_TREND)^0*(PREMIUM_TAX+OTHER_VARIABLE+COMMISSION_NB)+T47*FIXED_PER_POLICY+S47*NB_ACQUISITION -> 7546.2583 | Y47: =IF($J47=0,AA47,IF($J47=4,U47,U46)) -> 1426.2298 | Z47: =$I47*(1+LOSS_TREND)^1 -> 604.32952 | AA47: =Z47*GROSS_MULT+POLICY_FEE -> 1024.3536 | AB47: =AA47^MARKET_RISK_WEIGHT*(CURRENT_FLAT*(1+LOSS_TREND)^1)^(1-MARKET_RISK_WEIGHT) -> 1226.6998 | AC47: =CURRENT_FLAT*(1+LOSS_TREND)^1 -> 1469.0167 | AD47: =MEDIAN(RET_FLOOR,BASE_RETENTION-ELAST_MARKET*(AC47/AB47-1)-ELAST_INCREASE*MAX(AC47/Y47-1,0),RET_CEIL) -> 0.74223222 | AE47: =MEDIAN(CONV_FLOOR,BASE_CONVERSION-ELAST_MARKET*(CURRENT_FLAT*(1+LOSS_TREND)^1/AB47-1),CONV_CEIL) -> 0.25123222 | AF47: =IF($J47=0,0,IF($J47=4,T47*GRAD_CONTINUE,T46)*AD47) -> 15.798227 | AG47: =APPLICANTS_PER_YEAR*($H47/Segments!$AH$2)*AE47 -> 9.3458386 | AH47: =AF47+AG47 -> 25.144065 | AI47: =IFERROR((AF47*AC47+AG47*CURRENT_FLAT*(1+LOSS_TREND)^1)/AH47,AA47) -> 1469.0167 | AJ47: =AF47*AC47+AG47*CURRENT_FLAT*(1+LOSS_TREND)^1 -> 36937.051 | AK47: =AH47*Z47*(1+LAE_RATIO) -> 17018.737 | AL47: =AF47*AC47*(PREMIUM_TAX+OTHER_VARIABLE+COMMISSION_RN)+AG47*CURRENT_FLAT*(1+LOSS_TREND)^1*(PREMIUM_TAX+OTHER_VARIABLE+COMMISSION_NB)+AH47*FIXED_PER_POLICY+AG47*NB_ACQUISITION -> 8198.1517 | AM47: =IF($J47=0,AO47,IF($J47=4,AI47,AI46)) -> 1469.0167 | AN47: =$I47*(1+LOSS_TREND)^2 -> 622.4594 | AO47: =AN47*GROSS_MULT+POLICY_FEE -> 1053.8342 | AP47: =AO47^MARKET_RISK_WEIGHT*(CURRENT_FLAT*(1+LOSS_TREND)^2)^(1-MARKET_RISK_WEIGHT) -> 1262.7521 | AQ47: =CURRENT_FLAT*(1+LOSS_TREND)^2 -> 1513.0872 | AR47: =MEDIAN(RET_FLOOR,BASE_RETENTION-ELAST_MARKET*(AQ47/AP47-1)-ELAST_INCREASE*MAX(AQ47/AM47-1,0),RET_CEIL) -> 0.74187721 | AS47: =MEDIAN(CONV_FLOOR,BASE_CONVERSION-ELAST_MARKET*(CURRENT_FLAT*(1+LOSS_TREND)^2/AP47-1),CONV_CEIL) -> 0.25087721 | AT47: =IF($J47=0,0,IF($J47=4,AH47*GRAD_CONTINUE,AH46)*AR47) -> 6.3145321 | AU47: =APPLICANTS_PER_YEAR*($H47/Segments!$AH$2)*AS47 -> 9.3326323 | AV47: =AT47+AU47 -> 15.647164 | AW47: =IFERROR((AT47*AQ47+AU47*CURRENT_FLAT*(1+LOSS_TREND)^2)/AV47,AO47) -> 1513.0872 | AX47: =AT47*AQ47+AU47*CURRENT_FLAT*(1+LOSS_TREND)^2 -> 23675.524 | AY47: =AV47*AN47*(1+LAE_RATIO) -> 10908.492 | AZ47: =AT47*AQ47*(PREMIUM_TAX+OTHER_VARIABLE+COMMISSION_RN)+AU47*CURRENT_FLAT*(1+LOSS_TREND)^2*(PREMIUM_TAX+OTHER_VARIABLE+COMMISSION_NB)+AV47*FIXED_PER_POLICY+AU47*NB_ACQUISITION -> 5515.1711
A48: =Segments!$A$28 -> Non-greek | B48: =Segments!$B$28 -> On campus | C48: =Segments!$C$28 -> No | D48: =Segments!$D$28 -> <1.0 | E48: =Segments!$E$28 -> Senior | F48: =Segments!$F$28 -> 3 | G48: =Segments!$G$28 -> Base | H48: =Segments!$H$28 -> 29 | I48: =Segments!$Y$28 -> 548.40701 | J48: 3 | K48: =IF($J48=0,M48,CURRENT_FLAT) -> 1426.2298 | L48: =$I48*(1+LOSS_TREND)^0 -> 548.40701 | M48: =L48*GROSS_MULT+POLICY_FEE -> 933.41921 | N48: =M48^MARKET_RISK_WEIGHT*(CURRENT_FLAT*(1+LOSS_TREND)^0)^(1-MARKET_RISK_WEIGHT) -> 1153.8069 | O48: =CURRENT_FLAT*(1+LOSS_TREND)^0 -> 1426.2298 | P48: =MEDIAN(RET_FLOOR,BASE_RETENTION-ELAST_MARKET*(O48/N48-1)-ELAST_INCREASE*MAX(O48/K48-1,0),RET_CEIL) -> 0.73194605 | Q48: =MEDIAN(CONV_FLOOR,BASE_CONVERSION-ELAST_MARKET*(CURRENT_FLAT*(1+LOSS_TREND)^0/N48-1),CONV_CEIL) -> 0.23194605 | R48: =IF($J48=0,0,IF($J48=4,$H48*GRAD_CONTINUE,$H47)*P48) -> 22.690328 | S48: =APPLICANTS_PER_YEAR*($H48/Segments!$AH$2)*Q48 -> 8.0717226 | T48: =R48+S48 -> 30.76205 | U48: =IFERROR((R48*O48+S48*CURRENT_FLAT*(1+LOSS_TREND)^0)/T48,M48) -> 1426.2298 | V48: =R48*O48+S48*CURRENT_FLAT*(1+LOSS_TREND)^0 -> 43873.752 | W48: =T48*L48*(1+LAE_RATIO) -> 18894.539 | X48: =R48*O48*(PREMIUM_TAX+OTHER_VARIABLE+COMMISSION_RN)+S48*CURRENT_FLAT*(1+LOSS_TREND)^0*(PREMIUM_TAX+OTHER_VARIABLE+COMMISSION_NB)+T48*FIXED_PER_POLICY+S48*NB_ACQUISITION -> 9512.0978 | Y48: =IF($J48=0,AA48,IF($J48=4,U48,U47)) -> 1426.2298 | Z48: =$I48*(1+LOSS_TREND)^1 -> 564.85922 | AA48: =Z48*GROSS_MULT+POLICY_FEE -> 960.17179 | AB48: =AA48^MARKET_RISK_WEIGHT*(CURRENT_FLAT*(1+LOSS_TREND)^1)^(1-MARKET_RISK_WEIGHT) -> 1187.6482 | AC48: =CURRENT_FLAT*(1+LOSS_TREND)^1 -> 1469.0167 | AD48: =MEDIAN(RET_FLOOR,BASE_RETENTION-ELAST_MARKET*(AC48/AB48-1)-ELAST_INCREASE*MAX(AC48/Y48-1,0),RET_CEIL) -> 0.72254388 | AE48: =MEDIAN(CONV_FLOOR,BASE_CONVERSION-ELAST_MARKET*(CURRENT_FLAT*(1+LOSS_TREND)^1/AB48-1),CONV_CEIL) -> 0.23154388 | AF48: =IF($J48=0,0,IF($J48=4,T48*GRAD_CONTINUE,T47)*AD48) -> 17.080766 | AG48: =APPLICANTS_PER_YEAR*($H48/Segments!$AH$2)*AE48 -> 8.0577269 | AH48: =AF48+AG48 -> 25.138493 | AI48: =IFERROR((AF48*AC48+AG48*CURRENT_FLAT*(1+LOSS_TREND)^1)/AH48,AA48) -> 1469.0167 | AJ48: =AF48*AC48+AG48*CURRENT_FLAT*(1+LOSS_TREND)^1 -> 36928.866 | AK48: =AH48*Z48*(1+LAE_RATIO) -> 15903.675 | AL48: =AF48*AC48*(PREMIUM_TAX+OTHER_VARIABLE+COMMISSION_RN)+AG48*CURRENT_FLAT*(1+LOSS_TREND)^1*(PREMIUM_TAX+OTHER_VARIABLE+COMMISSION_NB)+AH48*FIXED_PER_POLICY+AG48*NB_ACQUISITION -> 8098.0614 | AM48: =IF($J48=0,AO48,IF($J48=4,AI48,AI47)) -> 1469.0167 | AN48: =$I48*(1+LOSS_TREND)^2 -> 581.80499 | AO48: =AN48*GROSS_MULT+POLICY_FEE -> 987.72694 | AP48: =AO48^MARKET_RISK_WEIGHT*(CURRENT_FLAT*(1+LOSS_TREND)^2)^(1-MARKET_RISK_WEIGHT) -> 1222.5044 | AQ48: =CURRENT_FLAT*(1+LOSS_TREND)^2 -> 1513.0872 | AR48: =MEDIAN(RET_FLOOR,BASE_RETENTION-ELAST_MARKET*(AQ48/AP48-1)-ELAST_INCREASE*MAX(AQ48/AM48-1,0),RET_CEIL) -> 0.72215266 | AS48: =MEDIAN(CONV_FLOOR,BASE_CONVERSION-ELAST_MARKET*(CURRENT_FLAT*(1+LOSS_TREND)^2/AP48-1),CONV_CEIL) -> 0.23115266 | AT48: =IF($J48=0,0,IF($J48=4,AH48*GRAD_CONTINUE,AH47)*AR48) -> 18.157854 | AU48: =APPLICANTS_PER_YEAR*($H48/Segments!$AH$2)*AS48 -> 8.0441126 | AV48: =AT48+AU48 -> 26.201966 | AW48: =IFERROR((AT48*AQ48+AU48*CURRENT_FLAT*(1+LOSS_TREND)^2)/AV48,AO48) -> 1513.0872 | AX48: =AT48*AQ48+AU48*CURRENT_FLAT*(1+LOSS_TREND)^2 -> 39645.859 | AY48: =AV48*AN48*(1+LAE_RATIO) -> 17073.767 | AZ48: =AT48*AQ48*(PREMIUM_TAX+OTHER_VARIABLE+COMMISSION_RN)+AU48*CURRENT_FLAT*(1+LOSS_TREND)^2*(PREMIUM_TAX+OTHER_VARIABLE+COMMISSION_NB)+AV48*FIXED_PER_POLICY+AU48*NB_ACQUISITION -> 8644.21
A49: =Segments!$A$29 -> Non-greek | B49: =Segments!$B$29 -> On campus | C49: =Segments!$C$29 -> No | D49: =Segments!$D$29 -> <1.0 | E49: =Segments!$E$29 -> Grad student | F49: =Segments!$F$29 -> 3 | G49: =Segments!$G$29 -> Grad | H49: =Segments!$H$29 -> 17 | I49: =Segments!$Y$29 -> 652.97749 | J49: 4 | K49: =IF($J49=0,M49,CURRENT_FLAT) -> 1426.2298 | L49: =$I49*(1+LOSS_TREND)^0 -> 652.97749 | M49: =L49*GROSS_MULT+POLICY_FEE -> 1103.459 | N49: =M49^MARKET_RISK_WEIGHT*(CURRENT_FLAT*(1+LOSS_TREND)^0)^(1-MARKET_RISK_WEIGHT) -> 1254.5063 | O49: =CURRENT_FLAT*(1+LOSS_TREND)^0 -> 1426.2298 | P49: =MEDIAN(RET_FLOOR,BASE_RETENTION-ELAST_MARKET*(O49/N49-1)-ELAST_INCREASE*MAX(O49/K49-1,0),RET_CEIL) -> 0.78155735 | Q49: =MEDIAN(CONV_FLOOR,BASE_CONVERSION-ELAST_MARKET*(CURRENT_FLAT*(1+LOSS_TREND)^0/N49-1),CONV_CEIL) -> 0.28155735 | R49: =IF($J49=0,0,IF($J49=4,$H49*GRAD_CONTINUE,$H48)*P49) -> 6.6432374 | S49: =APPLICANTS_PER_YEAR*($H49/Segments!$AH$2)*Q49 -> 5.7437698 | T49: =R49+S49 -> 12.387007 | U49: =IFERROR((R49*O49+S49*CURRENT_FLAT*(1+LOSS_TREND)^0)/T49,M49) -> 1426.2298 | V49: =R49*O49+S49*CURRENT_FLAT*(1+LOSS_TREND)^0 -> 17666.719 | W49: =T49*L49*(1+LAE_RATIO) -> 9059.0493 | X49: =R49*O49*(PREMIUM_TAX+OTHER_VARIABLE+COMMISSION_RN)+S49*CURRENT_FLAT*(1+LOSS_TREND)^0*(PREMIUM_TAX+OTHER_VARIABLE+COMMISSION_NB)+T49*FIXED_PER_POLICY+S49*NB_ACQUISITION -> 4017.062 | Y49: =IF($J49=0,AA49,IF($J49=4,U49,U48)) -> 1426.2298 | Z49: =$I49*(1+LOSS_TREND)^1 -> 672.56681 | AA49: =Z49*GROSS_MULT+POLICY_FEE -> 1135.3127 | AB49: =AA49^MARKET_RISK_WEIGHT*(CURRENT_FLAT*(1+LOSS_TREND)^1)^(1-MARKET_RISK_WEIGHT) -> 1291.4307 | AC49: =CURRENT_FLAT*(1+LOSS_TREND)^1 -> 1469.0167 | AD49: =MEDIAN(RET_FLOOR,BASE_RETENTION-ELAST_MARKET*(AC49/AB49-1)-ELAST_INCREASE*MAX(AC49/Y49-1,0),RET_CEIL) -> 0.7722445 | AE49: =MEDIAN(CONV_FLOOR,BASE_CONVERSION-ELAST_MARKET*(CURRENT_FLAT*(1+LOSS_TREND)^1/AB49-1),CONV_CEIL) -> 0.2812445 | AF49: =IF($J49=0,0,IF($J49=4,T49*GRAD_CONTINUE,T48)*AD49) -> 4.7828991 | AG49: =APPLICANTS_PER_YEAR*($H49/Segments!$AH$2)*AE49 -> 5.7373878 | AH49: =AF49+AG49 -> 10.520287 | AI49: =IFERROR((AF49*AC49+AG49*CURRENT_FLAT*(1+LOSS_TREND)^1)/AH49,AA49) -> 1469.0167 | AJ49: =AF49*AC49+AG49*CURRENT_FLAT*(1+LOSS_TREND)^1 -> 15454.477 | AK49: =AH49*Z49*(1+LAE_RATIO) -> 7924.6673 | AL49: =AF49*AC49*(PREMIUM_TAX+OTHER_VARIABLE+COMMISSION_RN)+AG49*CURRENT_FLAT*(1+LOSS_TREND)^1*(PREMIUM_TAX+OTHER_VARIABLE+COMMISSION_NB)+AH49*FIXED_PER_POLICY+AG49*NB_ACQUISITION -> 3569.7277 | AM49: =IF($J49=0,AO49,IF($J49=4,AI49,AI48)) -> 1469.0167 | AN49: =$I49*(1+LOSS_TREND)^2 -> 692.74382 | AO49: =AN49*GROSS_MULT+POLICY_FEE -> 1168.1221 | AP49: =AO49^MARKET_RISK_WEIGHT*(CURRENT_FLAT*(1+LOSS_TREND)^2)^(1-MARKET_RISK_WEIGHT) -> 1329.4625 | AQ49: =CURRENT_FLAT*(1+LOSS_TREND)^2 -> 1513.0872 | AR49: =MEDIAN(RET_FLOOR,BASE_RETENTION-ELAST_MARKET*(AQ49/AP49-1)-ELAST_INCREASE*MAX(AQ49/AM49-1,0),RET_CEIL) -> 0.77194027 | AS49: =MEDIAN(CONV_FLOOR,BASE_CONVERSION-ELAST_MARKET*(CURRENT_FLAT*(1+LOSS_TREND)^2/AP49-1),CONV_CEIL) -> 0.28094027 | AT49: =IF($J49=0,0,IF($J49=4,AH49*GRAD_CONTINUE,AH48)*AR49) -> 4.0605165 | AU49: =APPLICANTS_PER_YEAR*($H49/Segments!$AH$2)*AS49 -> 5.7311815 | AV49: =AT49+AU49 -> 9.791698 | AW49: =IFERROR((AT49*AQ49+AU49*CURRENT_FLAT*(1+LOSS_TREND)^2)/AV49,AO49) -> 1513.0872 | AX49: =AT49*AQ49+AU49*CURRENT_FLAT*(1+LOSS_TREND)^2 -> 14815.693 | AY49: =AV49*AN49*(1+LAE_RATIO) -> 7597.1149 | AZ49: =AT49*AQ49*(PREMIUM_TAX+OTHER_VARIABLE+COMMISSION_RN)+AU49*CURRENT_FLAT*(1+LOSS_TREND)^2*(PREMIUM_TAX+OTHER_VARIABLE+COMMISSION_NB)+AV49*FIXED_PER_POLICY+AU49*NB_ACQUISITION -> 3442.7916
A50: =Segments!$A$30 -> Non-greek | B50: =Segments!$B$30 -> On campus | C50: =Segments!$C$30 -> No | D50: =Segments!$D$30 -> 1.0-2.0 | E50: =Segments!$E$30 -> Freshman | F50: =Segments!$F$30 -> 1 | G50: =Segments!$G$30 -> Base | H50: =Segments!$H$30 -> 80 | I50: =Segments!$Y$30 -> 449.94965 | J50: 0 | K50: =IF($J50=0,M50,CURRENT_FLAT) -> 773.31988 | L50: =$I50*(1+LOSS_TREND)^0 -> 449.94965 | M50: =L50*GROSS_MULT+POLICY_FEE -> 773.31988 | N50: =M50^MARKET_RISK_WEIGHT*(CURRENT_FLAT*(1+LOSS_TREND)^0)^(1-MARKET_RISK_WEIGHT) -> 1050.2056 | O50: =CURRENT_FLAT*(1+LOSS_TREND)^0 -> 1426.2298 | P50: =MEDIAN(RET_FLOOR,BASE_RETENTION-ELAST_MARKET*(O50/N50-1)-ELAST_INCREASE*MAX(O50/K50-1,0),RET_CEIL) -> 0.41768752 | Q50: =MEDIAN(CONV_FLOOR,BASE_CONVERSION-ELAST_MARKET*(CURRENT_FLAT*(1+LOSS_TREND)^0/N50-1),CONV_CEIL) -> 0.17097594 | R50: =IF($J50=0,0,IF($J50=4,$H50*GRAD_CONTINUE,$H49)*P50) -> 0 | S50: =APPLICANTS_PER_YEAR*($H50/Segments!$AH$2)*Q50 -> 16.41369 | T50: =R50+S50 -> 16.41369 | U50: =IFERROR((R50*O50+S50*CURRENT_FLAT*(1+LOSS_TREND)^0)/T50,M50) -> 1426.2298 | V50: =R50*O50+S50*CURRENT_FLAT*(1+LOSS_TREND)^0 -> 23409.693 | W50: =T50*L50*(1+LAE_RATIO) -> 8271.5741 | X50: =R50*O50*(PREMIUM_TAX+OTHER_VARIABLE+COMMISSION_RN)+S50*CURRENT_FLAT*(1+LOSS_TREND)^0*(PREMIUM_TAX+OTHER_VARIABLE+COMMISSION_NB)+T50*FIXED_PER_POLICY+S50*NB_ACQUISITION -> 5982.3873 | Y50: =IF($J50=0,AA50,IF($J50=4,U50,U49)) -> 795.26948 | Z50: =$I50*(1+LOSS_TREND)^1 -> 463.44814 | AA50: =Z50*GROSS_MULT+POLICY_FEE -> 795.26948 | AB50: =AA50^MARKET_RISK_WEIGHT*(CURRENT_FLAT*(1+LOSS_TREND)^1)^(1-MARKET_RISK_WEIGHT) -> 1080.8627 | AC50: =CURRENT_FLAT*(1+LOSS_TREND)^1 -> 1469.0167 | AD50: =MEDIAN(RET_FLOOR,BASE_RETENTION-ELAST_MARKET*(AC50/AB50-1)-ELAST_INCREASE*MAX(AC50/Y50-1,0),RET_CEIL) -> 0.41628443 | AE50: =MEDIAN(CONV_FLOOR,BASE_CONVERSION-ELAST_MARKET*(CURRENT_FLAT*(1+LOSS_TREND)^1/AB50-1),CONV_CEIL) -> 0.1704425 | AF50: =IF($J50=0,0,IF($J50=4,T50*GRAD_CONTINUE,T49)*AD50) -> 0 | AG50: =APPLICANTS_PER_YEAR*($H50/Segments!$AH$2)*AE50 -> 16.36248 | AH50: =AF50+AG50 -> 16.36248 | AI50: =IFERROR((AF50*AC50+AG50*CURRENT_FLAT*(1+LOSS_TREND)^1)/AH50,AA50) -> 1469.0167 | AJ50: =AF50*AC50+AG50*CURRENT_FLAT*(1+LOSS_TREND)^1 -> 24036.756 | AK50: =AH50*Z50*(1+LAE_RATIO) -> 8493.1404 | AL50: =AF50*AC50*(PREMIUM_TAX+OTHER_VARIABLE+COMMISSION_RN)+AG50*CURRENT_FLAT*(1+LOSS_TREND)^1*(PREMIUM_TAX+OTHER_VARIABLE+COMMISSION_NB)+AH50*FIXED_PER_POLICY+AG50*NB_ACQUISITION -> 6120.545 | AM50: =IF($J50=0,AO50,IF($J50=4,AI50,AI49)) -> 817.87756 | AN50: =$I50*(1+LOSS_TREND)^2 -> 477.35159 | AO50: =AN50*GROSS_MULT+POLICY_FEE -> 817.87756 | AP50: =AO50^MARKET_RISK_WEIGHT*(CURRENT_FLAT*(1+LOSS_TREND)^2)^(1-MARKET_RISK_WEIGHT) -> 1112.4388 | AQ50: =CURRENT_FLAT*(1+LOSS_TREND)^2 -> 1513.0872 | AR50: =MEDIAN(RET_FLOOR,BASE_RETENTION-ELAST_MARKET*(AQ50/AP50-1)-ELAST_INCREASE*MAX(AQ50/AM50-1,0),RET_CEIL) -> 0.41491838 | AS50: =MEDIAN(CONV_FLOOR,BASE_CONVERSION-ELAST_MARKET*(CURRENT_FLAT*(1+LOSS_TREND)^2/AP50-1),CONV_CEIL) -> 0.1699234 | AT50: =IF($J50=0,0,IF($J50=4,AH50*GRAD_CONTINUE,AH49)*AR50) -> 0 | AU50: =APPLICANTS_PER_YEAR*($H50/Segments!$AH$2)*AS50 -> 16.312646 | AV50: =AT50+AU50 -> 16.312646 | AW50: =IFERROR((AT50*AQ50+AU50*CURRENT_FLAT*(1+LOSS_TREND)^2)/AV50,AO50) -> 1513.0872 | AX50: =AT50*AQ50+AU50*CURRENT_FLAT*(1+LOSS_TREND)^2 -> 24682.456 | AY50: =AV50*AN50*(1+LAE_RATIO) -> 8721.2918 | AZ50: =AT50*AQ50*(PREMIUM_TAX+OTHER_VARIABLE+COMMISSION_RN)+AU50*CURRENT_FLAT*(1+LOSS_TREND)^2*(PREMIUM_TAX+OTHER_VARIABLE+COMMISSION_NB)+AV50*FIXED_PER_POLICY+AU50*NB_ACQUISITION -> 6262.9392
A51: =Segments!$A$31 -> Non-greek | B51: =Segments!$B$31 -> On campus | C51: =Segments!$C$31 -> No | D51: =Segments!$D$31 -> 1.0-2.0 | E51: =Segments!$E$31 -> Sophomore | F51: =Segments!$F$31 -> 1 | G51: =Segments!$G$31 -> Sophomore | H51: =Segments!$H$31 -> 84 | I51: =Segments!$Y$31 -> 445.37197 | J51: 1 | K51: =IF($J51=0,M51,CURRENT_FLAT) -> 1426.2298 | L51: =$I51*(1+LOSS_TREND)^0 -> 445.37197 | M51: =L51*GROSS_MULT+POLICY_FEE -> 765.87622 | N51: =M51^MARKET_RISK_WEIGHT*(CURRENT_FLAT*(1+LOSS_TREND)^0)^(1-MARKET_RISK_WEIGHT) -> 1045.139 | O51: =CURRENT_FLAT*(1+LOSS_TREND)^0 -> 1426.2298 | P51: =MEDIAN(RET_FLOOR,BASE_RETENTION-ELAST_MARKET*(O51/N51-1)-ELAST_INCREASE*MAX(O51/K51-1,0),RET_CEIL) -> 0.66768415 | Q51: =MEDIAN(CONV_FLOOR,BASE_CONVERSION-ELAST_MARKET*(CURRENT_FLAT*(1+LOSS_TREND)^0/N51-1),CONV_CEIL) -> 0.16768415 | R51: =IF($J51=0,0,IF($J51=4,$H51*GRAD_CONTINUE,$H50)*P51) -> 53.414732 | S51: =APPLICANTS_PER_YEAR*($H51/Segments!$AH$2)*Q51 -> 16.902562 | T51: =R51+S51 -> 70.317294 | U51: =IFERROR((R51*O51+S51*CURRENT_FLAT*(1+LOSS_TREND)^0)/T51,M51) -> 1426.2298 | V51: =R51*O51+S51*CURRENT_FLAT*(1+LOSS_TREND)^0 -> 100288.62 | W51: =T51*L51*(1+LAE_RATIO) -> 35075.434 | X51: =R51*O51*(PREMIUM_TAX+OTHER_VARIABLE+COMMISSION_RN)+S51*CURRENT_FLAT*(1+LOSS_TREND)^0*(PREMIUM_TAX+OTHER_VARIABLE+COMMISSION_NB)+T51*FIXED_PER_POLICY+S51*NB_ACQUISITION -> 21627.202 | Y51: =IF($J51=0,AA51,IF($J51=4,U51,U50)) -> 1426.2298 | Z51: =$I51*(1+LOSS_TREND)^1 -> 458.73313 | AA51: =Z51*GROSS_MULT+POLICY_FEE -> 787.60251 | AB51: =AA51^MARKET_RISK_WEIGHT*(CURRENT_FLAT*(1+LOSS_TREND)^1)^(1-MARKET_RISK_WEIGHT) -> 1075.6399 | AC51: =CURRENT_FLAT*(1+LOSS_TREND)^1 -> 1469.0167 | AD51: =MEDIAN(RET_FLOOR,BASE_RETENTION-ELAST_MARKET*(AC51/AB51-1)-ELAST_INCREASE*MAX(AC51/Y51-1,0),RET_CEIL) -> 0.65814291 | AE51: =MEDIAN(CONV_FLOOR,BASE_CONVERSION-ELAST_MARKET*(CURRENT_FLAT*(1+LOSS_TREND)^1/AB51-1),CONV_CEIL) -> 0.16714291 | AF51: =IF($J51=0,0,IF($J51=4,T51*GRAD_CONTINUE,T50)*AD51) -> 10.802554 | AG51: =APPLICANTS_PER_YEAR*($H51/Segments!$AH$2)*AE51 -> 16.848006 | AH51: =AF51+AG51 -> 27.650559 | AI51: =IFERROR((AF51*AC51+AG51*CURRENT_FLAT*(1+LOSS_TREND)^1)/AH51,AA51) -> 1469.0167 | AJ51: =AF51*AC51+AG51*CURRENT_FLAT*(1+LOSS_TREND)^1 -> 40619.132 | AK51: =AH51*Z51*(1+LAE_RATIO) -> 14206.335 | AL51: =AF51*AC51*(PREMIUM_TAX+OTHER_VARIABLE+COMMISSION_RN)+AG51*CURRENT_FLAT*(1+LOSS_TREND)^1*(PREMIUM_TAX+OTHER_VARIABLE+COMMISSION_NB)+AH51*FIXED_PER_POLICY+AG51*NB_ACQUISITION -> 9517.4773 | AM51: =IF($J51=0,AO51,IF($J51=4,AI51,AI50)) -> 1469.0167 | AN51: =$I51*(1+LOSS_TREND)^2 -> 472.49513 | AO51: =AN51*GROSS_MULT+POLICY_FEE -> 809.98058 | AP51: =AO51^MARKET_RISK_WEIGHT*(CURRENT_FLAT*(1+LOSS_TREND)^2)^(1-MARKET_RISK_WEIGHT) -> 1107.0552 | AQ51: =CURRENT_FLAT*(1+LOSS_TREND)^2 -> 1513.0872 | AR51: =MEDIAN(RET_FLOOR,BASE_RETENTION-ELAST_MARKET*(AQ51/AP51-1)-ELAST_INCREASE*MAX(AQ51/AM51-1,0),RET_CEIL) -> 0.65761621 | AS51: =MEDIAN(CONV_FLOOR,BASE_CONVERSION-ELAST_MARKET*(CURRENT_FLAT*(1+LOSS_TREND)^2/AP51-1),CONV_CEIL) -> 0.16661621 | AT51: =IF($J51=0,0,IF($J51=4,AH51*GRAD_CONTINUE,AH50)*AR51) -> 10.760232 | AU51: =APPLICANTS_PER_YEAR*($H51/Segments!$AH$2)*AS51 -> 16.794914 | AV51: =AT51+AU51 -> 27.555146 | AW51: =IFERROR((AT51*AQ51+AU51*CURRENT_FLAT*(1+LOSS_TREND)^2)/AV51,AO51) -> 1513.0872 | AX51: =AT51*AQ51+AU51*CURRENT_FLAT*(1+LOSS_TREND)^2 -> 41693.337 | AY51: =AV51*AN51*(1+LAE_RATIO) -> 14582.033 | AZ51: =AT51*AQ51*(PREMIUM_TAX+OTHER_VARIABLE+COMMISSION_RN)+AU51*CURRENT_FLAT*(1+LOSS_TREND)^2*(PREMIUM_TAX+OTHER_VARIABLE+COMMISSION_NB)+AV51*FIXED_PER_POLICY+AU51*NB_ACQUISITION -> 9740.4424
A52: =Segments!$A$32 -> Non-greek | B52: =Segments!$B$32 -> On campus | C52: =Segments!$C$32 -> No | D52: =Segments!$D$32 -> 1.0-2.0 | E52: =Segments!$E$32 -> Junior | F52: =Segments!$F$32 -> 2 | G52: =Segments!$G$32 -> Base | H52: =Segments!$H$32 -> 76 | I52: =Segments!$Y$32 -> 532.40907 | J52: 2 | K52: =IF($J52=0,M52,CURRENT_FLAT) -> 1426.2298 | L52: =$I52*(1+LOSS_TREND)^0 -> 532.40907 | M52: =L52*GROSS_MULT+POLICY_FEE -> 907.40532 | N52: =M52^MARKET_RISK_WEIGHT*(CURRENT_FLAT*(1+LOSS_TREND)^0)^(1-MARKET_RISK_WEIGHT) -> 1137.6153 | O52: =CURRENT_FLAT*(1+LOSS_TREND)^0 -> 1426.2298 | P52: =MEDIAN(RET_FLOOR,BASE_RETENTION-ELAST_MARKET*(O52/N52-1)-ELAST_INCREASE*MAX(O52/K52-1,0),RET_CEIL) -> 0.72314933 | Q52: =MEDIAN(CONV_FLOOR,BASE_CONVERSION-ELAST_MARKET*(CURRENT_FLAT*(1+LOSS_TREND)^0/N52-1),CONV_CEIL) -> 0.22314933 | R52: =IF($J52=0,0,IF($J52=4,$H52*GRAD_CONTINUE,$H51)*P52) -> 60.744544 | S52: =APPLICANTS_PER_YEAR*($H52/Segments!$AH$2)*Q52 -> 20.351219 | T52: =R52+S52 -> 81.095763 | U52: =IFERROR((R52*O52+S52*CURRENT_FLAT*(1+LOSS_TREND)^0)/T52,M52) -> 1426.2298 | V52: =R52*O52+S52*CURRENT_FLAT*(1+LOSS_TREND)^0 -> 115661.19 | W52: =T52*L52*(1+LAE_RATIO) -> 48357.254 | X52: =R52*O52*(PREMIUM_TAX+OTHER_VARIABLE+COMMISSION_RN)+S52*CURRENT_FLAT*(1+LOSS_TREND)^0*(PREMIUM_TAX+OTHER_VARIABLE+COMMISSION_NB)+T52*FIXED_PER_POLICY+S52*NB_ACQUISITION -> 25006.554 | Y52: =IF($J52=0,AA52,IF($J52=4,U52,U51)) -> 1426.2298 | Z52: =$I52*(1+LOSS_TREND)^1 -> 548.38134 | AA52: =Z52*GROSS_MULT+POLICY_FEE -> 933.37748 | AB52: =AA52^MARKET_RISK_WEIGHT*(CURRENT_FLAT*(1+LOSS_TREND)^1)^(1-MARKET_RISK_WEIGHT) -> 1170.9599 | AC52: =CURRENT_FLAT*(1+LOSS_TREND)^1 -> 1469.0167 | AD52: =MEDIAN(RET_FLOOR,BASE_RETENTION-ELAST_MARKET*(AC52/AB52-1)-ELAST_INCREASE*MAX(AC52/Y52-1,0),RET_CEIL) -> 0.71372973 | AE52: =MEDIAN(CONV_FLOOR,BASE_CONVERSION-ELAST_MARKET*(CURRENT_FLAT*(1+LOSS_TREND)^1/AB52-1),CONV_CEIL) -> 0.22272973 | AF52: =IF($J52=0,0,IF($J52=4,T52*GRAD_CONTINUE,T51)*AD52) -> 50.187543 | AG52: =APPLICANTS_PER_YEAR*($H52/Segments!$AH$2)*AE52 -> 20.312951 | AH52: =AF52+AG52 -> 70.500494 | AI52: =IFERROR((AF52*AC52+AG52*CURRENT_FLAT*(1+LOSS_TREND)^1)/AH52,AA52) -> 1469.0167 | AJ52: =AF52*AC52+AG52*CURRENT_FLAT*(1+LOSS_TREND)^1 -> 103566.4 | AK52: =AH52*Z52*(1+LAE_RATIO) -> 43300.494 | AL52: =AF52*AC52*(PREMIUM_TAX+OTHER_VARIABLE+COMMISSION_RN)+AG52*CURRENT_FLAT*(1+LOSS_TREND)^1*(PREMIUM_TAX+OTHER_VARIABLE+COMMISSION_NB)+AH52*FIXED_PER_POLICY+AG52*NB_ACQUISITION -> 22536.286 | AM52: =IF($J52=0,AO52,IF($J52=4,AI52,AI51)) -> 1469.0167 | AN52: =$I52*(1+LOSS_TREND)^2 -> 564.83278 | AO52: =AN52*GROSS_MULT+POLICY_FEE -> 960.12881 | AP52: =AO52^MARKET_RISK_WEIGHT*(CURRENT_FLAT*(1+LOSS_TREND)^2)^(1-MARKET_RISK_WEIGHT) -> 1205.3044 | AQ52: =CURRENT_FLAT*(1+LOSS_TREND)^2 -> 1513.0872 | AR52: =MEDIAN(RET_FLOOR,BASE_RETENTION-ELAST_MARKET*(AQ52/AP52-1)-ELAST_INCREASE*MAX(AQ52/AM52-1,0),RET_CEIL) -> 0.71332154 | AS52: =MEDIAN(CONV_FLOOR,BASE_CONVERSION-ELAST_MARKET*(CURRENT_FLAT*(1+LOSS_TREND)^2/AP52-1),CONV_CEIL) -> 0.22232154 | AT52: =IF($J52=0,0,IF($J52=4,AH52*GRAD_CONTINUE,AH51)*AR52) -> 19.723739 | AU52: =APPLICANTS_PER_YEAR*($H52/Segments!$AH$2)*AS52 -> 20.275724 | AV52: =AT52+AU52 -> 39.999463 | AW52: =IFERROR((AT52*AQ52+AU52*CURRENT_FLAT*(1+LOSS_TREND)^2)/AV52,AO52) -> 1513.0872 | AX52: =AT52*AQ52+AU52*CURRENT_FLAT*(1+LOSS_TREND)^2 -> 60522.675 | AY52: =AV52*AN52*(1+LAE_RATIO) -> 25304.169 | AZ52: =AT52*AQ52*(PREMIUM_TAX+OTHER_VARIABLE+COMMISSION_RN)+AU52*CURRENT_FLAT*(1+LOSS_TREND)^2*(PREMIUM_TAX+OTHER_VARIABLE+COMMISSION_NB)+AV52*FIXED_PER_POLICY+AU52*NB_ACQUISITION -> 13819.431
A53: =Segments!$A$33 -> Non-greek | B53: =Segments!$B$33 -> On campus | C53: =Segments!$C$33 -> No | D53: =Segments!$D$33 -> 1.0-2.0 | E53: =Segments!$E$33 -> Senior | F53: =Segments!$F$33 -> 3 | G53: =Segments!$G$33 -> Base | H53: =Segments!$H$33 -> 90 | I53: =Segments!$Y$33 -> 497.63608 | J53: 3 | K53: =IF($J53=0,M53,CURRENT_FLAT) -> 1426.2298 | L53: =$I53*(1+LOSS_TREND)^0 -> 497.63608 | M53: =L53*GROSS_MULT+POLICY_FEE -> 850.86173 | N53: =M53^MARKET_RISK_WEIGHT*(CURRENT_FLAT*(1+LOSS_TREND)^0)^(1-MARKET_RISK_WEIGHT) -> 1101.6008 | O53: =CURRENT_FLAT*(1+LOSS_TREND)^0 -> 1426.2298 | P53: =MEDIAN(RET_FLOOR,BASE_RETENTION-ELAST_MARKET*(O53/N53-1)-ELAST_INCREASE*MAX(O53/K53-1,0),RET_CEIL) -> 0.7026558 | Q53: =MEDIAN(CONV_FLOOR,BASE_CONVERSION-ELAST_MARKET*(CURRENT_FLAT*(1+LOSS_TREND)^0/N53-1),CONV_CEIL) -> 0.2026558 | R53: =IF($J53=0,0,IF($J53=4,$H53*GRAD_CONTINUE,$H52)*P53) -> 53.401841 | S53: =APPLICANTS_PER_YEAR*($H53/Segments!$AH$2)*Q53 -> 21.886827 | T53: =R53+S53 -> 75.288668 | U53: =IFERROR((R53*O53+S53*CURRENT_FLAT*(1+LOSS_TREND)^0)/T53,M53) -> 1426.2298 | V53: =R53*O53+S53*CURRENT_FLAT*(1+LOSS_TREND)^0 -> 107378.94 | W53: =T53*L53*(1+LAE_RATIO) -> 41962.32 | X53: =R53*O53*(PREMIUM_TAX+OTHER_VARIABLE+COMMISSION_RN)+S53*CURRENT_FLAT*(1+LOSS_TREND)^0*(PREMIUM_TAX+OTHER_VARIABLE+COMMISSION_NB)+T53*FIXED_PER_POLICY+S53*NB_ACQUISITION -> 23440.111 | Y53: =IF($J53=0,AA53,IF($J53=4,U53,U52)) -> 1426.2298 | Z53: =$I53*(1+LOSS_TREND)^1 -> 512.56516 | AA53: =Z53*GROSS_MULT+POLICY_FEE -> 875.13758 | AB53: =AA53^MARKET_RISK_WEIGHT*(CURRENT_FLAT*(1+LOSS_TREND)^1)^(1-MARKET_RISK_WEIGHT) -> 1133.8394 | AC53: =CURRENT_FLAT*(1+LOSS_TREND)^1 -> 1469.0167 | AD53: =MEDIAN(RET_FLOOR,BASE_RETENTION-ELAST_MARKET*(AC53/AB53-1)-ELAST_INCREASE*MAX(AC53/Y53-1,0),RET_CEIL) -> 0.69319365 | AE53: =MEDIAN(CONV_FLOOR,BASE_CONVERSION-ELAST_MARKET*(CURRENT_FLAT*(1+LOSS_TREND)^1/AB53-1),CONV_CEIL) -> 0.20219365 | AF53: =IF($J53=0,0,IF($J53=4,T53*GRAD_CONTINUE,T52)*AD53) -> 56.215068 | AG53: =APPLICANTS_PER_YEAR*($H53/Segments!$AH$2)*AE53 -> 21.836914 | AH53: =AF53+AG53 -> 78.051983 | AI53: =IFERROR((AF53*AC53+AG53*CURRENT_FLAT*(1+LOSS_TREND)^1)/AH53,AA53) -> 1469.0167 | AJ53: =AF53*AC53+AG53*CURRENT_FLAT*(1+LOSS_TREND)^1 -> 114659.66 | AK53: =AH53*Z53*(1+LAE_RATIO) -> 44807.534 | AL53: =AF53*AC53*(PREMIUM_TAX+OTHER_VARIABLE+COMMISSION_RN)+AG53*CURRENT_FLAT*(1+LOSS_TREND)^1*(PREMIUM_TAX+OTHER_VARIABLE+COMMISSION_NB)+AH53*FIXED_PER_POLICY+AG53*NB_ACQUISITION -> 24900.397 | AM53: =IF($J53=0,AO53,IF($J53=4,AI53,AI52)) -> 1469.0167 | AN53: =$I53*(1+LOSS_TREND)^2 -> 527.94212 | AO53: =AN53*GROSS_MULT+POLICY_FEE -> 900.14171 | AP53: =AO53^MARKET_RISK_WEIGHT*(CURRENT_FLAT*(1+LOSS_TREND)^2)^(1-MARKET_RISK_WEIGHT) -> 1167.0445 | AQ53: =CURRENT_FLAT*(1+LOSS_TREND)^2 -> 1513.0872 | AR53: =MEDIAN(RET_FLOOR,BASE_RETENTION-ELAST_MARKET*(AQ53/AP53-1)-ELAST_INCREASE*MAX(AQ53/AM53-1,0),RET_CEIL) -> 0.69274401 | AS53: =MEDIAN(CONV_FLOOR,BASE_CONVERSION-ELAST_MARKET*(CURRENT_FLAT*(1+LOSS_TREND)^2/AP53-1),CONV_CEIL) -> 0.20174401 | AT53: =IF($J53=0,0,IF($J53=4,AH53*GRAD_CONTINUE,AH52)*AR53) -> 48.838795 | AU53: =APPLICANTS_PER_YEAR*($H53/Segments!$AH$2)*AS53 -> 21.788353 | AV53: =AT53+AU53 -> 70.627149 | AW53: =IFERROR((AT53*AQ53+AU53*CURRENT_FLAT*(1+LOSS_TREND)^2)/AV53,AO53) -> 1513.0872 | AX53: =AT53*AQ53+AU53*CURRENT_FLAT*(1+LOSS_TREND)^2 -> 106865.03 | AY53: =AV53*AN53*(1+LAE_RATIO) -> 41761.492 | AZ53: =AT53*AQ53*(PREMIUM_TAX+OTHER_VARIABLE+COMMISSION_RN)+AU53*CURRENT_FLAT*(1+LOSS_TREND)^2*(PREMIUM_TAX+OTHER_VARIABLE+COMMISSION_NB)+AV53*FIXED_PER_POLICY+AU53*NB_ACQUISITION -> 23308.612
A54: =Segments!$A$34 -> Non-greek | B54: =Segments!$B$34 -> On campus | C54: =Segments!$C$34 -> No | D54: =Segments!$D$34 -> 1.0-2.0 | E54: =Segments!$E$34 -> Grad student | F54: =Segments!$F$34 -> 3 | G54: =Segments!$G$34 -> Grad | H54: =Segments!$H$34 -> 40 | I54: =Segments!$Y$34 -> 592.52554 | J54: 4 | K54: =IF($J54=0,M54,CURRENT_FLAT) -> 1426.2298 | L54: =$I54*(1+LOSS_TREND)^0 -> 592.52554 | M54: =L54*GROSS_MULT+POLICY_FEE -> 1005.1594 | N54: =M54^MARKET_RISK_WEIGHT*(CURRENT_FLAT*(1+LOSS_TREND)^0)^(1-MARKET_RISK_WEIGHT) -> 1197.3255 | O54: =CURRENT_FLAT*(1+LOSS_TREND)^0 -> 1426.2298 | P54: =MEDIAN(RET_FLOOR,BASE_RETENTION-ELAST_MARKET*(O54/N54-1)-ELAST_INCREASE*MAX(O54/K54-1,0),RET_CEIL) -> 0.75441015 | Q54: =MEDIAN(CONV_FLOOR,BASE_CONVERSION-ELAST_MARKET*(CURRENT_FLAT*(1+LOSS_TREND)^0/N54-1),CONV_CEIL) -> 0.25441015 | R54: =IF($J54=0,0,IF($J54=4,$H54*GRAD_CONTINUE,$H53)*P54) -> 15.088203 | S54: =APPLICANTS_PER_YEAR*($H54/Segments!$AH$2)*Q54 -> 12.211687 | T54: =R54+S54 -> 27.29989 | U54: =IFERROR((R54*O54+S54*CURRENT_FLAT*(1+LOSS_TREND)^0)/T54,M54) -> 1426.2298 | V54: =R54*O54+S54*CURRENT_FLAT*(1+LOSS_TREND)^0 -> 38935.916 | W54: =T54*L54*(1+LAE_RATIO) -> 18116.988 | X54: =R54*O54*(PREMIUM_TAX+OTHER_VARIABLE+COMMISSION_RN)+S54*CURRENT_FLAT*(1+LOSS_TREND)^0*(PREMIUM_TAX+OTHER_VARIABLE+COMMISSION_NB)+T54*FIXED_PER_POLICY+S54*NB_ACQUISITION -> 8819.7617 | Y54: =IF($J54=0,AA54,IF($J54=4,U54,U53)) -> 1426.2298 | Z54: =$I54*(1+LOSS_TREND)^1 -> 610.30131 | AA54: =Z54*GROSS_MULT+POLICY_FEE -> 1034.0642 | AB54: =AA54^MARKET_RISK_WEIGHT*(CURRENT_FLAT*(1+LOSS_TREND)^1)^(1-MARKET_RISK_WEIGHT) -> 1232.5005 | AC54: =CURRENT_FLAT*(1+LOSS_TREND)^1 -> 1469.0167 | AD54: =MEDIAN(RET_FLOOR,BASE_RETENTION-ELAST_MARKET*(AC54/AB54-1)-ELAST_INCREASE*MAX(AC54/Y54-1,0),RET_CEIL) -> 0.74505028 | AE54: =MEDIAN(CONV_FLOOR,BASE_CONVERSION-ELAST_MARKET*(CURRENT_FLAT*(1+LOSS_TREND)^1/AB54-1),CONV_CEIL) -> 0.25405028 | AF54: =IF($J54=0,0,IF($J54=4,T54*GRAD_CONTINUE,T53)*AD54) -> 10.169895 | AG54: =APPLICANTS_PER_YEAR*($H54/Segments!$AH$2)*AE54 -> 12.194413 | AH54: =AF54+AG54 -> 22.364309 | AI54: =IFERROR((AF54*AC54+AG54*CURRENT_FLAT*(1+LOSS_TREND)^1)/AH54,AA54) -> 1469.0167 | AJ54: =AF54*AC54+AG54*CURRENT_FLAT*(1+LOSS_TREND)^1 -> 32853.542 | AK54: =AH54*Z54*(1+LAE_RATIO) -> 15286.843 | AL54: =AF54*AC54*(PREMIUM_TAX+OTHER_VARIABLE+COMMISSION_RN)+AG54*CURRENT_FLAT*(1+LOSS_TREND)^1*(PREMIUM_TAX+OTHER_VARIABLE+COMMISSION_NB)+AH54*FIXED_PER_POLICY+AG54*NB_ACQUISITION -> 7588.4489 | AM54: =IF($J54=0,AO54,IF($J54=4,AI54,AI53)) -> 1469.0167 | AN54: =$I54*(1+LOSS_TREND)^2 -> 628.61035 | AO54: =AN54*GROSS_MULT+POLICY_FEE -> 1063.8361 | AP54: =AO54^MARKET_RISK_WEIGHT*(CURRENT_FLAT*(1+LOSS_TREND)^2)^(1-MARKET_RISK_WEIGHT) -> 1268.7304 | AQ54: =CURRENT_FLAT*(1+LOSS_TREND)^2 -> 1513.0872 | AR54: =MEDIAN(RET_FLOOR,BASE_RETENTION-ELAST_MARKET*(AQ54/AP54-1)-ELAST_INCREASE*MAX(AQ54/AM54-1,0),RET_CEIL) -> 0.74470026 | AS54: =MEDIAN(CONV_FLOOR,BASE_CONVERSION-ELAST_MARKET*(CURRENT_FLAT*(1+LOSS_TREND)^2/AP54-1),CONV_CEIL) -> 0.25370026 | AT54: =IF($J54=0,0,IF($J54=4,AH54*GRAD_CONTINUE,AH53)*AR54) -> 8.3273533 | AU54: =APPLICANTS_PER_YEAR*($H54/Segments!$AH$2)*AS54 -> 12.177613 | AV54: =AT54+AU54 -> 20.504966 | AW54: =IFERROR((AT54*AQ54+AU54*CURRENT_FLAT*(1+LOSS_TREND)^2)/AV54,AO54) -> 1513.0872 | AX54: =AT54*AQ54+AU54*CURRENT_FLAT*(1+LOSS_TREND)^2 -> 31025.801 | AY54: =AV54*AN54*(1+LAE_RATIO) -> 14436.39 | AZ54: =AT54*AQ54*(PREMIUM_TAX+OTHER_VARIABLE+COMMISSION_RN)+AU54*CURRENT_FLAT*(1+LOSS_TREND)^2*(PREMIUM_TAX+OTHER_VARIABLE+COMMISSION_NB)+AV54*FIXED_PER_POLICY+AU54*NB_ACQUISITION -> 7223.3186
A55: =Segments!$A$35 -> Non-greek | B55: =Segments!$B$35 -> On campus | C55: =Segments!$C$35 -> No | D55: =Segments!$D$35 -> 2.0-3.0 | E55: =Segments!$E$35 -> Freshman | F55: =Segments!$F$35 -> 1 | G55: =Segments!$G$35 -> Base | H55: =Segments!$H$35 -> 143 | I55: =Segments!$Y$35 -> 442.1564 | J55: 0 | K55: =IF($J55=0,M55,CURRENT_FLAT) -> 760.64744 | L55: =$I55*(1+LOSS_TREND)^0 -> 442.1564 | M55: =L55*GROSS_MULT+POLICY_FEE -> 760.64744 | N55: =M55^MARKET_RISK_WEIGHT*(CURRENT_FLAT*(1+LOSS_TREND)^0)^(1-MARKET_RISK_WEIGHT) -> 1041.5652 | O55: =CURRENT_FLAT*(1+LOSS_TREND)^0 -> 1426.2298 | P55: =MEDIAN(RET_FLOOR,BASE_RETENTION-ELAST_MARKET*(O55/N55-1)-ELAST_INCREASE*MAX(O55/K55-1,0),RET_CEIL) -> 0.40283677 | Q55: =MEDIAN(CONV_FLOOR,BASE_CONVERSION-ELAST_MARKET*(CURRENT_FLAT*(1+LOSS_TREND)^0/N55-1),CONV_CEIL) -> 0.16534301 | R55: =IF($J55=0,0,IF($J55=4,$H55*GRAD_CONTINUE,$H54)*P55) -> 0 | S55: =APPLICANTS_PER_YEAR*($H55/Segments!$AH$2)*Q55 -> 28.37286 | T55: =R55+S55 -> 28.37286 | U55: =IFERROR((R55*O55+S55*CURRENT_FLAT*(1+LOSS_TREND)^0)/T55,M55) -> 1426.2298 | V55: =R55*O55+S55*CURRENT_FLAT*(1+LOSS_TREND)^0 -> 40466.217 | W55: =T55*L55*(1+LAE_RATIO) -> 14050.67 | X55: =R55*O55*(PREMIUM_TAX+OTHER_VARIABLE+COMMISSION_RN)+S55*CURRENT_FLAT*(1+LOSS_TREND)^0*(PREMIUM_TAX+OTHER_VARIABLE+COMMISSION_NB)+T55*FIXED_PER_POLICY+S55*NB_ACQUISITION -> 10341.211 | Y55: =IF($J55=0,AA55,IF($J55=4,U55,U54)) -> 782.21687 | Z55: =$I55*(1+LOSS_TREND)^1 -> 455.42109 | AA55: =Z55*GROSS_MULT+POLICY_FEE -> 782.21687 | AB55: =AA55^MARKET_RISK_WEIGHT*(CURRENT_FLAT*(1+LOSS_TREND)^1)^(1-MARKET_RISK_WEIGHT) -> 1071.956 | AC55: =CURRENT_FLAT*(1+LOSS_TREND)^1 -> 1469.0167 | AD55: =MEDIAN(RET_FLOOR,BASE_RETENTION-ELAST_MARKET*(AC55/AB55-1)-ELAST_INCREASE*MAX(AC55/Y55-1,0),RET_CEIL) -> 0.40139104 | AE55: =MEDIAN(CONV_FLOOR,BASE_CONVERSION-ELAST_MARKET*(CURRENT_FLAT*(1+LOSS_TREND)^1/AB55-1),CONV_CEIL) -> 0.16479618 | AF55: =IF($J55=0,0,IF($J55=4,T55*GRAD_CONTINUE,T54)*AD55) -> 0 | AG55: =APPLICANTS_PER_YEAR*($H55/Segments!$AH$2)*AE55 -> 28.279024 | AH55: =AF55+AG55 -> 28.279024 | AI55: =IFERROR((AF55*AC55+AG55*CURRENT_FLAT*(1+LOSS_TREND)^1)/AH55,AA55) -> 1469.0167 | AJ55: =AF55*AC55+AG55*CURRENT_FLAT*(1+LOSS_TREND)^1 -> 41542.357 | AK55: =AH55*Z55*(1+LAE_RATIO) -> 14424.327 | AL55: =AF55*AC55*(PREMIUM_TAX+OTHER_VARIABLE+COMMISSION_RN)+AG55*CURRENT_FLAT*(1+LOSS_TREND)^1*(PREMIUM_TAX+OTHER_VARIABLE+COMMISSION_NB)+AH55*FIXED_PER_POLICY+AG55*NB_ACQUISITION -> 10578.044 | AM55: =IF($J55=0,AO55,IF($J55=4,AI55,AI54)) -> 804.43337 | AN55: =$I55*(1+LOSS_TREND)^2 -> 469.08372 | AO55: =AN55*GROSS_MULT+POLICY_FEE -> 804.43337 | AP55: =AO55^MARKET_RISK_WEIGHT*(CURRENT_FLAT*(1+LOSS_TREND)^2)^(1-MARKET_RISK_WEIGHT) -> 1103.2578 | AQ55: =CURRENT_FLAT*(1+LOSS_TREND)^2 -> 1513.0872 | AR55: =MEDIAN(RET_FLOOR,BASE_RETENTION-ELAST_MARKET*(AQ55/AP55-1)-ELAST_INCREASE*MAX(AQ55/AM55-1,0),RET_CEIL) -> 0.39998341 | AS55: =MEDIAN(CONV_FLOOR,BASE_CONVERSION-ELAST_MARKET*(CURRENT_FLAT*(1+LOSS_TREND)^2/AP55-1),CONV_CEIL) -> 0.16426402 | AT55: =IF($J55=0,0,IF($J55=4,AH55*GRAD_CONTINUE,AH54)*AR55) -> 0 | AU55: =APPLICANTS_PER_YEAR*($H55/Segments!$AH$2)*AS55 -> 28.187705 | AV55: =AT55+AU55 -> 28.187705 | AW55: =IFERROR((AT55*AQ55+AU55*CURRENT_FLAT*(1+LOSS_TREND)^2)/AV55,AO55) -> 1513.0872 | AX55: =AT55*AQ55+AU55*CURRENT_FLAT*(1+LOSS_TREND)^2 -> 42650.455 | AY55: =AV55*AN55*(1+LAE_RATIO) -> 14809.081 | AZ55: =AT55*AQ55*(PREMIUM_TAX+OTHER_VARIABLE+COMMISSION_RN)+AU55*CURRENT_FLAT*(1+LOSS_TREND)^2*(PREMIUM_TAX+OTHER_VARIABLE+COMMISSION_NB)+AV55*FIXED_PER_POLICY+AU55*NB_ACQUISITION -> 10822.149
A56: =Segments!$A$36 -> Non-greek | B56: =Segments!$B$36 -> On campus | C56: =Segments!$C$36 -> No | D56: =Segments!$D$36 -> 2.0-3.0 | E56: =Segments!$E$36 -> Sophomore | F56: =Segments!$F$36 -> 1 | G56: =Segments!$G$36 -> Sophomore | H56: =Segments!$H$36 -> 131 | I56: =Segments!$Y$36 -> 437.65801 | J56: 1 | K56: =IF($J56=0,M56,CURRENT_FLAT) -> 1426.2298 | L56: =$I56*(1+LOSS_TREND)^0 -> 437.65801 | M56: =L56*GROSS_MULT+POLICY_FEE -> 753.33271 | N56: =M56^MARKET_RISK_WEIGHT*(CURRENT_FLAT*(1+LOSS_TREND)^0)^(1-MARKET_RISK_WEIGHT) -> 1036.545 | O56: =CURRENT_FLAT*(1+LOSS_TREND)^0 -> 1426.2298 | P56: =MEDIAN(RET_FLOOR,BASE_RETENTION-ELAST_MARKET*(O56/N56-1)-ELAST_INCREASE*MAX(O56/K56-1,0),RET_CEIL) -> 0.66202708 | Q56: =MEDIAN(CONV_FLOOR,BASE_CONVERSION-ELAST_MARKET*(CURRENT_FLAT*(1+LOSS_TREND)^0/N56-1),CONV_CEIL) -> 0.16202708 | R56: =IF($J56=0,0,IF($J56=4,$H56*GRAD_CONTINUE,$H55)*P56) -> 94.669873 | S56: =APPLICANTS_PER_YEAR*($H56/Segments!$AH$2)*Q56 -> 25.470657 | T56: =R56+S56 -> 120.14053 | U56: =IFERROR((R56*O56+S56*CURRENT_FLAT*(1+LOSS_TREND)^0)/T56,M56) -> 1426.2298 | V56: =R56*O56+S56*CURRENT_FLAT*(1+LOSS_TREND)^0 -> 171348 | W56: =T56*L56*(1+LAE_RATIO) -> 58890.121 | X56: =R56*O56*(PREMIUM_TAX+OTHER_VARIABLE+COMMISSION_RN)+S56*CURRENT_FLAT*(1+LOSS_TREND)^0*(PREMIUM_TAX+OTHER_VARIABLE+COMMISSION_NB)+T56*FIXED_PER_POLICY+S56*NB_ACQUISITION -> 36695.795 | Y56: =IF($J56=0,AA56,IF($J56=4,U56,U55)) -> 1426.2298 | Z56: =$I56*(1+LOSS_TREND)^1 -> 450.78775 | AA56: =Z56*GROSS_MULT+POLICY_FEE -> 774.68269 | AB56: =AA56^MARKET_RISK_WEIGHT*(CURRENT_FLAT*(1+LOSS_TREND)^1)^(1-MARKET_RISK_WEIGHT) -> 1066.781 | AC56: =CURRENT_FLAT*(1+LOSS_TREND)^1 -> 1469.0167 | AD56: =MEDIAN(RET_FLOOR,BASE_RETENTION-ELAST_MARKET*(AC56/AB56-1)-ELAST_INCREASE*MAX(AC56/Y56-1,0),RET_CEIL) -> 0.65247226 | AE56: =MEDIAN(CONV_FLOOR,BASE_CONVERSION-ELAST_MARKET*(CURRENT_FLAT*(1+LOSS_TREND)^1/AB56-1),CONV_CEIL) -> 0.16147226 | AF56: =IF($J56=0,0,IF($J56=4,T56*GRAD_CONTINUE,T55)*AD56) -> 18.512504 | AG56: =APPLICANTS_PER_YEAR*($H56/Segments!$AH$2)*AE56 -> 25.38344 | AH56: =AF56+AG56 -> 43.895944 | AI56: =IFERROR((AF56*AC56+AG56*CURRENT_FLAT*(1+LOSS_TREND)^1)/AH56,AA56) -> 1469.0167 | AJ56: =AF56*AC56+AG56*CURRENT_FLAT*(1+LOSS_TREND)^1 -> 64483.873 | AK56: =AH56*Z56*(1+LAE_RATIO) -> 22162.284 | AL56: =AF56*AC56*(PREMIUM_TAX+OTHER_VARIABLE+COMMISSION_RN)+AG56*CURRENT_FLAT*(1+LOSS_TREND)^1*(PREMIUM_TAX+OTHER_VARIABLE+COMMISSION_NB)+AH56*FIXED_PER_POLICY+AG56*NB_ACQUISITION -> 15005.061 | AM56: =IF($J56=0,AO56,IF($J56=4,AI56,AI55)) -> 1469.0167 | AN56: =$I56*(1+LOSS_TREND)^2 -> 464.31138 | AO56: =AN56*GROSS_MULT+POLICY_FEE -> 796.67317 | AP56: =AO56^MARKET_RISK_WEIGHT*(CURRENT_FLAT*(1+LOSS_TREND)^2)^(1-MARKET_RISK_WEIGHT) -> 1097.9235 | AQ56: =CURRENT_FLAT*(1+LOSS_TREND)^2 -> 1513.0872 | AR56: =MEDIAN(RET_FLOOR,BASE_RETENTION-ELAST_MARKET*(AQ56/AP56-1)-ELAST_INCREASE*MAX(AQ56/AM56-1,0),RET_CEIL) -> 0.65193232 | AS56: =MEDIAN(CONV_FLOOR,BASE_CONVERSION-ELAST_MARKET*(CURRENT_FLAT*(1+LOSS_TREND)^2/AP56-1),CONV_CEIL) -> 0.16093232 | AT56: =IF($J56=0,0,IF($J56=4,AH56*GRAD_CONTINUE,AH55)*AR56) -> 18.436009 | AU56: =APPLICANTS_PER_YEAR*($H56/Segments!$AH$2)*AS56 -> 25.29856 | AV56: =AT56+AU56 -> 43.734569 | AW56: =IFERROR((AT56*AQ56+AU56*CURRENT_FLAT*(1+LOSS_TREND)^2)/AV56,AO56) -> 1513.0872 | AX56: =AT56*AQ56+AU56*CURRENT_FLAT*(1+LOSS_TREND)^2 -> 66174.216 | AY56: =AV56*AN56*(1+LAE_RATIO) -> 22743.233 | AZ56: =AT56*AQ56*(PREMIUM_TAX+OTHER_VARIABLE+COMMISSION_RN)+AU56*CURRENT_FLAT*(1+LOSS_TREND)^2*(PREMIUM_TAX+OTHER_VARIABLE+COMMISSION_NB)+AV56*FIXED_PER_POLICY+AU56*NB_ACQUISITION -> 15353.845
A57: =Segments!$A$37 -> Non-greek | B57: =Segments!$B$37 -> On campus | C57: =Segments!$C$37 -> No | D57: =Segments!$D$37 -> 2.0-3.0 | E57: =Segments!$E$37 -> Junior | F57: =Segments!$F$37 -> 2 | G57: =Segments!$G$37 -> Base | H57: =Segments!$H$37 -> 129 | I57: =Segments!$Y$37 -> 523.1876 | J57: 2 | K57: =IF($J57=0,M57,CURRENT_FLAT) -> 1426.2298 | L57: =$I57*(1+LOSS_TREND)^0 -> 523.1876 | M57: =L57*GROSS_MULT+POLICY_FEE -> 892.41049 | N57: =M57^MARKET_RISK_WEIGHT*(CURRENT_FLAT*(1+LOSS_TREND)^0)^(1-MARKET_RISK_WEIGHT) -> 1128.1766 | O57: =CURRENT_FLAT*(1+LOSS_TREND)^0 -> 1426.2298 | P57: =MEDIAN(RET_FLOOR,BASE_RETENTION-ELAST_MARKET*(O57/N57-1)-ELAST_INCREASE*MAX(O57/K57-1,0),RET_CEIL) -> 0.7179049 | Q57: =MEDIAN(CONV_FLOOR,BASE_CONVERSION-ELAST_MARKET*(CURRENT_FLAT*(1+LOSS_TREND)^0/N57-1),CONV_CEIL) -> 0.2179049 | R57: =IF($J57=0,0,IF($J57=4,$H57*GRAD_CONTINUE,$H56)*P57) -> 94.045542 | S57: =APPLICANTS_PER_YEAR*($H57/Segments!$AH$2)*Q57 -> 33.731679 | T57: =R57+S57 -> 127.77722 | U57: =IFERROR((R57*O57+S57*CURRENT_FLAT*(1+LOSS_TREND)^0)/T57,M57) -> 1426.2298 | V57: =R57*O57+S57*CURRENT_FLAT*(1+LOSS_TREND)^0 -> 182239.68 | W57: =T57*L57*(1+LAE_RATIO) -> 74873.632 | X57: =R57*O57*(PREMIUM_TAX+OTHER_VARIABLE+COMMISSION_RN)+S57*CURRENT_FLAT*(1+LOSS_TREND)^0*(PREMIUM_TAX+OTHER_VARIABLE+COMMISSION_NB)+T57*FIXED_PER_POLICY+S57*NB_ACQUISITION -> 39525.955 | Y57: =IF($J57=0,AA57,IF($J57=4,U57,U56)) -> 1426.2298 | Z57: =$I57*(1+LOSS_TREND)^1 -> 538.88322 | AA57: =Z57*GROSS_MULT+POLICY_FEE -> 917.9328 | AB57: =AA57^MARKET_RISK_WEIGHT*(CURRENT_FLAT*(1+LOSS_TREND)^1)^(1-MARKET_RISK_WEIGHT) -> 1161.2315 | AC57: =CURRENT_FLAT*(1+LOSS_TREND)^1 -> 1469.0167 | AD57: =MEDIAN(RET_FLOOR,BASE_RETENTION-ELAST_MARKET*(AC57/AB57-1)-ELAST_INCREASE*MAX(AC57/Y57-1,0),RET_CEIL) -> 0.70847467 | AE57: =MEDIAN(CONV_FLOOR,BASE_CONVERSION-ELAST_MARKET*(CURRENT_FLAT*(1+LOSS_TREND)^1/AB57-1),CONV_CEIL) -> 0.21747467 | AF57: =IF($J57=0,0,IF($J57=4,T57*GRAD_CONTINUE,T56)*AD57) -> 85.116522 | AG57: =APPLICANTS_PER_YEAR*($H57/Segments!$AH$2)*AE57 -> 33.665079 | AH57: =AF57+AG57 -> 118.7816 | AI57: =IFERROR((AF57*AC57+AG57*CURRENT_FLAT*(1+LOSS_TREND)^1)/AH57,AA57) -> 1469.0167 | AJ57: =AF57*AC57+AG57*CURRENT_FLAT*(1+LOSS_TREND)^1 -> 174492.15 | AK57: =AH57*Z57*(1+LAE_RATIO) -> 71690.542 | AL57: =AF57*AC57*(PREMIUM_TAX+OTHER_VARIABLE+COMMISSION_RN)+AG57*CURRENT_FLAT*(1+LOSS_TREND)^1*(PREMIUM_TAX+OTHER_VARIABLE+COMMISSION_NB)+AH57*FIXED_PER_POLICY+AG57*NB_ACQUISITION -> 37927.185 | AM57: =IF($J57=0,AO57,IF($J57=4,AI57,AI56)) -> 1469.0167 | AN57: =$I57*(1+LOSS_TREND)^2 -> 555.04972 | AO57: =AN57*GROSS_MULT+POLICY_FEE -> 944.22078 | AP57: =AO57^MARKET_RISK_WEIGHT*(CURRENT_FLAT*(1+LOSS_TREND)^2)^(1-MARKET_RISK_WEIGHT) -> 1195.2775 | AQ57: =CURRENT_FLAT*(1+LOSS_TREND)^2 -> 1513.0872 | AR57: =MEDIAN(RET_FLOOR,BASE_RETENTION-ELAST_MARKET*(AQ57/AP57-1)-ELAST_INCREASE*MAX(AQ57/AM57-1,0),RET_CEIL) -> 0.70805613 | AS57: =MEDIAN(CONV_FLOOR,BASE_CONVERSION-ELAST_MARKET*(CURRENT_FLAT*(1+LOSS_TREND)^2/AP57-1),CONV_CEIL) -> 0.21705613 | AT57: =IF($J57=0,0,IF($J57=4,AH57*GRAD_CONTINUE,AH56)*AR57) -> 31.080792 | AU57: =APPLICANTS_PER_YEAR*($H57/Segments!$AH$2)*AS57 -> 33.600288 | AV57: =AT57+AU57 -> 64.68108 | AW57: =IFERROR((AT57*AQ57+AU57*CURRENT_FLAT*(1+LOSS_TREND)^2)/AV57,AO57) -> 1513.0872 | AX57: =AT57*AQ57+AU57*CURRENT_FLAT*(1+LOSS_TREND)^2 -> 97868.112 | AY57: =AV57*AN57*(1+LAE_RATIO) -> 40209.361 | AZ57: =AT57*AQ57*(PREMIUM_TAX+OTHER_VARIABLE+COMMISSION_RN)+AU57*CURRENT_FLAT*(1+LOSS_TREND)^2*(PREMIUM_TAX+OTHER_VARIABLE+COMMISSION_NB)+AV57*FIXED_PER_POLICY+AU57*NB_ACQUISITION -> 22410.108
A58: =Segments!$A$38 -> Non-greek | B58: =Segments!$B$38 -> On campus | C58: =Segments!$C$38 -> No | D58: =Segments!$D$38 -> 2.0-3.0 | E58: =Segments!$E$38 -> Senior | F58: =Segments!$F$38 -> 3 | G58: =Segments!$G$38 -> Base | H58: =Segments!$H$38 -> 152 | I58: =Segments!$Y$38 -> 489.01688 | J58: 3 | K58: =IF($J58=0,M58,CURRENT_FLAT) -> 1426.2298 | L58: =$I58*(1+LOSS_TREND)^0 -> 489.01688 | M58: =L58*GROSS_MULT+POLICY_FEE -> 836.84624 | N58: =M58^MARKET_RISK_WEIGHT*(CURRENT_FLAT*(1+LOSS_TREND)^0)^(1-MARKET_RISK_WEIGHT) -> 1092.4903 | O58: =CURRENT_FLAT*(1+LOSS_TREND)^0 -> 1426.2298 | P58: =MEDIAN(RET_FLOOR,BASE_RETENTION-ELAST_MARKET*(O58/N58-1)-ELAST_INCREASE*MAX(O58/K58-1,0),RET_CEIL) -> 0.69725746 | Q58: =MEDIAN(CONV_FLOOR,BASE_CONVERSION-ELAST_MARKET*(CURRENT_FLAT*(1+LOSS_TREND)^0/N58-1),CONV_CEIL) -> 0.19725746 | R58: =IF($J58=0,0,IF($J58=4,$H58*GRAD_CONTINUE,$H57)*P58) -> 89.946212 | S58: =APPLICANTS_PER_YEAR*($H58/Segments!$AH$2)*Q58 -> 35.97976 | T58: =R58+S58 -> 125.92597 | U58: =IFERROR((R58*O58+S58*CURRENT_FLAT*(1+LOSS_TREND)^0)/T58,M58) -> 1426.2298 | V58: =R58*O58+S58*CURRENT_FLAT*(1+LOSS_TREND)^0 -> 179599.37 | W58: =T58*L58*(1+LAE_RATIO) -> 68969.518 | X58: =R58*O58*(PREMIUM_TAX+OTHER_VARIABLE+COMMISSION_RN)+S58*CURRENT_FLAT*(1+LOSS_TREND)^0*(PREMIUM_TAX+OTHER_VARIABLE+COMMISSION_NB)+T58*FIXED_PER_POLICY+S58*NB_ACQUISITION -> 39158.334 | Y58: =IF($J58=0,AA58,IF($J58=4,U58,U57)) -> 1426.2298 | Z58: =$I58*(1+LOSS_TREND)^1 -> 503.68739 | AA58: =Z58*GROSS_MULT+POLICY_FEE -> 860.70163 | AB58: =AA58^MARKET_RISK_WEIGHT*(CURRENT_FLAT*(1+LOSS_TREND)^1)^(1-MARKET_RISK_WEIGHT) -> 1124.4488 | AC58: =CURRENT_FLAT*(1+LOSS_TREND)^1 -> 1469.0167 | AD58: =MEDIAN(RET_FLOOR,BASE_RETENTION-ELAST_MARKET*(AC58/AB58-1)-ELAST_INCREASE*MAX(AC58/Y58-1,0),RET_CEIL) -> 0.68778364 | AE58: =MEDIAN(CONV_FLOOR,BASE_CONVERSION-ELAST_MARKET*(CURRENT_FLAT*(1+LOSS_TREND)^1/AB58-1),CONV_CEIL) -> 0.19678364 | AF58: =IF($J58=0,0,IF($J58=4,T58*GRAD_CONTINUE,T57)*AD58) -> 87.883082 | AG58: =APPLICANTS_PER_YEAR*($H58/Segments!$AH$2)*AE58 -> 35.893336 | AH58: =AF58+AG58 -> 123.77642 | AI58: =IFERROR((AF58*AC58+AG58*CURRENT_FLAT*(1+LOSS_TREND)^1)/AH58,AA58) -> 1469.0167 | AJ58: =AF58*AC58+AG58*CURRENT_FLAT*(1+LOSS_TREND)^1 -> 181829.62 | AK58: =AH58*Z58*(1+LAE_RATIO) -> 69825.976 | AL58: =AF58*AC58*(PREMIUM_TAX+OTHER_VARIABLE+COMMISSION_RN)+AG58*CURRENT_FLAT*(1+LOSS_TREND)^1*(PREMIUM_TAX+OTHER_VARIABLE+COMMISSION_NB)+AH58*FIXED_PER_POLICY+AG58*NB_ACQUISITION -> 39584.137 | AM58: =IF($J58=0,AO58,IF($J58=4,AI58,AI57)) -> 1469.0167 | AN58: =$I58*(1+LOSS_TREND)^2 -> 518.79801 | AO58: =AN58*GROSS_MULT+POLICY_FEE -> 885.27268 | AP58: =AO58^MARKET_RISK_WEIGHT*(CURRENT_FLAT*(1+LOSS_TREND)^2)^(1-MARKET_RISK_WEIGHT) -> 1157.3654 | AQ58: =CURRENT_FLAT*(1+LOSS_TREND)^2 -> 1513.0872 | AR58: =MEDIAN(RET_FLOOR,BASE_RETENTION-ELAST_MARKET*(AQ58/AP58-1)-ELAST_INCREASE*MAX(AQ58/AM58-1,0),RET_CEIL) -> 0.68732263 | AS58: =MEDIAN(CONV_FLOOR,BASE_CONVERSION-ELAST_MARKET*(CURRENT_FLAT*(1+LOSS_TREND)^2/AP58-1),CONV_CEIL) -> 0.19632263 | AT58: =IF($J58=0,0,IF($J58=4,AH58*GRAD_CONTINUE,AH57)*AR58) -> 81.641283 | AU58: =APPLICANTS_PER_YEAR*($H58/Segments!$AH$2)*AS58 -> 35.809248 | AV58: =AT58+AU58 -> 117.45053 | AW58: =IFERROR((AT58*AQ58+AU58*CURRENT_FLAT*(1+LOSS_TREND)^2)/AV58,AO58) -> 1513.0872 | AX58: =AT58*AQ58+AU58*CURRENT_FLAT*(1+LOSS_TREND)^2 -> 177712.89 | AY58: =AV58*AN58*(1+LAE_RATIO) -> 68245.074 | AZ58: =AT58*AQ58*(PREMIUM_TAX+OTHER_VARIABLE+COMMISSION_RN)+AU58*CURRENT_FLAT*(1+LOSS_TREND)^2*(PREMIUM_TAX+OTHER_VARIABLE+COMMISSION_NB)+AV58*FIXED_PER_POLICY+AU58*NB_ACQUISITION -> 38728.366
A59: =Segments!$A$39 -> Non-greek | B59: =Segments!$B$39 -> On campus | C59: =Segments!$C$39 -> No | D59: =Segments!$D$39 -> 2.0-3.0 | E59: =Segments!$E$39 -> Grad student | F59: =Segments!$F$39 -> 3 | G59: =Segments!$G$39 -> Grad | H59: =Segments!$H$39 -> 61 | I59: =Segments!$Y$39 -> 582.26283 | J59: 4 | K59: =IF($J59=0,M59,CURRENT_FLAT) -> 1426.2298 | L59: =$I59*(1+LOSS_TREND)^0 -> 582.26283 | M59: =L59*GROSS_MULT+POLICY_FEE -> 988.47142 | N59: =M59^MARKET_RISK_WEIGHT*(CURRENT_FLAT*(1+LOSS_TREND)^0)^(1-MARKET_RISK_WEIGHT) -> 1187.3447 | O59: =CURRENT_FLAT*(1+LOSS_TREND)^0 -> 1426.2298 | P59: =MEDIAN(RET_FLOOR,BASE_RETENTION-ELAST_MARKET*(O59/N59-1)-ELAST_INCREASE*MAX(O59/K59-1,0),RET_CEIL) -> 0.74940364 | Q59: =MEDIAN(CONV_FLOOR,BASE_CONVERSION-ELAST_MARKET*(CURRENT_FLAT*(1+LOSS_TREND)^0/N59-1),CONV_CEIL) -> 0.24940364 | R59: =IF($J59=0,0,IF($J59=4,$H59*GRAD_CONTINUE,$H58)*P59) -> 22.856811 | S59: =APPLICANTS_PER_YEAR*($H59/Segments!$AH$2)*Q59 -> 18.256347 | T59: =R59+S59 -> 41.113158 | U59: =IFERROR((R59*O59+S59*CURRENT_FLAT*(1+LOSS_TREND)^0)/T59,M59) -> 1426.2298 | V59: =R59*O59+S59*CURRENT_FLAT*(1+LOSS_TREND)^0 -> 58636.81 | W59: =T59*L59*(1+LAE_RATIO) -> 26811.303 | X59: =R59*O59*(PREMIUM_TAX+OTHER_VARIABLE+COMMISSION_RN)+S59*CURRENT_FLAT*(1+LOSS_TREND)^0*(PREMIUM_TAX+OTHER_VARIABLE+COMMISSION_NB)+T59*FIXED_PER_POLICY+S59*NB_ACQUISITION -> 13272.35 | Y59: =IF($J59=0,AA59,IF($J59=4,U59,U58)) -> 1426.2298 | Z59: =$I59*(1+LOSS_TREND)^1 -> 599.73072 | AA59: =Z59*GROSS_MULT+POLICY_FEE -> 1016.8756 | AB59: =AA59^MARKET_RISK_WEIGHT*(CURRENT_FLAT*(1+LOSS_TREND)^1)^(1-MARKET_RISK_WEIGHT) -> 1222.214 | AC59: =CURRENT_FLAT*(1+LOSS_TREND)^1 -> 1469.0167 | AD59: =MEDIAN(RET_FLOOR,BASE_RETENTION-ELAST_MARKET*(AC59/AB59-1)-ELAST_INCREASE*MAX(AC59/Y59-1,0),RET_CEIL) -> 0.74003461 | AE59: =MEDIAN(CONV_FLOOR,BASE_CONVERSION-ELAST_MARKET*(CURRENT_FLAT*(1+LOSS_TREND)^1/AB59-1),CONV_CEIL) -> 0.24903461 | AF59: =IF($J59=0,0,IF($J59=4,T59*GRAD_CONTINUE,T58)*AD59) -> 15.21258 | AG59: =APPLICANTS_PER_YEAR*($H59/Segments!$AH$2)*AE59 -> 18.229334 | AH59: =AF59+AG59 -> 33.441913 | AI59: =IFERROR((AF59*AC59+AG59*CURRENT_FLAT*(1+LOSS_TREND)^1)/AH59,AA59) -> 1469.0167 | AJ59: =AF59*AC59+AG59*CURRENT_FLAT*(1+LOSS_TREND)^1 -> 49126.728 | AK59: =AH59*Z59*(1+LAE_RATIO) -> 22462.88 | AL59: =AF59*AC59*(PREMIUM_TAX+OTHER_VARIABLE+COMMISSION_RN)+AG59*CURRENT_FLAT*(1+LOSS_TREND)^1*(PREMIUM_TAX+OTHER_VARIABLE+COMMISSION_NB)+AH59*FIXED_PER_POLICY+AG59*NB_ACQUISITION -> 11346.795 | AM59: =IF($J59=0,AO59,IF($J59=4,AI59,AI58)) -> 1469.0167 | AN59: =$I59*(1+LOSS_TREND)^2 -> 617.72264 | AO59: =AN59*GROSS_MULT+POLICY_FEE -> 1046.1318 | AP59: =AO59^MARKET_RISK_WEIGHT*(CURRENT_FLAT*(1+LOSS_TREND)^2)^(1-MARKET_RISK_WEIGHT) -> 1258.129 | AQ59: =CURRENT_FLAT*(1+LOSS_TREND)^2 -> 1513.0872 | AR59: =MEDIAN(RET_FLOOR,BASE_RETENTION-ELAST_MARKET*(AQ59/AP59-1)-ELAST_INCREASE*MAX(AQ59/AM59-1,0),RET_CEIL) -> 0.73967568 | AS59: =MEDIAN(CONV_FLOOR,BASE_CONVERSION-ELAST_MARKET*(CURRENT_FLAT*(1+LOSS_TREND)^2/AP59-1),CONV_CEIL) -> 0.24867568 | AT59: =IF($J59=0,0,IF($J59=4,AH59*GRAD_CONTINUE,AH58)*AR59) -> 12.368085 | AU59: =APPLICANTS_PER_YEAR*($H59/Segments!$AH$2)*AS59 -> 18.20306 | AV59: =AT59+AU59 -> 30.571145 | AW59: =IFERROR((AT59*AQ59+AU59*CURRENT_FLAT*(1+LOSS_TREND)^2)/AV59,AO59) -> 1513.0872 | AX59: =AT59*AQ59+AU59*CURRENT_FLAT*(1+LOSS_TREND)^2 -> 46256.807 | AY59: =AV59*AN59*(1+LAE_RATIO) -> 21150.627 | AZ59: =AT59*AQ59*(PREMIUM_TAX+OTHER_VARIABLE+COMMISSION_RN)+AU59*CURRENT_FLAT*(1+LOSS_TREND)^2*(PREMIUM_TAX+OTHER_VARIABLE+COMMISSION_NB)+AV59*FIXED_PER_POLICY+AU59*NB_ACQUISITION -> 10773.034
A60: =Segments!$A$40 -> Non-greek | B60: =Segments!$B$40 -> On campus | C60: =Segments!$C$40 -> No | D60: =Segments!$D$40 -> 3.0+ | E60: =Segments!$E$40 -> Freshman | F60: =Segments!$F$40 -> 1 | G60: =Segments!$G$40 -> Base | H60: =Segments!$H$40 -> 85 | I60: =Segments!$Y$40 -> 387.57114 | J60: 0 | K60: =IF($J60=0,M60,CURRENT_FLAT) -> 671.88755 | L60: =$I60*(1+LOSS_TREND)^0 -> 387.57114 | M60: =L60*GROSS_MULT+POLICY_FEE -> 671.88755 | N60: =M60^MARKET_RISK_WEIGHT*(CURRENT_FLAT*(1+LOSS_TREND)^0)^(1-MARKET_RISK_WEIGHT) -> 978.91064 | O60: =CURRENT_FLAT*(1+LOSS_TREND)^0 -> 1426.2298 | P60: =MEDIAN(RET_FLOOR,BASE_RETENTION-ELAST_MARKET*(O60/N60-1)-ELAST_INCREASE*MAX(O60/K60-1,0),RET_CEIL) -> 0.3 | Q60: =MEDIAN(CONV_FLOOR,BASE_CONVERSION-ELAST_MARKET*(CURRENT_FLAT*(1+LOSS_TREND)^0/N60-1),CONV_CEIL) -> 0.12152197 | R60: =IF($J60=0,0,IF($J60=4,$H60*GRAD_CONTINUE,$H59)*P60) -> 0 | S60: =APPLICANTS_PER_YEAR*($H60/Segments!$AH$2)*Q60 -> 12.395241 | T60: =R60+S60 -> 12.395241 | U60: =IFERROR((R60*O60+S60*CURRENT_FLAT*(1+LOSS_TREND)^0)/T60,M60) -> 1426.2298 | V60: =R60*O60+S60*CURRENT_FLAT*(1+LOSS_TREND)^0 -> 17678.462 | W60: =T60*L60*(1+LAE_RATIO) -> 5380.5223 | X60: =R60*O60*(PREMIUM_TAX+OTHER_VARIABLE+COMMISSION_RN)+S60*CURRENT_FLAT*(1+LOSS_TREND)^0*(PREMIUM_TAX+OTHER_VARIABLE+COMMISSION_NB)+T60*FIXED_PER_POLICY+S60*NB_ACQUISITION -> 4517.7614 | Y60: =IF($J60=0,AA60,IF($J60=4,U60,U59)) -> 690.79418 | Z60: =$I60*(1+LOSS_TREND)^1 -> 399.19827 | AA60: =Z60*GROSS_MULT+POLICY_FEE -> 690.79418 | AB60: =AA60^MARKET_RISK_WEIGHT*(CURRENT_FLAT*(1+LOSS_TREND)^1)^(1-MARKET_RISK_WEIGHT) -> 1007.3669 | AC60: =CURRENT_FLAT*(1+LOSS_TREND)^1 -> 1469.0167 | AD60: =MEDIAN(RET_FLOOR,BASE_RETENTION-ELAST_MARKET*(AC60/AB60-1)-ELAST_INCREASE*MAX(AC60/Y60-1,0),RET_CEIL) -> 0.3 | AE60: =MEDIAN(CONV_FLOOR,BASE_CONVERSION-ELAST_MARKET*(CURRENT_FLAT*(1+LOSS_TREND)^1/AB60-1),CONV_CEIL) -> 0.12086318 | AF60: =IF($J60=0,0,IF($J60=4,T60*GRAD_CONTINUE,T59)*AD60) -> 0 | AG60: =APPLICANTS_PER_YEAR*($H60/Segments!$AH$2)*AE60 -> 12.328044 | AH60: =AF60+AG60 -> 12.328044 | AI60: =IFERROR((AF60*AC60+AG60*CURRENT_FLAT*(1+LOSS_TREND)^1)/AH60,AA60) -> 1469.0167 | AJ60: =AF60*AC60+AG60*CURRENT_FLAT*(1+LOSS_TREND)^1 -> 18110.102 | AK60: =AH60*Z60*(1+LAE_RATIO) -> 5511.894 | AL60: =AF60*AC60*(PREMIUM_TAX+OTHER_VARIABLE+COMMISSION_RN)+AG60*CURRENT_FLAT*(1+LOSS_TREND)^1*(PREMIUM_TAX+OTHER_VARIABLE+COMMISSION_NB)+AH60*FIXED_PER_POLICY+AG60*NB_ACQUISITION -> 4611.4249 | AM60: =IF($J60=0,AO60,IF($J60=4,AI60,AI59)) -> 710.268 | AN60: =$I60*(1+LOSS_TREND)^2 -> 411.17422 | AO60: =AN60*GROSS_MULT+POLICY_FEE -> 710.268 | AP60: =AO60^MARKET_RISK_WEIGHT*(CURRENT_FLAT*(1+LOSS_TREND)^2)^(1-MARKET_RISK_WEIGHT) -> 1036.6761 | AQ60: =CURRENT_FLAT*(1+LOSS_TREND)^2 -> 1513.0872 | AR60: =MEDIAN(RET_FLOOR,BASE_RETENTION-ELAST_MARKET*(AQ60/AP60-1)-ELAST_INCREASE*MAX(AQ60/AM60-1,0),RET_CEIL) -> 0.3 | AS60: =MEDIAN(CONV_FLOOR,BASE_CONVERSION-ELAST_MARKET*(CURRENT_FLAT*(1+LOSS_TREND)^2/AP60-1),CONV_CEIL) -> 0.12022186 | AT60: =IF($J60=0,0,IF($J60=4,AH60*GRAD_CONTINUE,AH59)*AR60) -> 0 | AU60: =APPLICANTS_PER_YEAR*($H60/Segments!$AH$2)*AS60 -> 12.262629 | AV60: =AT60+AU60 -> 12.262629 | AW60: =IFERROR((AT60*AQ60+AU60*CURRENT_FLAT*(1+LOSS_TREND)^2)/AV60,AO60) -> 1513.0872 | AX60: =AT60*AQ60+AU60*CURRENT_FLAT*(1+LOSS_TREND)^2 -> 18554.427 | AY60: =AV60*AN60*(1+LAE_RATIO) -> 5647.1263 | AZ60: =AT60*AQ60*(PREMIUM_TAX+OTHER_VARIABLE+COMMISSION_RN)+AU60*CURRENT_FLAT*(1+LOSS_TREND)^2*(PREMIUM_TAX+OTHER_VARIABLE+COMMISSION_NB)+AV60*FIXED_PER_POLICY+AU60*NB_ACQUISITION -> 4708.01
